Workbook
Name AfterTaxA: Input!$C$5
Name AfterTaxB: Input!$C$8
Name BaseRepayment: Input!$C$41
Name CapIncrement: Input!$C$32
Name CapIndexYears: Input!$C$33
Name CarryFwdStartA: Input!$C$25
Name CarryFwdStartB: Input!$C$26
Name ConcessCap: Input!$C$23
Name CurrentAgeA: Input!$C$11
Name CurrentAgeB: Input!$C$12
Name Div293Thresh: Input!$C$29
Name ExtraRepay: Input!$C$44
Name FreqA: Input!$C$4
Name FreqB: Input!$C$7
Name IncA: Input!$C$3
Name IncB: Input!$C$6
Name Inflation: Input!$C$13
Name LoanAmount: Input!$C$37
Name LoanRate: Input!$C$38
Name LoanStart: Input!$C$40
Name LoanTerm: Input!$C$39
Name MedicareRate: Input!$C$20
Name MRate: _xlfn.LAMBDA(_xlpm.inc, _xlfn.LET( _xlpm.brackets, PersonaB!TaxBracket, _xlpm.rate, _xlfn.XLOOKUP(_xlpm.inc, INDEX(_xlpm.brackets,0,1), INDEX(_xlpm.brackets,0,3),,-1), _xlpm.rate+0.02))
Name NetInvLoss: Input!$C$30
Name OffsetStart: Input!$C$43
Name PersonATaxPayable: Input!$C$9
Name PersonBTaxPayable: Input!$C$10
Name PPY: Offset!$V$3
Name PPY_Loan: Loan!$AY$2
Name PPYA: PersonaA!$W$3
Name PPYB: PersonaB!$W$3
Name ProjYears: Input!$C$15
Name ProjYearsA: Input!$C$14
Name ProjYearsB: Input!$C$15
Name RetirementAgeA: Input!$C$17
Name RetirementAgeB: Input!$C$17
Name SGRate: Input!$C$24
Name SpousalTransfer: Input!$C$50
Name StartYear: Input!$C$16
Name StdPayment: Loan!$AY$4
Name SuperBalStartA: Input!$C$27
Name SuperBalStartB: Input!$C$28
Name SuperReturn: Input!$C$31
Name SuperTaxRate: Input!$C$34
Name TaxBracket: TaxBracketsOrig[]
Name TaxBracket: TaxBracketsOrig[]
Name TaxBracket: TaxBracketsOrig[]
Name TotalPeriods_Loan: Loan!$AY$3
Name TotalPeriodsA: PersonaA!$W$4
Name TotalPeriodsB: PersonaB!$W$4
Name TotalPeriodsB: PersonaB!$W$4
Name TotalPeriodsOffset: Offset!$V$4
Name TransferDir: Input!$C$51

Sheet README
A1: SUPERSMART MORTGAGE STRATEGY MODEL 2.0
A2: README — Model Guide & Methodology
B4: ① PROJECT OVERVIEW | D4: ② HOW THE STRATEGY WORKS
B5: This model implements an Australian tax-optimised mortgage repayment strategy ("SuperSmart") that coordinates salary sacrifice to superannuation, offset account accumulation, and annual sweeps to accelerate mortgage payoff while maximising lifetime tax savings. | D5: The SuperSmart strategy works in three coordinated stages each financial year:
B6: Client Requirements Met: | D6: Step 1 — Salary Sacrifice to Super (Tax Reduction)
B7: ✅ Dual-persona tax modelling (Person A & B with different incomes, ages, retirement horizons) | D7: Each persona redirects pre-tax income into superannuation up to their allowable concessional cap (including carry-forward from unused prior years). This reduces taxable income from the marginal rate (up to 47% incl. Medicare) to the 15% super contributions tax — saving up to 32 cents per dollar contributed.
B8: ✅ Three-scenario mortgage comparison (No Strategy / Extra Repayments / SuperSmart with Offset)
B9: ✅ Carry-forward concessional cap utilisation with 5-year rolling tracker and spousal transfers | D9: Step 2 — Offset Account Accumulation (Interest Reduction)
B10: ✅ Division 293 high-earner surcharge modelling and Medicare levy integration | D10: The tax-saved funds are deposited into a mortgage offset account each pay period. While sitting in offset, the balance directly reduces the effective mortgage principal that accrues interest. For example, a $400K offset against a $1.8M loan means interest accrues on $1.4M only.
B11: ✅ Monthly-granularity offset account with annual sweep-to-mortgage mechanism
B12: ✅ Inflation-adjusted projections with dynamic SG rate and concessional cap indexation | D12: Step 3 — Annual Sweep to Mortgage (Principal Acceleration)
B13: ✅ 28 advanced DAX measures with Power BI-ready formulas for portfolio dashboarding | D13: At the end of each financial year, the accumulated offset balance is swept as a lump-sum extra repayment against the loan principal. This permanently reduces the outstanding balance, creating a compounding effect: each year's sweep means the following year's interest is lower, accelerating payoff.
B14: ✅ Executive dashboard with KPI scorecards, 6 charts, and conditional-formatted summary
B15: ③ SHEET-BY-SHEET GUIDE | D15: ④ DATA FLOW & FORMULA CHAIN
B16: Navigate the model using this flow: Input → Engine Sheets → Summary → Dashboard | D16: Every output is formula-driven. No hardcoded results. Change any input and all 11 sheets recalculate.
B17: 📘 Dashboard (Start Here) | D17: Layer 1: Input Parameters
B18: Executive summary with 4 KPI scorecards (Tax Saved, Interest Saved, Super Wealth, ROI) and 6 visualisations. All values are formula-linked — changes to Input flow through automatically. | D18: Input sheet → Named ranges (IncA, IncB, LoanRate, LoanAmount, etc.) feed all downstream sheets via absolute references.
B19: 📊 Measures | D19: Layer 2: Tax Engine
B20: 28 advanced KPIs across 4 categories: Strategy Efficiency, Mortgage Acceleration, Super & Wealth, Risk & Sensitivity. Each row has the computed value, plain-English description, and a copy-pasteable Power BI DAX measure. | D20: Tax Helper calculates marginal rates and tax payable → feeds PersonaA/B with each persona's marginal rate and the base pre-tax contribution amount per period.
B21: ⚙️ Input (Client Configuration) | D21: Layer 3: Contribution Engines
B22: All client-specific parameters: incomes, ages, super balances, carry-forward, mortgage terms, SG rate, Div 293 threshold, inflation. Blue text = change per client. Yellow = system assumptions. Green = formula-derived (do not edit). The Live Model Preview panel on the right shows real-time impacts. | D22: PersonaA/B compute monthly salary sacrifice amounts → tax saved per period → deposits to Offset. YearlyParamsA/B track annual carry-forward, SG, Div 293, and cap indexation.
B23: 💰 Tax Helper | D23: Layer 4: Mortgage & Offset
B24: Australian marginal tax table with Medicare levy. Calculates tax payable with and without the strategy for both personas. Produces the 'Year 1 Tax Saved' and 'Lifetime Tax Saved' headline figures. Uses the ATO 2024–25 tax brackets. | D24: Offset accumulates monthly deposits → reduces effective balance in Loan sheet → annual sweep resets offset to zero and applies lump sum to principal. Loan runs 3 parallel amortisation schedules.
B25: 👤 PersonaA / PersonaB (Contribution Engines) | D25: Layer 5: Aggregation & Output
B26: Monthly-granularity salary sacrifice calculators for each persona. Tracks: base pre-tax contribution, carry-forward allowance, actual contribution, tax saved per period, cumulative YTD totals. Handles the carry-forward burn sequence and spousal transfer logic. | D26: YearlySummary aggregates all engines into 34-column yearly table → Measures derives 28 KPIs from YearlySummary → Dashboard visualises the headline outputs.
... B34: The model's core output table — one row per projection year with 34 columns covering: contributions, tax saved, cumulative tax saved, super balances, loan balances (all 3 scenarios), interest saved, sweep amounts, offset peak, employer SG, carry-forward remaining, Div 293 tax, and savings rates. This sheet feeds the Dashboard and Measures. | D34: • Offset sweep: Annual frequency at end of financial year (June 30).
B35: ⑥ QUICK-START: HOW TO USE
B36: Step 1 — Enter Client Details
B37: Go to the Input sheet. Update the blue-text cells in sections ①–⑤: gross incomes, ages, super balances, carry-forward balances, loan amount, interest rate, and loan term. Leave green-text (formula) cells untouched.
B39: Step 2 — Verify Tax Calculation
B40: Check the Tax Helper sheet — confirm the marginal rates and tax payable figures match the client's latest tax assessment. The 'WITH SuperSmart' section should show the reduced taxable income after salary sacrifice.
B42: Step 3 — Review the Dashboard
B43: Navigate to Dashboard for the executive summary. The 4 KPI cards show headline metrics. Scroll down for the loan trajectory chart (3 scenarios), cumulative tax saved, super growth, and contribution breakdown.
B45: Step 4 — Deep-Dive with Measures
B46: The Measures sheet provides 28 KPIs with descriptions. Use these to answer client questions: 'What's my break-even super return?' (B35), 'How much risk is front-loaded in Year 1?' (B39), 'What's the real benefit after inflation?' (B37).
B48: Step 5 — Scenario Analysis
B49: Adjust Input parameters to test scenarios: change the interest rate (C38), super return (C31), or inflation rate (C13) and watch all sheets recalculate. Compare the Dashboard before/after to quantify the impact.
B51: Step 6 — Export to Power BI (Optional)
B52: Column D of the Measures sheet contains valid Power BI DAX measures. To use: (1) Import this workbook into Power BI via Get Data > Excel, (2) Create relationships between Input, YearlySummary, and Loan tables, (3) Copy each DAX formula from column D into New Measure in Power BI Desktop.

Sheet Input
B2: ① Personal & Income | E2: 📋 INPUT GUIDE
B3: Annual Gross Income - Person A | C3: 145000 | D3: =IF(C3>=250000,"⚠ Div293","") | E3: Blue text | F3: Client-specific (change per client)
B4: Pay Frequency - Person A | C4: Monthly | E4: Yellow cells | F4: System assumptions (rarely changed)
B5: Desired After-Tax Contribution - Person A | C5: 7000 | E5: Green text | F5: Calculated (formula-derived)
B6: Annual Gross Income - Person B | C6: 230000 | D6: =IF(C6>=250000,"⚠ Div293","")
B7: Pay Frequency - Person B | C7: Monthly
B8: Desired After-Tax Contribution - Person B | C8: 5000
B9: Person A Tax Payable | C9: ='Tax Helper'!C33 -> 37620
B10: Person B Tax Payable | C10: ='Tax Helper'!D33 -> 73970
B11: Current Age - Person A | C11: 53 | E11: LIVE MODEL PREVIEW
B12: Current Age - Person B | C12: 50 | E12: Tax & Income
B13: Inflation Rate (annual) | C13: 0.025 | E13: Combined Gross Income | F13: =IncA+IncB -> 375000
B14: Projection Years (to Retirement) A | C14: =RetirementAgeA-CurrentAgeA -> 12 | E14: Effective Tax Rate (no strategy) | F14: ='Tax Helper'!E35 -> 0.29757333
B15: Projection Years (to Retirement) B | C15: =RetirementAgeB-CurrentAgeB -> 15 | E15: Lifetime Tax Payable (no strategy) | F15: ='Tax Helper'!E53 -> 1979490
B16: Start Date (enter as date e.g. 1/07/2027) | C16: 46388 | E16: Year 1 Tax Saved | F16: ='Tax Helper'!E46 -> 77750
B17: Retirement Age Person | C17: 65 | E17: Lifetime Tax Saved | F17: ='Tax Helper'!E47 -> 254263.08
B18: Total Lifetime tax payable | C18: ='Tax Helper'!E53 -> 1979490 | D18: =IF(C17>67,"⚠ Past preservation","")
B19: ② Medicare | E19: Monthly Repayment | F19: =StdPayment -> 27061.315
B20: Medicare Rate | C20: 0.02 | E20: Extra Repay (converted) | F20: =IF(C42=0,0,C42*52/PPY_Loan) -> 650
E21: Payoff (Scenario A) | F21: =IF(ISNUMBER(Loan!AR8), ROUND(Loan!AR8,1)&" yrs", ">"&ProjYears&" yrs") -> 12.1 yrs
B22: ③ Superannuation Parameters | E22: Payoff (SuperSmart) | F22: =IF(ISNUMBER(Loan!AV8), ROUND(Loan!AV8,1)&" yrs", ">"&ProjYears&" yrs") -> 11.8 yrs
B23: Concessional contribution cap (including SG) | C23: 32500 | E23: Interest Saved | F23: ='Tax Helper'!E49 -> 30271.925
B24: SG rate | C24: 0.12
B25: Carry-Forward Balance - Person A | C25: 70000 | E25: Super & Strategy
B26: Carry-Forward Balance - Person B | C26: 120000 | E26: Yr 1 Contribution (combined) | F26: =YearlySummary!E2 -> 210000
B27: Super Balance - Person A (for carry-forward eligibility) | C27: 180000 | E27: Combined Benefit (lifetime) | F27: ='Tax Helper'!E50 -> 560308.13
B28: Super Balance - Person B (for carry-forward eligibility) | C28: 200000 | D28: =IF(C27>=500000,"⚠ No carry-fwd","")
B29: Division 293 threshold | C29: 250000 | D29: =IF(C28>=500000,"⚠ No carry-fwd","")
B30: Net Investment Losses | C30: 0
B31: Assumed super investment return p.a. | C31: 0.07
B32: Indexation increment for cap ($2,500 every 2 years) | C32: 2500
B33: Years between cap indexation | C33: 2
B34: Super contributions tax rate (inside fund) | C34: 0.15
B36: ④ Mortgage Parameters
B37: Loan Amount | C37: 2500000
B38: Annual Interest Rate | C38: 0.08
B39: Loan Term(Years) | C39: 12
B40: Start Date | C40: =StartYear -> 46388
B41: Base Repayment | C41: 8000
B42: Extra Repayment (weekly equivalent, optional) | C42: 150
B43: Opening Offset Account Balance | C43: 0
B44: Extra Repayment per Period ▸ auto-converted | C44: =IF(C42=0, 0, C42*52/PPY_Loan) -> 650
B45: Expected Minimum Contribution
B46: Per Period — Person A | C46: =IFERROR((StdPayment/2)*PPY_Loan/_xlfn.XLOOKUP(C4,FreqLookup[Frequency],FreqLookup[PeriodsPerYear]),0) -> 13530.657
B47: Per Period — Person B | C47: =IFERROR((StdPayment/2)*PPY_Loan/_xlfn.XLOOKUP(C7,FreqLookup[Frequency],FreqLookup[PeriodsPerYear]),0) -> 13530.657
B49: ⑤ Spousal Transfer
B50: Allow Spousal Transfer of Excess Contributions? | C50: Yes
B51: If Yes, Transfer Excess from Person A to B? | C51: Yes
B56: Frequency Lookup Table
B57: Frequency | C57: PeriodsPerYear
B58: Weekly | C58: 52
B59: Monthly | C59: 12 | F59: Yes
B60: Fortnightly | C60: 26 | F60: No
B138: | Frequency Lookup | 47‑52

Sheet Tax Helper
G1: {=TaxPayable(F1)} -> 0
B2: Medicare | C2: =MedicareRate -> 0.02 | F2: {=TaxPayable(280000)+TaxPayable(287000)+TaxPayable(294175)+TaxPayable(301529.375)+TaxPayable(309067.609375)+TaxPayable(316794.299609375)+TaxPayable(324714.157099609)+TaxPayable(332832.0110271)+TaxPayable(341152.811302777)+TaxPayable(349681.631585346)+TaxPayable(358423.67237498)+TaxPayable(367384.264184354)+TaxPayable(376568.870788963)+TaxPayable(385983.092558687)+TaxPayable(395632.669872654)+TaxPayable(405523.486619471)+TaxPayable(415661.573784958)} -> 2165588.5 | G2: {=TaxPayable(F17)} -> 0
B3: Income | C3: =IncA -> 145000
B5: Tax Table
B6: Lower Limit | C6: Upper Limit | D6: Rate | E6: Adjusted Rate(Medicare Inc)
B7: 0 | C7: 18200 | D7: 0 | E7: =D7+0.02 -> 0.02
B8: =C7+1 -> 18201 | C8: 45000 | D8: 0.15 | E8: =D8+0.02 -> 0.17
B9: =C8+1 -> 45001 | C9: 135000 | D9: 0.3 | E9: =D9+0.02 -> 0.32
B10: =C9+1 -> 135001 | C10: 190000 | D10: 0.37 | E10: =D10+0.02 -> 0.39
B11: =C10+1 -> 190001 | C11: 99999999 | D11: 0.45 | E11: =D11+0.02 -> 0.47
B13: Adjusted Tax Table
B14: Lower Limit | C14: Upper Limit | D14: Rate
B15: 0 | C15: 18200 | D15: 0
B16: =C15 -> 18200 | C16: 45000 | D16: 0.15
B17: =C16 -> 45000 | C17: 135000 | D17: 0.3
B18: =C17 -> 135000 | C18: 190000 | D18: 0.37
B19: =C18 -> 190000 | C19: 99999999 | D19: 0.45
B22: Marginal Tax Rate | C22: {=MRate($C$3)} -> 0.39
B23: Tax payable | C23: {=TaxPayable($C$3)} -> 37620
B25: Tax Comparison: Without vs With SuperSmart
C27: Person A | D27: Person B | E27: Combined
B28: WITHOUT SuperSmart (Current Position)
B29: Annual Gross Income | C29: =IncA -> 145000 | D29: =IncB -> 230000 | E29: =C29+D29 -> 375000
B30: Marginal Tax Rate (incl. Medicare) | C30: {=MRate(IncA)} -> 0.39 | D30: {=MRate(IncB)} -> 0.47
B31: Income Tax Payable (excl. Medicare) | C31: {=TaxPayable(IncA)-IncA*MedicareRate} -> 34720 | D31: {=TaxPayable(IncB)-IncB*MedicareRate} -> 69370 | E31: =C31+D31 -> 104090
B32: Medicare Levy (2%) | C32: =IncA*MedicareRate -> 2900 | D32: =IncB*MedicareRate -> 4600 | E32: =C32+D32 -> 7500
B33: Total Tax Payable | C33: {=TaxPayable(IncA)} -> 37620 | D33: {=TaxPayable(IncB)} -> 73970 | E33: =C33+D33 -> 111590
B34: After-Tax Income | C34: =IncA-C33 -> 107380 | D34: =IncB-D33 -> 156030 | E34: =C34+D34 -> 263410
B35: Effective Tax Rate | C35: =C33/IncA -> 0.25944828 | D35: =D33/IncB -> 0.3216087 | E35: =E33/E29 -> 0.29757333
B37: WITH SuperSmart (Year 1)
B38: Annual Gross Income | C38: =IncA -> 145000 | D38: =IncB -> 230000 | E38: =C38+D38 -> 375000
B39: Year 1 Personal Super Contribution | C39: =IFERROR(_xlfn.XLOOKUP(YEAR(StartYear), YearlyParamsA!A:A, YearlyParamsA!AA:AA, 0), 0) -> 85100 | D39: =IFERROR(_xlfn.XLOOKUP(YEAR(StartYear), YearlyParamsB!A:A, YearlyParamsB!AB:AB, 0), 0) -> 124900 | E39: =C39+D39 -> 210000
B40: Reduced Taxable Income | C40: =C38-C39 -> 59900 | D40: =D38-D39 -> 105100 | E40: =C40+D40 -> 165000
B41: Total Tax Payable (on reduced income) | C41: {=TaxPayable(C40)} -> 9688 | D41: {=TaxPayable(D40)} -> 24152 | E41: =C41+D41 -> 33840
B42: After-Tax Income (before super contribution) | C42: =C40-C41 -> 50212 | D42: =D40-D41 -> 80948 | E42: =C42+D42 -> 131160
B43: Effective Tax Rate | C43: =IF(C38=0,0,C41/C38) -> 0.066813793 | D43: =IF(D38=0,0,D41/D38) -> 0.1050087 | E43: =IF(E38=0,0,E41/E38) -> 0.09024
B45: TAX SAVINGS (Year 1)
B46: Tax Savings (Year 1) | C46: =C33-C41 -> 27932 | D46: =D33-D41 -> 49818 | E46: =E33-E41 -> 77750
B47: Lifetime Super Balance | C47: =IFERROR(_xlfn.XLOOKUP(YEAR(StartYear)+ProjYearsA-1, PersonaA!B:B, PersonaA!S:S,,,-1), 0) -> 122649.62 | D47: =IFERROR(_xlfn.XLOOKUP(YEAR(StartYear)+ProjYearsB-1, PersonaB!B:B, PersonaB!S:S,,,-1), 0) -> 131613.46 | E47: =C47+D47 -> 254263.08
B48: Lifetime Tax Saved | C48: =IFERROR(SUM(_xlfn.XLOOKUP(YEAR(StartYear), YearlyParamsA!A:A, YearlyParamsA!AA:AA):_xlfn.XLOOKUP(YEAR(StartYear)+ProjYearsA-1, YearlyParamsA!A:A, YearlyParamsA!AA:AA)), 0) -> 188674.72 | D48: =IFERROR(SUM(_xlfn.XLOOKUP(YEAR(StartYear), YearlyParamsB!A:A, YearlyParamsB!AB:AB):_xlfn.XLOOKUP(YEAR(StartYear)+ProjYearsB-1, YearlyParamsB!A:A, YearlyParamsB!AB:AB)), 0) -> 341361.49 | E48: =C48+D48 -> 530036.2
B49: Interest Saved on Mortgage | C49: {=LOOKUP(2,1/(YearlySummary[Year]<>""),YearlySummary[InterestSaved_Cumul])} -> 30271.925 | E49: =C49 -> 30271.925
B50: Combined Benefit (Tax + Interest) | C50: =C48+C49 -> 218946.64 | E50: =E48+E49 -> 560308.13
B52: EXPECTED LIFETIME TAX PAYABLE (No Strategy)
B53: Lifetime Tax Payable | C53: =SUMIF(YearlyParamsA!A2:A99,"<>",YearlyParamsA!AB2:AB99) -> 552998.73 | D53: =SUMIF(YearlyParamsB!A2:A128,"<>",YearlyParamsB!AC2:AC128) -> 1426491.3 | E53: =C53+D53 -> 1979490
B54: Years to Retirement | C54: =ProjYearsA -> 12 | D54: =ProjYearsB -> 15
B55: Total Lifetime Income | C55: {=SUMPRODUCT((YearlyParamsA!A2:A99<>"")*IF(YearlyParamsA!A2:A99<>"",YearlyParamsA!B2:B99,0))} -> 2000355.2 | D55: {=SUMPRODUCT((YearlyParamsB!A2:A128<>"")*IF(YearlyParamsB!A2:A128<>"",YearlyParamsB!B2:B128,0))} -> 4124343.1 | E55: =C55+D55 -> 6124698.3
B56: Avg. Effective Tax Rate | C56: =IF(C55=0,0,C53/C55) -> 0.27645027 | D56: =IF(D55=0,0,D53/D55) -> 0.34587114 | E56: =IF(E55=0,0,E53/E55) -> 0.32319796

Sheet PersonaA
A1: Period | B1: Year | C1: PeriodInYear | D1: IsSweepPeriod | E1: AnnualIncome | F1: MarginalRate | G1: BasePreTax | H1: CarryFwdThisYear | I1: EmployerSGAnnual | J1: AllowablePersonalAnnual | K1: CumulativePrev | L1: TaxSavedPrev | M1: ClientPreTaxContrib | N1: AvailableRoom | O1: ClientContribution | P1: TotalTaxBenefit | Q1: CumulativeSuperYTD | R1: CumulativeTaxSavedYTD | S1: CumulativeTaxSavedTotal
A2: =IF(ROW()-1 <= TotalPeriodsA, ROW()-1, "") -> 1 | B2: =IF(ROW()-1 <= TotalPeriodsA, YEAR(StartYear) + INT((ROW()-2)/PPYA), "") -> 2027 | C2: =IF($A2="", "", MOD($A2-1, PPYA)+1) -> 1 | D2: =IF($A2="", "", C2=PPYA) -> FALSE | E2: =IF($A2="","",IncA*(1+Inflation)^((B2 - YEAR(StartYear)))) -> 145000 | F2: {=IF($A2="", "", MRate(E2))} -> 0.39 | G2: =IF($A2="", "", AfterTaxA/(1-F2)) -> 11475.41 | H2: =IF($A2="", "", _xlfn.XLOOKUP($B2, YearlyParamsA!$A:$A, YearlyParamsA!$E:$E, 0)) -> 70000 | I2: =IF($A2="", "", E2*SGRate) -> 17400 | J2: =IFERROR(IF($A2="", "", _xlfn.XLOOKUP($B2, YearlyParamsA!$A:$A, YearlyParamsA!$I:$I, 0)), 0) -> 85100 | K2: =IF($A2="", "", 0) -> 0 | L2: =IF($A2="", "", 0) -> 0 | M2: =IF($A2="", "", G2) -> 11475.41 | N2: =IFERROR(IF($A2="", "", J2-K2), 0) -> 85100 | O2: =IFERROR(IF($A2="", "", MIN(G2,N2)), 0) -> 11475.41 | P2: =IFERROR(IF($A2="", "", MIN(G2+L2/PPYA,N2)*F2 + MAX(0, MIN(G2+L2/PPYA,N2) - MIN(G2,N2))), 0) -> 4475.4098 | Q2: =IFERROR(IF($A2="", "", K2+MIN(G2+L2/PPYA,N2)), 0) -> 11475.41 | R2: =IFERROR(IF($A2="", "", L2+P2), 0) -> 4475.4098 | S2: =IFERROR(IF($A2="","",P2),0) -> 4475.4098 | T2: =IF($A2="", "", LoanTerm + INT(($A2-1)/PPYA)) -> 12
A3: =IF(ROW()-1 <= TotalPeriodsA, ROW()-1, "") -> 2 | B3: =IF(ROW()-1 <= TotalPeriodsA, YEAR(StartYear) + INT((ROW()-2)/PPYA), "") -> 2027 | C3: =IF($A3="", "", MOD($A3-1, PPYA)+1) -> 2 | D3: =IF($A3="", "", C3=PPYA) -> FALSE | E3: =IF($A3="","",IncA*(1+Inflation)^((B3 - YEAR(StartYear)))) -> 145000 | F3: {=IF($A3="", "", MRate(E3))} -> 0.39 | G3: =IF($A3="", "", AfterTaxA/(1-F3)) -> 11475.41 | H3: =IF($A3="", "", _xlfn.XLOOKUP($B3, YearlyParamsA!$A:$A, YearlyParamsA!$E:$E, 0)) -> 70000 | I3: =IF($A3="", "", E3*SGRate) -> 17400 | J3: =IFERROR(IF($A3="", "", _xlfn.XLOOKUP($B3, YearlyParamsA!$A:$A, YearlyParamsA!$I:$I, 0)), 0) -> 85100 | K3: =IFERROR(IF($A2="", "", IF(B3<>B2,0,Q2)), 0) -> 11475.41 | L3: =IFERROR(IF($A2="","",IF(B3<>B2, 0, L2 + MIN(G2+L2/PPYA, J2-K2)*F2)), 0) -> 4475.4098 | M3: =IF($A3="", "", G3) -> 11475.41 | N3: =IFERROR(IF($A3="", "", J3-K3), 0) -> 73624.59 | O3: =IFERROR(IF($A3="", "", MIN(G3,N3)), 0) -> 11475.41 | P3: =IFERROR(IF($A3="", "", MIN(G3+L3/PPYA,N3)*F3 + MAX(0, MIN(G3+L3/PPYA,N3) - MIN(G3,N3))), 0) -> 4993.8115 | Q3: =IFERROR(IF($A3="", "", K3+MIN(G3+L3/PPYA,N3)), 0) -> 23323.77 | R3: =IFERROR(IF($A2="", "", IF(B3<>B2,P3,R2+P3)), 0) -> 9469.2213 | S3: =IFERROR(IF($A3="", "", S2+P3), 0) -> 9469.2213 | V3: PeriodsPerYear | W3: =_xlfn.XLOOKUP(FreqA,FreqLookup[Frequency],FreqLookup[PeriodsPerYear]) -> 12
A4: =IF(ROW()-1 <= TotalPeriodsA, ROW()-1, "") -> 3 | B4: =IF(ROW()-1 <= TotalPeriodsA, YEAR(StartYear) + INT((ROW()-2)/PPYA), "") -> 2027 | C4: =IF($A4="", "", MOD($A4-1, PPYA)+1) -> 3 | D4: =IF($A4="", "", C4=PPYA) -> FALSE | E4: =IF($A4="","",IncA*(1+Inflation)^((B4 - YEAR(StartYear)))) -> 145000 | F4: {=IF($A4="", "", MRate(E4))} -> 0.39 | G4: =IF($A4="", "", AfterTaxA/(1-F4)) -> 11475.41 | H4: =IF($A4="", "", _xlfn.XLOOKUP($B4, YearlyParamsA!$A:$A, YearlyParamsA!$E:$E, 0)) -> 70000 | I4: =IF($A4="", "", E4*SGRate) -> 17400 | J4: =IFERROR(IF($A4="", "", _xlfn.XLOOKUP($B4, YearlyParamsA!$A:$A, YearlyParamsA!$I:$I, 0)), 0) -> 85100 | K4: =IFERROR(IF($A3="", "", IF(B4<>B3,0,Q3)), 0) -> 23323.77 | L4: =IFERROR(IF($A3="","",IF(B4<>B3, 0, L3 + MIN(G3+L3/PPYA, J3-K3)*F3)), 0) -> 9096.2705 | M4: =IF($A4="", "", G4) -> 11475.41 | N4: =IFERROR(IF($A4="", "", J4-K4), 0) -> 61776.23 | O4: =IFERROR(IF($A4="", "", MIN(G4,N4)), 0) -> 11475.41 | P4: =IFERROR(IF($A4="", "", MIN(G4+L4/PPYA,N4)*F4 + MAX(0, MIN(G4+L4/PPYA,N4) - MIN(G4,N4))), 0) -> 5529.0612 | Q4: =IFERROR(IF($A4="", "", K4+MIN(G4+L4/PPYA,N4)), 0) -> 35557.203 | R4: =IFERROR(IF($A3="", "", IF(B4<>B3,P4,R3+P4)), 0) -> 14998.282 | S4: =IFERROR(IF($A4="", "", S3+P4), 0) -> 14998.282 | V4: TotalPeriods | W4: =ProjYearsA*PPYA -> 144
A5: =IF(ROW()-1 <= TotalPeriodsA, ROW()-1, "") -> 4 | B5: =IF(ROW()-1 <= TotalPeriodsA, YEAR(StartYear) + INT((ROW()-2)/PPYA), "") -> 2027 | C5: =IF($A5="", "", MOD($A5-1, PPYA)+1) -> 4 | D5: =IF($A5="", "", C5=PPYA) -> FALSE | E5: =IF($A5="","",IncA*(1+Inflation)^((B5 - YEAR(StartYear)))) -> 145000 | F5: {=IF($A5="", "", MRate(E5))} -> 0.39 | G5: =IF($A5="", "", AfterTaxA/(1-F5)) -> 11475.41 | H5: =IF($A5="", "", _xlfn.XLOOKUP($B5, YearlyParamsA!$A:$A, YearlyParamsA!$E:$E, 0)) -> 70000 | I5: =IF($A5="", "", E5*SGRate) -> 17400 | J5: =IFERROR(IF($A5="", "", _xlfn.XLOOKUP($B5, YearlyParamsA!$A:$A, YearlyParamsA!$I:$I, 0)), 0) -> 85100 | K5: =IFERROR(IF($A4="", "", IF(B5<>B4,0,Q4)), 0) -> 35557.203 | L5: =IFERROR(IF($A4="","",IF(B5<>B4, 0, L4 + MIN(G4+L4/PPYA, J4-K4)*F4)), 0) -> 13867.309 | M5: =IF($A5="", "", G5) -> 11475.41 | N5: =IFERROR(IF($A5="", "", J5-K5), 0) -> 49542.797 | O5: =IFERROR(IF($A5="", "", MIN(G5,N5)), 0) -> 11475.41 | P5: =IFERROR(IF($A5="", "", MIN(G5+L5/PPYA,N5)*F5 + MAX(0, MIN(G5+L5/PPYA,N5) - MIN(G5,N5))), 0) -> 6081.7065 | Q5: =IFERROR(IF($A5="", "", K5+MIN(G5+L5/PPYA,N5)), 0) -> 48188.222 | R5: =IFERROR(IF($A4="", "", IF(B5<>B4,P5,R4+P5)), 0) -> 21079.989 | S5: =IFERROR(IF($A5="", "", S4+P5), 0) -> 21079.989
A6: =IF(ROW()-1 <= TotalPeriodsA, ROW()-1, "") -> 5 | B6: =IF(ROW()-1 <= TotalPeriodsA, YEAR(StartYear) + INT((ROW()-2)/PPYA), "") -> 2027 | C6: =IF($A6="", "", MOD($A6-1, PPYA)+1) -> 5 | D6: =IF($A6="", "", C6=PPYA) -> FALSE | E6: =IF($A6="","",IncA*(1+Inflation)^((B6 - YEAR(StartYear)))) -> 145000 | F6: {=IF($A6="", "", MRate(E6))} -> 0.39 | G6: =IF($A6="", "", AfterTaxA/(1-F6)) -> 11475.41 | H6: =IF($A6="", "", _xlfn.XLOOKUP($B6, YearlyParamsA!$A:$A, YearlyParamsA!$E:$E, 0)) -> 70000 | I6: =IF($A6="", "", E6*SGRate) -> 17400 | J6: =IFERROR(IF($A6="", "", _xlfn.XLOOKUP($B6, YearlyParamsA!$A:$A, YearlyParamsA!$I:$I, 0)), 0) -> 85100 | K6: =IFERROR(IF($A5="", "", IF(B6<>B5,0,Q5)), 0) -> 48188.222 | L6: =IFERROR(IF($A5="","",IF(B6<>B5, 0, L5 + MIN(G5+L5/PPYA, J5-K5)*F5)), 0) -> 18793.407 | M6: =IF($A6="", "", G6) -> 11475.41 | N6: =IFERROR(IF($A6="", "", J6-K6), 0) -> 36911.778 | O6: =IFERROR(IF($A6="", "", MIN(G6,N6)), 0) -> 11475.41 | P6: =IFERROR(IF($A6="", "", MIN(G6+L6/PPYA,N6)*F6 + MAX(0, MIN(G6+L6/PPYA,N6) - MIN(G6,N6))), 0) -> 6652.3128 | Q6: =IFERROR(IF($A6="", "", K6+MIN(G6+L6/PPYA,N6)), 0) -> 61229.749 | R6: =IFERROR(IF($A5="", "", IF(B6<>B5,P6,R5+P6)), 0) -> 27732.302 | S6: =IFERROR(IF($A6="", "", S5+P6), 0) -> 27732.302
A7: =IF(ROW()-1 <= TotalPeriodsA, ROW()-1, "") -> 6 | B7: =IF(ROW()-1 <= TotalPeriodsA, YEAR(StartYear) + INT((ROW()-2)/PPYA), "") -> 2027 | C7: =IF($A7="", "", MOD($A7-1, PPYA)+1) -> 6 | D7: =IF($A7="", "", C7=PPYA) -> FALSE | E7: =IF($A7="","",IncA*(1+Inflation)^((B7 - YEAR(StartYear)))) -> 145000 | F7: {=IF($A7="", "", MRate(E7))} -> 0.39 | G7: =IF($A7="", "", AfterTaxA/(1-F7)) -> 11475.41 | H7: =IF($A7="", "", _xlfn.XLOOKUP($B7, YearlyParamsA!$A:$A, YearlyParamsA!$E:$E, 0)) -> 70000 | I7: =IF($A7="", "", E7*SGRate) -> 17400 | J7: =IFERROR(IF($A7="", "", _xlfn.XLOOKUP($B7, YearlyParamsA!$A:$A, YearlyParamsA!$I:$I, 0)), 0) -> 85100 | K7: =IFERROR(IF($A6="", "", IF(B7<>B6,0,Q6)), 0) -> 61229.749 | L7: =IFERROR(IF($A6="","",IF(B7<>B6, 0, L6 + MIN(G6+L6/PPYA, J6-K6)*F6)), 0) -> 23879.602 | M7: =IF($A7="", "", G7) -> 11475.41 | N7: =IFERROR(IF($A7="", "", J7-K7), 0) -> 23870.251 | O7: =IFERROR(IF($A7="", "", MIN(G7,N7)), 0) -> 11475.41 | P7: =IFERROR(IF($A7="", "", MIN(G7+L7/PPYA,N7)*F7 + MAX(0, MIN(G7+L7/PPYA,N7) - MIN(G7,N7))), 0) -> 7241.4637 | Q7: =IFERROR(IF($A7="", "", K7+MIN(G7+L7/PPYA,N7)), 0) -> 74695.126 | R7: =IFERROR(IF($A6="", "", IF(B7<>B6,P7,R6+P7)), 0) -> 34973.765 | S7: =IFERROR(IF($A7="", "", S6+P7), 0) -> 34973.765
A8: =IF(ROW()-1 <= TotalPeriodsA, ROW()-1, "") -> 7 | B8: =IF(ROW()-1 <= TotalPeriodsA, YEAR(StartYear) + INT((ROW()-2)/PPYA), "") -> 2027 | C8: =IF($A8="", "", MOD($A8-1, PPYA)+1) -> 7 | D8: =IF($A8="", "", C8=PPYA) -> FALSE | E8: =IF($A8="","",IncA*(1+Inflation)^((B8 - YEAR(StartYear)))) -> 145000 | F8: {=IF($A8="", "", MRate(E8))} -> 0.39 | G8: =IF($A8="", "", AfterTaxA/(1-F8)) -> 11475.41 | H8: =IF($A8="", "", _xlfn.XLOOKUP($B8, YearlyParamsA!$A:$A, YearlyParamsA!$E:$E, 0)) -> 70000 | I8: =IF($A8="", "", E8*SGRate) -> 17400 | J8: =IFERROR(IF($A8="", "", _xlfn.XLOOKUP($B8, YearlyParamsA!$A:$A, YearlyParamsA!$I:$I, 0)), 0) -> 85100 | K8: =IFERROR(IF($A7="", "", IF(B8<>B7,0,Q7)), 0) -> 74695.126 | L8: =IFERROR(IF($A7="","",IF(B8<>B7, 0, L7 + MIN(G7+L7/PPYA, J7-K7)*F7)), 0) -> 29131.099 | M8: =IF($A8="", "", G8) -> 11475.41 | N8: =IFERROR(IF($A8="", "", J8-K8), 0) -> 10404.874 | O8: =IFERROR(IF($A8="", "", MIN(G8,N8)), 0) -> 10404.874 | P8: =IFERROR(IF($A8="", "", MIN(G8+L8/PPYA,N8)*F8 + MAX(0, MIN(G8+L8/PPYA,N8) - MIN(G8,N8))), 0) -> 4057.901 | Q8: =IFERROR(IF($A8="", "", K8+MIN(G8+L8/PPYA,N8)), 0) -> 85100 | R8: =IFERROR(IF($A7="", "", IF(B8<>B7,P8,R7+P8)), 0) -> 39031.666 | S8: =IFERROR(IF($A8="", "", S7+P8), 0) -> 39031.666
A9: =IF(ROW()-1 <= TotalPeriodsA, ROW()-1, "") -> 8 | B9: =IF(ROW()-1 <= TotalPeriodsA, YEAR(StartYear) + INT((ROW()-2)/PPYA), "") -> 2027 | C9: =IF($A9="", "", MOD($A9-1, PPYA)+1) -> 8 | D9: =IF($A9="", "", C9=PPYA) -> FALSE | E9: =IF($A9="","",IncA*(1+Inflation)^((B9 - YEAR(StartYear)))) -> 145000 | F9: {=IF($A9="", "", MRate(E9))} -> 0.39 | G9: =IF($A9="", "", AfterTaxA/(1-F9)) -> 11475.41 | H9: =IF($A9="", "", _xlfn.XLOOKUP($B9, YearlyParamsA!$A:$A, YearlyParamsA!$E:$E, 0)) -> 70000 | I9: =IF($A9="", "", E9*SGRate) -> 17400 | J9: =IFERROR(IF($A9="", "", _xlfn.XLOOKUP($B9, YearlyParamsA!$A:$A, YearlyParamsA!$I:$I, 0)), 0) -> 85100 | K9: =IFERROR(IF($A8="", "", IF(B9<>B8,0,Q8)), 0) -> 85100 | L9: =IFERROR(IF($A8="","",IF(B9<>B8, 0, L8 + MIN(G8+L8/PPYA, J8-K8)*F8)), 0) -> 33189 | M9: =IF($A9="", "", G9) -> 11475.41 | N9: =IFERROR(IF($A9="", "", J9-K9), 0) -> 0 | O9: =IFERROR(IF($A9="", "", MIN(G9,N9)), 0) -> 0 | P9: =IFERROR(IF($A9="", "", MIN(G9+L9/PPYA,N9)*F9 + MAX(0, MIN(G9+L9/PPYA,N9) - MIN(G9,N9))), 0) -> 0 | Q9: =IFERROR(IF($A9="", "", K9+MIN(G9+L9/PPYA,N9)), 0) -> 85100 | R9: =IFERROR(IF($A8="", "", IF(B9<>B8,P9,R8+P9)), 0) -> 39031.666 | S9: =IFERROR(IF($A9="", "", S8+P9), 0) -> 39031.666
A10: =IF(ROW()-1 <= TotalPeriodsA, ROW()-1, "") -> 9 | B10: =IF(ROW()-1 <= TotalPeriodsA, YEAR(StartYear) + INT((ROW()-2)/PPYA), "") -> 2027 | C10: =IF($A10="", "", MOD($A10-1, PPYA)+1) -> 9 | D10: =IF($A10="", "", C10=PPYA) -> FALSE | E10: =IF($A10="","",IncA*(1+Inflation)^((B10 - YEAR(StartYear)))) -> 145000 | F10: {=IF($A10="", "", MRate(E10))} -> 0.39 | G10: =IF($A10="", "", AfterTaxA/(1-F10)) -> 11475.41 | H10: =IF($A10="", "", _xlfn.XLOOKUP($B10, YearlyParamsA!$A:$A, YearlyParamsA!$E:$E, 0)) -> 70000 | I10: =IF($A10="", "", E10*SGRate) -> 17400 | J10: =IFERROR(IF($A10="", "", _xlfn.XLOOKUP($B10, YearlyParamsA!$A:$A, YearlyParamsA!$I:$I, 0)), 0) -> 85100 | K10: =IFERROR(IF($A9="", "", IF(B10<>B9,0,Q9)), 0) -> 85100 | L10: =IFERROR(IF($A9="","",IF(B10<>B9, 0, L9 + MIN(G9+L9/PPYA, J9-K9)*F9)), 0) -> 33189 | M10: =IF($A10="", "", G10) -> 11475.41 | N10: =IFERROR(IF($A10="", "", J10-K10), 0) -> 0 | O10: =IFERROR(IF($A10="", "", MIN(G10,N10)), 0) -> 0 | P10: =IFERROR(IF($A10="", "", MIN(G10+L10/PPYA,N10)*F10 + MAX(0, MIN(G10+L10/PPYA,N10) - MIN(G10,N10))), 0) -> 0 | Q10: =IFERROR(IF($A10="", "", K10+MIN(G10+L10/PPYA,N10)), 0) -> 85100 | R10: =IFERROR(IF($A9="", "", IF(B10<>B9,P10,R9+P10)), 0) -> 39031.666 | S10: =IFERROR(IF($A10="", "", S9+P10), 0) -> 39031.666
A11: =IF(ROW()-1 <= TotalPeriodsA, ROW()-1, "") -> 10 | B11: =IF(ROW()-1 <= TotalPeriodsA, YEAR(StartYear) + INT((ROW()-2)/PPYA), "") -> 2027 | C11: =IF($A11="", "", MOD($A11-1, PPYA)+1) -> 10 | D11: =IF($A11="", "", C11=PPYA) -> FALSE | E11: =IF($A11="","",IncA*(1+Inflation)^((B11 - YEAR(StartYear)))) -> 145000 | F11: {=IF($A11="", "", MRate(E11))} -> 0.39 | G11: =IF($A11="", "", AfterTaxA/(1-F11)) -> 11475.41 | H11: =IF($A11="", "", _xlfn.XLOOKUP($B11, YearlyParamsA!$A:$A, YearlyParamsA!$E:$E, 0)) -> 70000 | I11: =IF($A11="", "", E11*SGRate) -> 17400 | J11: =IFERROR(IF($A11="", "", _xlfn.XLOOKUP($B11, YearlyParamsA!$A:$A, YearlyParamsA!$I:$I, 0)), 0) -> 85100 | K11: =IFERROR(IF($A10="", "", IF(B11<>B10,0,Q10)), 0) -> 85100 | L11: =IFERROR(IF($A10="","",IF(B11<>B10, 0, L10 + MIN(G10+L10/PPYA, J10-K10)*F10)), 0) -> 33189 | M11: =IF($A11="", "", G11) -> 11475.41 | N11: =IFERROR(IF($A11="", "", J11-K11), 0) -> 0 | O11: =IFERROR(IF($A11="", "", MIN(G11,N11)), 0) -> 0 | P11: =IFERROR(IF($A11="", "", MIN(G11+L11/PPYA,N11)*F11 + MAX(0, MIN(G11+L11/PPYA,N11) - MIN(G11,N11))), 0) -> 0 | Q11: =IFERROR(IF($A11="", "", K11+MIN(G11+L11/PPYA,N11)), 0) -> 85100 | R11: =IFERROR(IF($A10="", "", IF(B11<>B10,P11,R10+P11)), 0) -> 39031.666 | S11: =IFERROR(IF($A11="", "", S10+P11), 0) -> 39031.666
A12: =IF(ROW()-1 <= TotalPeriodsA, ROW()-1, "") -> 11 | B12: =IF(ROW()-1 <= TotalPeriodsA, YEAR(StartYear) + INT((ROW()-2)/PPYA), "") -> 2027 | C12: =IF($A12="", "", MOD($A12-1, PPYA)+1) -> 11 | D12: =IF($A12="", "", C12=PPYA) -> FALSE | E12: =IF($A12="","",IncA*(1+Inflation)^((B12 - YEAR(StartYear)))) -> 145000 | F12: {=IF($A12="", "", MRate(E12))} -> 0.39 | G12: =IF($A12="", "", AfterTaxA/(1-F12)) -> 11475.41 | H12: =IF($A12="", "", _xlfn.XLOOKUP($B12, YearlyParamsA!$A:$A, YearlyParamsA!$E:$E, 0)) -> 70000 | I12: =IF($A12="", "", E12*SGRate) -> 17400 | J12: =IFERROR(IF($A12="", "", _xlfn.XLOOKUP($B12, YearlyParamsA!$A:$A, YearlyParamsA!$I:$I, 0)), 0) -> 85100 | K12: =IFERROR(IF($A11="", "", IF(B12<>B11,0,Q11)), 0) -> 85100 | L12: =IFERROR(IF($A11="","",IF(B12<>B11, 0, L11 + MIN(G11+L11/PPYA, J11-K11)*F11)), 0) -> 33189 | M12: =IF($A12="", "", G12) -> 11475.41 | N12: =IFERROR(IF($A12="", "", J12-K12), 0) -> 0 | O12: =IFERROR(IF($A12="", "", MIN(G12,N12)), 0) -> 0 | P12: =IFERROR(IF($A12="", "", MIN(G12+L12/PPYA,N12)*F12 + MAX(0, MIN(G12+L12/PPYA,N12) - MIN(G12,N12))), 0) -> 0 | Q12: =IFERROR(IF($A12="", "", K12+MIN(G12+L12/PPYA,N12)), 0) -> 85100 | R12: =IFERROR(IF($A11="", "", IF(B12<>B11,P12,R11+P12)), 0) -> 39031.666 | S12: =IFERROR(IF($A12="", "", S11+P12), 0) -> 39031.666
A13: =IF(ROW()-1 <= TotalPeriodsA, ROW()-1, "") -> 12 | B13: =IF(ROW()-1 <= TotalPeriodsA, YEAR(StartYear) + INT((ROW()-2)/PPYA), "") -> 2027 | C13: =IF($A13="", "", MOD($A13-1, PPYA)+1) -> 12 | D13: =IF($A13="", "", C13=PPYA) -> TRUE | E13: =IF($A13="","",IncA*(1+Inflation)^((B13 - YEAR(StartYear)))) -> 145000 | F13: {=IF($A13="", "", MRate(E13))} -> 0.39 | G13: =IF($A13="", "", AfterTaxA/(1-F13)) -> 11475.41 | H13: =IF($A13="", "", _xlfn.XLOOKUP($B13, YearlyParamsA!$A:$A, YearlyParamsA!$E:$E, 0)) -> 70000 | I13: =IF($A13="", "", E13*SGRate) -> 17400 | J13: =IFERROR(IF($A13="", "", _xlfn.XLOOKUP($B13, YearlyParamsA!$A:$A, YearlyParamsA!$I:$I, 0)), 0) -> 85100 | K13: =IFERROR(IF($A12="", "", IF(B13<>B12,0,Q12)), 0) -> 85100 | L13: =IFERROR(IF($A12="","",IF(B13<>B12, 0, L12 + MIN(G12+L12/PPYA, J12-K12)*F12)), 0) -> 33189 | M13: =IF($A13="", "", G13) -> 11475.41 | N13: =IFERROR(IF($A13="", "", J13-K13), 0) -> 0 | O13: =IFERROR(IF($A13="", "", MIN(G13,N13)), 0) -> 0 | P13: =IFERROR(IF($A13="", "", MIN(G13+L13/PPYA,N13)*F13 + MAX(0, MIN(G13+L13/PPYA,N13) - MIN(G13,N13))), 0) -> 0 | Q13: =IFERROR(IF($A13="", "", K13+MIN(G13+L13/PPYA,N13)), 0) -> 85100 | R13: =IFERROR(IF($A12="", "", IF(B13<>B12,P13,R12+P13)), 0) -> 39031.666 | S13: =IFERROR(IF($A13="", "", S12+P13), 0) -> 39031.666
A14: =IF(ROW()-1 <= TotalPeriodsA, ROW()-1, "") -> 13 | B14: =IF(ROW()-1 <= TotalPeriodsA, YEAR(StartYear) + INT((ROW()-2)/PPYA), "") -> 2028 | C14: =IF($A14="", "", MOD($A14-1, PPYA)+1) -> 1 | D14: =IF($A14="", "", C14=PPYA) -> FALSE | E14: =IF($A14="","",IncA*(1+Inflation)^((B14 - YEAR(StartYear)))) -> 148625 | F14: {=IF($A14="", "", MRate(E14))} -> 0.39 | G14: =IF($A14="", "", AfterTaxA/(1-F14)) -> 11475.41 | H14: =IF($A14="", "", _xlfn.XLOOKUP($B14, YearlyParamsA!$A:$A, YearlyParamsA!$E:$E, 0)) -> 0 | I14: =IF($A14="", "", E14*SGRate) -> 17835 | J14: =IFERROR(IF($A14="", "", _xlfn.XLOOKUP($B14, YearlyParamsA!$A:$A, YearlyParamsA!$I:$I, 0)), 0) -> 14665 | K14: =IFERROR(IF($A13="", "", IF(B14<>B13,0,Q13)), 0) -> 0 | L14: =IFERROR(IF($A13="","",IF(B14<>B13, 0, L13 + MIN(G13+L13/PPYA, J13-K13)*F13)), 0) -> 0 | M14: =IF($A14="", "", G14) -> 11475.41 | N14: =IFERROR(IF($A14="", "", J14-K14), 0) -> 14665 | O14: =IFERROR(IF($A14="", "", MIN(G14,N14)), 0) -> 11475.41 | P14: =IFERROR(IF($A14="", "", MIN(G14+L14/PPYA,N14)*F14 + MAX(0, MIN(G14+L14/PPYA,N14) - MIN(G14,N14))), 0) -> 4475.4098 | Q14: =IFERROR(IF($A14="", "", K14+MIN(G14+L14/PPYA,N14)), 0) -> 11475.41 | R14: =IFERROR(IF($A13="", "", IF(B14<>B13,P14,R13+P14)), 0) -> 4475.4098 | S14: =IFERROR(IF($A14="", "", S13+P14), 0) -> 43507.076
A15: =IF(ROW()-1 <= TotalPeriodsA, ROW()-1, "") -> 14 | B15: =IF(ROW()-1 <= TotalPeriodsA, YEAR(StartYear) + INT((ROW()-2)/PPYA), "") -> 2028 | C15: =IF($A15="", "", MOD($A15-1, PPYA)+1) -> 2 | D15: =IF($A15="", "", C15=PPYA) -> FALSE | E15: =IF($A15="","",IncA*(1+Inflation)^((B15 - YEAR(StartYear)))) -> 148625 | F15: {=IF($A15="", "", MRate(E15))} -> 0.39 | G15: =IF($A15="", "", AfterTaxA/(1-F15)) -> 11475.41 | H15: =IF($A15="", "", _xlfn.XLOOKUP($B15, YearlyParamsA!$A:$A, YearlyParamsA!$E:$E, 0)) -> 0 | I15: =IF($A15="", "", E15*SGRate) -> 17835 | J15: =IFERROR(IF($A15="", "", _xlfn.XLOOKUP($B15, YearlyParamsA!$A:$A, YearlyParamsA!$I:$I, 0)), 0) -> 14665 | K15: =IFERROR(IF($A14="", "", IF(B15<>B14,0,Q14)), 0) -> 11475.41 | L15: =IFERROR(IF($A14="","",IF(B15<>B14, 0, L14 + MIN(G14+L14/PPYA, J14-K14)*F14)), 0) -> 4475.4098 | M15: =IF($A15="", "", G15) -> 11475.41 | N15: =IFERROR(IF($A15="", "", J15-K15), 0) -> 3189.5902 | O15: =IFERROR(IF($A15="", "", MIN(G15,N15)), 0) -> 3189.5902 | P15: =IFERROR(IF($A15="", "", MIN(G15+L15/PPYA,N15)*F15 + MAX(0, MIN(G15+L15/PPYA,N15) - MIN(G15,N15))), 0) -> 1243.9402 | Q15: =IFERROR(IF($A15="", "", K15+MIN(G15+L15/PPYA,N15)), 0) -> 14665 | R15: =IFERROR(IF($A14="", "", IF(B15<>B14,P15,R14+P15)), 0) -> 5719.35 | S15: =IFERROR(IF($A15="", "", S14+P15), 0) -> 44751.016
A16: =IF(ROW()-1 <= TotalPeriodsA, ROW()-1, "") -> 15 | B16: =IF(ROW()-1 <= TotalPeriodsA, YEAR(StartYear) + INT((ROW()-2)/PPYA), "") -> 2028 | C16: =IF($A16="", "", MOD($A16-1, PPYA)+1) -> 3 | D16: =IF($A16="", "", C16=PPYA) -> FALSE | E16: =IF($A16="","",IncA*(1+Inflation)^((B16 - YEAR(StartYear)))) -> 148625 | F16: {=IF($A16="", "", MRate(E16))} -> 0.39 | G16: =IF($A16="", "", AfterTaxA/(1-F16)) -> 11475.41 | H16: =IF($A16="", "", _xlfn.XLOOKUP($B16, YearlyParamsA!$A:$A, YearlyParamsA!$E:$E, 0)) -> 0 | I16: =IF($A16="", "", E16*SGRate) -> 17835 | J16: =IFERROR(IF($A16="", "", _xlfn.XLOOKUP($B16, YearlyParamsA!$A:$A, YearlyParamsA!$I:$I, 0)), 0) -> 14665 | K16: =IFERROR(IF($A15="", "", IF(B16<>B15,0,Q15)), 0) -> 14665 | L16: =IFERROR(IF($A15="","",IF(B16<>B15, 0, L15 + MIN(G15+L15/PPYA, J15-K15)*F15)), 0) -> 5719.35 | M16: =IF($A16="", "", G16) -> 11475.41 | N16: =IFERROR(IF($A16="", "", J16-K16), 0) -> 0 | O16: =IFERROR(IF($A16="", "", MIN(G16,N16)), 0) -> 0 | P16: =IFERROR(IF($A16="", "", MIN(G16+L16/PPYA,N16)*F16 + MAX(0, MIN(G16+L16/PPYA,N16) - MIN(G16,N16))), 0) -> 0 | Q16: =IFERROR(IF($A16="", "", K16+MIN(G16+L16/PPYA,N16)), 0) -> 14665 | R16: =IFERROR(IF($A15="", "", IF(B16<>B15,P16,R15+P16)), 0) -> 5719.35 | S16: =IFERROR(IF($A16="", "", S15+P16), 0) -> 44751.016
... A145: =IF(ROW()-1 <= TotalPeriodsA, ROW()-1, "") -> 144 | B145: =IF(ROW()-1 <= TotalPeriodsA, YEAR(StartYear) + INT((ROW()-2)/PPYA), "") -> 2038 | C145: =IF($A145="", "", MOD($A145-1, PPYA)+1) -> 12 | D145: =IF($A145="", "", C145=PPYA) -> TRUE | E145: =IF($A145="","",IncA*(1+Inflation)^((B145 - YEAR(StartYear)))) -> 190252.57 | F145: {=IF($A145="", "", MRate(E145))} -> 0.47 | G145: =IF($A145="", "", AfterTaxA/(1-F145)) -> 13207.547 | H145: =IF($A145="", "", _xlfn.XLOOKUP($B145, YearlyParamsA!$A:$A, YearlyParamsA!$E:$E, 0)) -> 0 | I145: =IF($A145="", "", E145*SGRate) -> 22830.308 | J145: =IFERROR(IF($A145="", "", _xlfn.XLOOKUP($B145, YearlyParamsA!$A:$A, YearlyParamsA!$I:$I, 0)), 0) -> 22169.692 | K145: =IFERROR(IF($A144="", "", IF(B145<>B144,0,Q144)), 0) -> 22169.692 | L145: =IFERROR(IF($A144="","",IF(B145<>B144, 0, L144 + MIN(G144+L144/PPYA, J144-K144)*F144)), 0) -> 10419.755 | M145: =IF($A145="", "", G145) -> 13207.547 | N145: =IFERROR(IF($A145="", "", J145-K145), 0) -> 0 | O145: =IFERROR(IF($A145="", "", MIN(G145,N145)), 0) -> 0 | P145: =IFERROR(IF($A145="", "", MIN(G145+L145/PPYA,N145)*F145 + MAX(0, MIN(G145+L145/PPYA,N145) - MIN(G145,N145))), 0) -> 0 | Q145: =IFERROR(IF($A145="", "", K145+MIN(G145+L145/PPYA,N145)), 0) -> 22169.692 | R145: =IFERROR(IF($A144="", "", IF(B145<>B144,P145,R144+P145)), 0) -> 10419.755 | S145: =IFERROR(IF($A145="", "", S144+P145), 0) -> 122649.62

Sheet PersonaB
A1: Period | B1: Year | C1: PeriodInYear | D1: IsSweepPeriod | E1: AnnualIncome | F1: MarginalRate | G1: BasePreTax | H1: CarryFwdThisYear | I1: EmployerSGAnnual | J1: AllowablePersonalAnnual | K1: CumulativePrev | L1: TaxSavedPrev | M1: ClientPreTaxContrib | N1: AvailableRoom | O1: ClientContribution | P1: TotalTaxBenefit | Q1: CumulativeSuperYTD | R1: CumulativeTaxSavedYTD | S1: CumulativeTaxSavedTotal | T1: LoanTermAdj
A2: =IF(ROW()-1 <= TotalPeriodsB, ROW()-1, "") -> 1 | B2: =IF(ROW()-1 <= TotalPeriodsB, YEAR(StartYear) + INT((ROW()-2)/PPYB), "") -> 2027 | C2: =IF($A2="", "", MOD($A2-1, PPYB)+1) -> 1 | D2: =IF($A2="", "", C2=PPYB) -> FALSE | E2: =IF($A2="","",IncB*(1+Inflation)^((B2 - YEAR(StartYear)))) -> 230000 | F2: {=IF($A2="", "", MRate(E2))} -> 0.47 | G2: =IF($A2="", "", AfterTaxB/(1-F2)) -> 9433.9623 | H2: =IF($A2="", "", _xlfn.XLOOKUP($B2, YearlyParamsB!$A:$A, YearlyParamsB!$E:$E, 0)) -> 120000 | I2: =IF($A2="", "", E2*SGRate) -> 27600 | J2: =IFERROR(IF($A2="", "", _xlfn.XLOOKUP($B2, YearlyParamsB!$A:$A, YearlyParamsB!$I:$I, 0)), 0) -> 124900 | K2: =IF($A2="", "", 0) -> 0 | L2: =IF($A2="", "", 0) -> 0 | M2: =IF($A2="", "", G2) -> 9433.9623 | N2: =IFERROR(IF($A2="", "", J2-K2), 0) -> 124900 | O2: =IFERROR(IF($A2="", "", MIN(G2,N2)), 0) -> 9433.9623 | P2: =IFERROR(IF($A2="", "", MIN(G2+L2/PPYB,N2)*F2 + MAX(0, MIN(G2+L2/PPYB,N2) - MIN(G2,N2))), 0) -> 4433.9623 | Q2: =IFERROR(IF($A2="", "", K2+MIN(G2+L2/PPYB,N2)), 0) -> 9433.9623 | R2: =IFERROR(IF($A2="", "", L2+P2), 0) -> 4433.9623 | S2: =IFERROR(IF($A2="","",P2),0) -> 4433.9623 | T2: =IF($A2="", "", LoanTerm + INT(($A2-1)/PPYB)) -> 12
A3: =IF(ROW()-1 <= TotalPeriodsB, ROW()-1, "") -> 2 | B3: =IF(ROW()-1 <= TotalPeriodsB, YEAR(StartYear) + INT((ROW()-2)/PPYB), "") -> 2027 | C3: =IF($A3="", "", MOD($A3-1, PPYB)+1) -> 2 | D3: =IF($A3="", "", C3=PPYB) -> FALSE | E3: =IF($A3="","",IncB*(1+Inflation)^((B3 - YEAR(StartYear)))) -> 230000 | F3: {=IF($A3="", "", MRate(E3))} -> 0.47 | G3: =IF($A3="", "", AfterTaxB/(1-F3)) -> 9433.9623 | H3: =IF($A3="", "", _xlfn.XLOOKUP($B3, YearlyParamsB!$A:$A, YearlyParamsB!$E:$E, 0)) -> 120000 | I3: =IF($A3="", "", E3*SGRate) -> 27600 | J3: =IFERROR(IF($A3="", "", _xlfn.XLOOKUP($B3, YearlyParamsB!$A:$A, YearlyParamsB!$I:$I, 0)), 0) -> 124900 | K3: =IFERROR(IF($A2="", "", IF(B3<>B2,0,Q2)), 0) -> 9433.9623 | L3: =IFERROR(IF($A2="","",IF(B3<>B2, 0, L2 + MIN(G2+L2/PPYB, J2-K2)*F2)), 0) -> 4433.9623 | M3: =IF($A3="", "", G3) -> 9433.9623 | N3: =IFERROR(IF($A3="", "", J3-K3), 0) -> 115466.04 | O3: =IFERROR(IF($A3="", "", MIN(G3,N3)), 0) -> 9433.9623 | P3: =IFERROR(IF($A3="", "", MIN(G3+L3/PPYB,N3)*F3 + MAX(0, MIN(G3+L3/PPYB,N3) - MIN(G3,N3))), 0) -> 4977.1226 | Q3: =IFERROR(IF($A3="", "", K3+MIN(G3+L3/PPYB,N3)), 0) -> 19237.421 | R3: =IFERROR(IF($A2="", "", IF(B3<>B2,P3,R2+P3)), 0) -> 9411.0849 | S3: =IFERROR(IF($A3="", "", S2+P3), 0) -> 9411.0849 | V3: PeriodsPerYear | W3: =_xlfn.XLOOKUP(FreqB,FreqLookup[Frequency],FreqLookup[PeriodsPerYear]) -> 12
A4: =IF(ROW()-1 <= TotalPeriodsB, ROW()-1, "") -> 3 | B4: =IF(ROW()-1 <= TotalPeriodsB, YEAR(StartYear) + INT((ROW()-2)/PPYB), "") -> 2027 | C4: =IF($A4="", "", MOD($A4-1, PPYB)+1) -> 3 | D4: =IF($A4="", "", C4=PPYB) -> FALSE | E4: =IF($A4="","",IncB*(1+Inflation)^((B4 - YEAR(StartYear)))) -> 230000 | F4: {=IF($A4="", "", MRate(E4))} -> 0.47 | G4: =IF($A4="", "", AfterTaxB/(1-F4)) -> 9433.9623 | H4: =IF($A4="", "", _xlfn.XLOOKUP($B4, YearlyParamsB!$A:$A, YearlyParamsB!$E:$E, 0)) -> 120000 | I4: =IF($A4="", "", E4*SGRate) -> 27600 | J4: =IFERROR(IF($A4="", "", _xlfn.XLOOKUP($B4, YearlyParamsB!$A:$A, YearlyParamsB!$I:$I, 0)), 0) -> 124900 | K4: =IFERROR(IF($A3="", "", IF(B4<>B3,0,Q3)), 0) -> 19237.421 | L4: =IFERROR(IF($A3="","",IF(B4<>B3, 0, L3 + MIN(G3+L3/PPYB, J3-K3)*F3)), 0) -> 9041.5881 | M4: =IF($A4="", "", G4) -> 9433.9623 | N4: =IFERROR(IF($A4="", "", J4-K4), 0) -> 105662.58 | O4: =IFERROR(IF($A4="", "", MIN(G4,N4)), 0) -> 9433.9623 | P4: =IFERROR(IF($A4="", "", MIN(G4+L4/PPYB,N4)*F4 + MAX(0, MIN(G4+L4/PPYB,N4) - MIN(G4,N4))), 0) -> 5541.5568 | Q4: =IFERROR(IF($A4="", "", K4+MIN(G4+L4/PPYB,N4)), 0) -> 29424.849 | R4: =IFERROR(IF($A3="", "", IF(B4<>B3,P4,R3+P4)), 0) -> 14952.642 | S4: =IFERROR(IF($A4="", "", S3+P4), 0) -> 14952.642 | V4: TotalPeriods | W4: =ProjYearsB*PPYB -> 180
A5: =IF(ROW()-1 <= TotalPeriodsB, ROW()-1, "") -> 4 | B5: =IF(ROW()-1 <= TotalPeriodsB, YEAR(StartYear) + INT((ROW()-2)/PPYB), "") -> 2027 | C5: =IF($A5="", "", MOD($A5-1, PPYB)+1) -> 4 | D5: =IF($A5="", "", C5=PPYB) -> FALSE | E5: =IF($A5="","",IncB*(1+Inflation)^((B5 - YEAR(StartYear)))) -> 230000 | F5: {=IF($A5="", "", MRate(E5))} -> 0.47 | G5: =IF($A5="", "", AfterTaxB/(1-F5)) -> 9433.9623 | H5: =IF($A5="", "", _xlfn.XLOOKUP($B5, YearlyParamsB!$A:$A, YearlyParamsB!$E:$E, 0)) -> 120000 | I5: =IF($A5="", "", E5*SGRate) -> 27600 | J5: =IFERROR(IF($A5="", "", _xlfn.XLOOKUP($B5, YearlyParamsB!$A:$A, YearlyParamsB!$I:$I, 0)), 0) -> 124900 | K5: =IFERROR(IF($A4="", "", IF(B5<>B4,0,Q4)), 0) -> 29424.849 | L5: =IFERROR(IF($A4="","",IF(B5<>B4, 0, L4 + MIN(G4+L4/PPYB, J4-K4)*F4)), 0) -> 13829.679 | M5: =IF($A5="", "", G5) -> 9433.9623 | N5: =IFERROR(IF($A5="", "", J5-K5), 0) -> 95475.151 | O5: =IFERROR(IF($A5="", "", MIN(G5,N5)), 0) -> 9433.9623 | P5: =IFERROR(IF($A5="", "", MIN(G5+L5/PPYB,N5)*F5 + MAX(0, MIN(G5+L5/PPYB,N5) - MIN(G5,N5))), 0) -> 6128.098 | Q5: =IFERROR(IF($A5="", "", K5+MIN(G5+L5/PPYB,N5)), 0) -> 40011.285 | R5: =IFERROR(IF($A4="", "", IF(B5<>B4,P5,R4+P5)), 0) -> 21080.74 | S5: =IFERROR(IF($A5="", "", S4+P5), 0) -> 21080.74
A6: =IF(ROW()-1 <= TotalPeriodsB, ROW()-1, "") -> 5 | B6: =IF(ROW()-1 <= TotalPeriodsB, YEAR(StartYear) + INT((ROW()-2)/PPYB), "") -> 2027 | C6: =IF($A6="", "", MOD($A6-1, PPYB)+1) -> 5 | D6: =IF($A6="", "", C6=PPYB) -> FALSE | E6: =IF($A6="","",IncB*(1+Inflation)^((B6 - YEAR(StartYear)))) -> 230000 | F6: {=IF($A6="", "", MRate(E6))} -> 0.47 | G6: =IF($A6="", "", AfterTaxB/(1-F6)) -> 9433.9623 | H6: =IF($A6="", "", _xlfn.XLOOKUP($B6, YearlyParamsB!$A:$A, YearlyParamsB!$E:$E, 0)) -> 120000 | I6: =IF($A6="", "", E6*SGRate) -> 27600 | J6: =IFERROR(IF($A6="", "", _xlfn.XLOOKUP($B6, YearlyParamsB!$A:$A, YearlyParamsB!$I:$I, 0)), 0) -> 124900 | K6: =IFERROR(IF($A5="", "", IF(B6<>B5,0,Q5)), 0) -> 40011.285 | L6: =IFERROR(IF($A5="","",IF(B6<>B5, 0, L5 + MIN(G5+L5/PPYB, J5-K5)*F5)), 0) -> 18805.304 | M6: =IF($A6="", "", G6) -> 9433.9623 | N6: =IFERROR(IF($A6="", "", J6-K6), 0) -> 84888.715 | O6: =IFERROR(IF($A6="", "", MIN(G6,N6)), 0) -> 9433.9623 | P6: =IFERROR(IF($A6="", "", MIN(G6+L6/PPYB,N6)*F6 + MAX(0, MIN(G6+L6/PPYB,N6) - MIN(G6,N6))), 0) -> 6737.612 | Q6: =IFERROR(IF($A6="", "", K6+MIN(G6+L6/PPYB,N6)), 0) -> 51012.356 | R6: =IFERROR(IF($A5="", "", IF(B6<>B5,P6,R5+P6)), 0) -> 27818.352 | S6: =IFERROR(IF($A6="", "", S5+P6), 0) -> 27818.352
A7: =IF(ROW()-1 <= TotalPeriodsB, ROW()-1, "") -> 6 | B7: =IF(ROW()-1 <= TotalPeriodsB, YEAR(StartYear) + INT((ROW()-2)/PPYB), "") -> 2027 | C7: =IF($A7="", "", MOD($A7-1, PPYB)+1) -> 6 | D7: =IF($A7="", "", C7=PPYB) -> FALSE | E7: =IF($A7="","",IncB*(1+Inflation)^((B7 - YEAR(StartYear)))) -> 230000 | F7: {=IF($A7="", "", MRate(E7))} -> 0.47 | G7: =IF($A7="", "", AfterTaxB/(1-F7)) -> 9433.9623 | H7: =IF($A7="", "", _xlfn.XLOOKUP($B7, YearlyParamsB!$A:$A, YearlyParamsB!$E:$E, 0)) -> 120000 | I7: =IF($A7="", "", E7*SGRate) -> 27600 | J7: =IFERROR(IF($A7="", "", _xlfn.XLOOKUP($B7, YearlyParamsB!$A:$A, YearlyParamsB!$I:$I, 0)), 0) -> 124900 | K7: =IFERROR(IF($A6="", "", IF(B7<>B6,0,Q6)), 0) -> 51012.356 | L7: =IFERROR(IF($A6="","",IF(B7<>B6, 0, L6 + MIN(G6+L6/PPYB, J6-K6)*F6)), 0) -> 23975.807 | M7: =IF($A7="", "", G7) -> 9433.9623 | N7: =IFERROR(IF($A7="", "", J7-K7), 0) -> 73887.644 | O7: =IFERROR(IF($A7="", "", MIN(G7,N7)), 0) -> 9433.9623 | P7: =IFERROR(IF($A7="", "", MIN(G7+L7/PPYB,N7)*F7 + MAX(0, MIN(G7+L7/PPYB,N7) - MIN(G7,N7))), 0) -> 7370.9986 | Q7: =IFERROR(IF($A7="", "", K7+MIN(G7+L7/PPYB,N7)), 0) -> 62444.302 | R7: =IFERROR(IF($A6="", "", IF(B7<>B6,P7,R6+P7)), 0) -> 35189.35 | S7: =IFERROR(IF($A7="", "", S6+P7), 0) -> 35189.35
A8: =IF(ROW()-1 <= TotalPeriodsB, ROW()-1, "") -> 7 | B8: =IF(ROW()-1 <= TotalPeriodsB, YEAR(StartYear) + INT((ROW()-2)/PPYB), "") -> 2027 | C8: =IF($A8="", "", MOD($A8-1, PPYB)+1) -> 7 | D8: =IF($A8="", "", C8=PPYB) -> FALSE | E8: =IF($A8="","",IncB*(1+Inflation)^((B8 - YEAR(StartYear)))) -> 230000 | F8: {=IF($A8="", "", MRate(E8))} -> 0.47 | G8: =IF($A8="", "", AfterTaxB/(1-F8)) -> 9433.9623 | H8: =IF($A8="", "", _xlfn.XLOOKUP($B8, YearlyParamsB!$A:$A, YearlyParamsB!$E:$E, 0)) -> 120000 | I8: =IF($A8="", "", E8*SGRate) -> 27600 | J8: =IFERROR(IF($A8="", "", _xlfn.XLOOKUP($B8, YearlyParamsB!$A:$A, YearlyParamsB!$I:$I, 0)), 0) -> 124900 | K8: =IFERROR(IF($A7="", "", IF(B8<>B7,0,Q7)), 0) -> 62444.302 | L8: =IFERROR(IF($A7="","",IF(B8<>B7, 0, L7 + MIN(G7+L7/PPYB, J7-K7)*F7)), 0) -> 29348.822 | M8: =IF($A8="", "", G8) -> 9433.9623 | N8: =IFERROR(IF($A8="", "", J8-K8), 0) -> 62455.698 | O8: =IFERROR(IF($A8="", "", MIN(G8,N8)), 0) -> 9433.9623 | P8: =IFERROR(IF($A8="", "", MIN(G8+L8/PPYB,N8)*F8 + MAX(0, MIN(G8+L8/PPYB,N8) - MIN(G8,N8))), 0) -> 8029.1929 | Q8: =IFERROR(IF($A8="", "", K8+MIN(G8+L8/PPYB,N8)), 0) -> 74323.999 | R8: =IFERROR(IF($A7="", "", IF(B8<>B7,P8,R7+P8)), 0) -> 43218.543 | S8: =IFERROR(IF($A8="", "", S7+P8), 0) -> 43218.543
A9: =IF(ROW()-1 <= TotalPeriodsB, ROW()-1, "") -> 8 | B9: =IF(ROW()-1 <= TotalPeriodsB, YEAR(StartYear) + INT((ROW()-2)/PPYB), "") -> 2027 | C9: =IF($A9="", "", MOD($A9-1, PPYB)+1) -> 8 | D9: =IF($A9="", "", C9=PPYB) -> FALSE | E9: =IF($A9="","",IncB*(1+Inflation)^((B9 - YEAR(StartYear)))) -> 230000 | F9: {=IF($A9="", "", MRate(E9))} -> 0.47 | G9: =IF($A9="", "", AfterTaxB/(1-F9)) -> 9433.9623 | H9: =IF($A9="", "", _xlfn.XLOOKUP($B9, YearlyParamsB!$A:$A, YearlyParamsB!$E:$E, 0)) -> 120000 | I9: =IF($A9="", "", E9*SGRate) -> 27600 | J9: =IFERROR(IF($A9="", "", _xlfn.XLOOKUP($B9, YearlyParamsB!$A:$A, YearlyParamsB!$I:$I, 0)), 0) -> 124900 | K9: =IFERROR(IF($A8="", "", IF(B9<>B8,0,Q8)), 0) -> 74323.999 | L9: =IFERROR(IF($A8="","",IF(B9<>B8, 0, L8 + MIN(G8+L8/PPYB, J8-K8)*F8)), 0) -> 34932.28 | M9: =IF($A9="", "", G9) -> 9433.9623 | N9: =IFERROR(IF($A9="", "", J9-K9), 0) -> 50576.001 | O9: =IFERROR(IF($A9="", "", MIN(G9,N9)), 0) -> 9433.9623 | P9: =IFERROR(IF($A9="", "", MIN(G9+L9/PPYB,N9)*F9 + MAX(0, MIN(G9+L9/PPYB,N9) - MIN(G9,N9))), 0) -> 8713.1665 | Q9: =IFERROR(IF($A9="", "", K9+MIN(G9+L9/PPYB,N9)), 0) -> 86668.985 | R9: =IFERROR(IF($A8="", "", IF(B9<>B8,P9,R8+P9)), 0) -> 51931.71 | S9: =IFERROR(IF($A9="", "", S8+P9), 0) -> 51931.71
A10: =IF(ROW()-1 <= TotalPeriodsB, ROW()-1, "") -> 9 | B10: =IF(ROW()-1 <= TotalPeriodsB, YEAR(StartYear) + INT((ROW()-2)/PPYB), "") -> 2027 | C10: =IF($A10="", "", MOD($A10-1, PPYB)+1) -> 9 | D10: =IF($A10="", "", C10=PPYB) -> FALSE | E10: =IF($A10="","",IncB*(1+Inflation)^((B10 - YEAR(StartYear)))) -> 230000 | F10: {=IF($A10="", "", MRate(E10))} -> 0.47 | G10: =IF($A10="", "", AfterTaxB/(1-F10)) -> 9433.9623 | H10: =IF($A10="", "", _xlfn.XLOOKUP($B10, YearlyParamsB!$A:$A, YearlyParamsB!$E:$E, 0)) -> 120000 | I10: =IF($A10="", "", E10*SGRate) -> 27600 | J10: =IFERROR(IF($A10="", "", _xlfn.XLOOKUP($B10, YearlyParamsB!$A:$A, YearlyParamsB!$I:$I, 0)), 0) -> 124900 | K10: =IFERROR(IF($A9="", "", IF(B10<>B9,0,Q9)), 0) -> 86668.985 | L10: =IFERROR(IF($A9="","",IF(B10<>B9, 0, L9 + MIN(G9+L9/PPYB, J9-K9)*F9)), 0) -> 40734.423 | M10: =IF($A10="", "", G10) -> 9433.9623 | N10: =IFERROR(IF($A10="", "", J10-K10), 0) -> 38231.015 | O10: =IFERROR(IF($A10="", "", MIN(G10,N10)), 0) -> 9433.9623 | P10: =IFERROR(IF($A10="", "", MIN(G10+L10/PPYB,N10)*F10 + MAX(0, MIN(G10+L10/PPYB,N10) - MIN(G10,N10))), 0) -> 9423.9291 | Q10: =IFERROR(IF($A10="", "", K10+MIN(G10+L10/PPYB,N10)), 0) -> 99497.482 | R10: =IFERROR(IF($A9="", "", IF(B10<>B9,P10,R9+P10)), 0) -> 61355.639 | S10: =IFERROR(IF($A10="", "", S9+P10), 0) -> 61355.639
A11: =IF(ROW()-1 <= TotalPeriodsB, ROW()-1, "") -> 10 | B11: =IF(ROW()-1 <= TotalPeriodsB, YEAR(StartYear) + INT((ROW()-2)/PPYB), "") -> 2027 | C11: =IF($A11="", "", MOD($A11-1, PPYB)+1) -> 10 | D11: =IF($A11="", "", C11=PPYB) -> FALSE | E11: =IF($A11="","",IncB*(1+Inflation)^((B11 - YEAR(StartYear)))) -> 230000 | F11: {=IF($A11="", "", MRate(E11))} -> 0.47 | G11: =IF($A11="", "", AfterTaxB/(1-F11)) -> 9433.9623 | H11: =IF($A11="", "", _xlfn.XLOOKUP($B11, YearlyParamsB!$A:$A, YearlyParamsB!$E:$E, 0)) -> 120000 | I11: =IF($A11="", "", E11*SGRate) -> 27600 | J11: =IFERROR(IF($A11="", "", _xlfn.XLOOKUP($B11, YearlyParamsB!$A:$A, YearlyParamsB!$I:$I, 0)), 0) -> 124900 | K11: =IFERROR(IF($A10="", "", IF(B11<>B10,0,Q10)), 0) -> 99497.482 | L11: =IFERROR(IF($A10="","",IF(B11<>B10, 0, L10 + MIN(G10+L10/PPYB, J10-K10)*F10)), 0) -> 46763.817 | M11: =IF($A11="", "", G11) -> 9433.9623 | N11: =IFERROR(IF($A11="", "", J11-K11), 0) -> 25402.518 | O11: =IFERROR(IF($A11="", "", MIN(G11,N11)), 0) -> 9433.9623 | P11: =IFERROR(IF($A11="", "", MIN(G11+L11/PPYB,N11)*F11 + MAX(0, MIN(G11+L11/PPYB,N11) - MIN(G11,N11))), 0) -> 10162.53 | Q11: =IFERROR(IF($A11="", "", K11+MIN(G11+L11/PPYB,N11)), 0) -> 112828.43 | R11: =IFERROR(IF($A10="", "", IF(B11<>B10,P11,R10+P11)), 0) -> 71518.169 | S11: =IFERROR(IF($A11="", "", S10+P11), 0) -> 71518.169
A12: =IF(ROW()-1 <= TotalPeriodsB, ROW()-1, "") -> 11 | B12: =IF(ROW()-1 <= TotalPeriodsB, YEAR(StartYear) + INT((ROW()-2)/PPYB), "") -> 2027 | C12: =IF($A12="", "", MOD($A12-1, PPYB)+1) -> 11 | D12: =IF($A12="", "", C12=PPYB) -> FALSE | E12: =IF($A12="","",IncB*(1+Inflation)^((B12 - YEAR(StartYear)))) -> 230000 | F12: {=IF($A12="", "", MRate(E12))} -> 0.47 | G12: =IF($A12="", "", AfterTaxB/(1-F12)) -> 9433.9623 | H12: =IF($A12="", "", _xlfn.XLOOKUP($B12, YearlyParamsB!$A:$A, YearlyParamsB!$E:$E, 0)) -> 120000 | I12: =IF($A12="", "", E12*SGRate) -> 27600 | J12: =IFERROR(IF($A12="", "", _xlfn.XLOOKUP($B12, YearlyParamsB!$A:$A, YearlyParamsB!$I:$I, 0)), 0) -> 124900 | K12: =IFERROR(IF($A11="", "", IF(B12<>B11,0,Q11)), 0) -> 112828.43 | L12: =IFERROR(IF($A11="","",IF(B12<>B11, 0, L11 + MIN(G11+L11/PPYB, J11-K11)*F11)), 0) -> 53029.362 | M12: =IF($A12="", "", G12) -> 9433.9623 | N12: =IFERROR(IF($A12="", "", J12-K12), 0) -> 12071.571 | O12: =IFERROR(IF($A12="", "", MIN(G12,N12)), 0) -> 9433.9623 | P12: =IFERROR(IF($A12="", "", MIN(G12+L12/PPYB,N12)*F12 + MAX(0, MIN(G12+L12/PPYB,N12) - MIN(G12,N12))), 0) -> 8311.2464 | Q12: =IFERROR(IF($A12="", "", K12+MIN(G12+L12/PPYB,N12)), 0) -> 124900 | R12: =IFERROR(IF($A11="", "", IF(B12<>B11,P12,R11+P12)), 0) -> 79829.415 | S12: =IFERROR(IF($A12="", "", S11+P12), 0) -> 79829.415
A13: =IF(ROW()-1 <= TotalPeriodsB, ROW()-1, "") -> 12 | B13: =IF(ROW()-1 <= TotalPeriodsB, YEAR(StartYear) + INT((ROW()-2)/PPYB), "") -> 2027 | C13: =IF($A13="", "", MOD($A13-1, PPYB)+1) -> 12 | D13: =IF($A13="", "", C13=PPYB) -> TRUE | E13: =IF($A13="","",IncB*(1+Inflation)^((B13 - YEAR(StartYear)))) -> 230000 | F13: {=IF($A13="", "", MRate(E13))} -> 0.47 | G13: =IF($A13="", "", AfterTaxB/(1-F13)) -> 9433.9623 | H13: =IF($A13="", "", _xlfn.XLOOKUP($B13, YearlyParamsB!$A:$A, YearlyParamsB!$E:$E, 0)) -> 120000 | I13: =IF($A13="", "", E13*SGRate) -> 27600 | J13: =IFERROR(IF($A13="", "", _xlfn.XLOOKUP($B13, YearlyParamsB!$A:$A, YearlyParamsB!$I:$I, 0)), 0) -> 124900 | K13: =IFERROR(IF($A12="", "", IF(B13<>B12,0,Q12)), 0) -> 124900 | L13: =IFERROR(IF($A12="","",IF(B13<>B12, 0, L12 + MIN(G12+L12/PPYB, J12-K12)*F12)), 0) -> 58703 | M13: =IF($A13="", "", G13) -> 9433.9623 | N13: =IFERROR(IF($A13="", "", J13-K13), 0) -> 0 | O13: =IFERROR(IF($A13="", "", MIN(G13,N13)), 0) -> 0 | P13: =IFERROR(IF($A13="", "", MIN(G13+L13/PPYB,N13)*F13 + MAX(0, MIN(G13+L13/PPYB,N13) - MIN(G13,N13))), 0) -> 0 | Q13: =IFERROR(IF($A13="", "", K13+MIN(G13+L13/PPYB,N13)), 0) -> 124900 | R13: =IFERROR(IF($A12="", "", IF(B13<>B12,P13,R12+P13)), 0) -> 79829.415 | S13: =IFERROR(IF($A13="", "", S12+P13), 0) -> 79829.415
A14: =IF(ROW()-1 <= TotalPeriodsB, ROW()-1, "") -> 13 | B14: =IF(ROW()-1 <= TotalPeriodsB, YEAR(StartYear) + INT((ROW()-2)/PPYB), "") -> 2028 | C14: =IF($A14="", "", MOD($A14-1, PPYB)+1) -> 1 | D14: =IF($A14="", "", C14=PPYB) -> FALSE | E14: =IF($A14="","",IncB*(1+Inflation)^((B14 - YEAR(StartYear)))) -> 235750 | F14: {=IF($A14="", "", MRate(E14))} -> 0.47 | G14: =IF($A14="", "", AfterTaxB/(1-F14)) -> 9433.9623 | H14: =IF($A14="", "", _xlfn.XLOOKUP($B14, YearlyParamsB!$A:$A, YearlyParamsB!$E:$E, 0)) -> 0 | I14: =IF($A14="", "", E14*SGRate) -> 28290 | J14: =IFERROR(IF($A14="", "", _xlfn.XLOOKUP($B14, YearlyParamsB!$A:$A, YearlyParamsB!$I:$I, 0)), 0) -> 4210 | K14: =IFERROR(IF($A13="", "", IF(B14<>B13,0,Q13)), 0) -> 0 | L14: =IFERROR(IF($A13="","",IF(B14<>B13, 0, L13 + MIN(G13+L13/PPYB, J13-K13)*F13)), 0) -> 0 | M14: =IF($A14="", "", G14) -> 9433.9623 | N14: =IFERROR(IF($A14="", "", J14-K14), 0) -> 4210 | O14: =IFERROR(IF($A14="", "", MIN(G14,N14)), 0) -> 4210 | P14: =IFERROR(IF($A14="", "", MIN(G14+L14/PPYB,N14)*F14 + MAX(0, MIN(G14+L14/PPYB,N14) - MIN(G14,N14))), 0) -> 1978.7 | Q14: =IFERROR(IF($A14="", "", K14+MIN(G14+L14/PPYB,N14)), 0) -> 4210 | R14: =IFERROR(IF($A13="", "", IF(B14<>B13,P14,R13+P14)), 0) -> 1978.7 | S14: =IFERROR(IF($A14="", "", S13+P14), 0) -> 81808.115
A15: =IF(ROW()-1 <= TotalPeriodsB, ROW()-1, "") -> 14 | B15: =IF(ROW()-1 <= TotalPeriodsB, YEAR(StartYear) + INT((ROW()-2)/PPYB), "") -> 2028 | C15: =IF($A15="", "", MOD($A15-1, PPYB)+1) -> 2 | D15: =IF($A15="", "", C15=PPYB) -> FALSE | E15: =IF($A15="","",IncB*(1+Inflation)^((B15 - YEAR(StartYear)))) -> 235750 | F15: {=IF($A15="", "", MRate(E15))} -> 0.47 | G15: =IF($A15="", "", AfterTaxB/(1-F15)) -> 9433.9623 | H15: =IF($A15="", "", _xlfn.XLOOKUP($B15, YearlyParamsB!$A:$A, YearlyParamsB!$E:$E, 0)) -> 0 | I15: =IF($A15="", "", E15*SGRate) -> 28290 | J15: =IFERROR(IF($A15="", "", _xlfn.XLOOKUP($B15, YearlyParamsB!$A:$A, YearlyParamsB!$I:$I, 0)), 0) -> 4210 | K15: =IFERROR(IF($A14="", "", IF(B15<>B14,0,Q14)), 0) -> 4210 | L15: =IFERROR(IF($A14="","",IF(B15<>B14, 0, L14 + MIN(G14+L14/PPYB, J14-K14)*F14)), 0) -> 1978.7 | M15: =IF($A15="", "", G15) -> 9433.9623 | N15: =IFERROR(IF($A15="", "", J15-K15), 0) -> 0 | O15: =IFERROR(IF($A15="", "", MIN(G15,N15)), 0) -> 0 | P15: =IFERROR(IF($A15="", "", MIN(G15+L15/PPYB,N15)*F15 + MAX(0, MIN(G15+L15/PPYB,N15) - MIN(G15,N15))), 0) -> 0 | Q15: =IFERROR(IF($A15="", "", K15+MIN(G15+L15/PPYB,N15)), 0) -> 4210 | R15: =IFERROR(IF($A14="", "", IF(B15<>B14,P15,R14+P15)), 0) -> 1978.7 | S15: =IFERROR(IF($A15="", "", S14+P15), 0) -> 81808.115
A16: =IF(ROW()-1 <= TotalPeriodsB, ROW()-1, "") -> 15 | B16: =IF(ROW()-1 <= TotalPeriodsB, YEAR(StartYear) + INT((ROW()-2)/PPYB), "") -> 2028 | C16: =IF($A16="", "", MOD($A16-1, PPYB)+1) -> 3 | D16: =IF($A16="", "", C16=PPYB) -> FALSE | E16: =IF($A16="","",IncB*(1+Inflation)^((B16 - YEAR(StartYear)))) -> 235750 | F16: {=IF($A16="", "", MRate(E16))} -> 0.47 | G16: =IF($A16="", "", AfterTaxB/(1-F16)) -> 9433.9623 | H16: =IF($A16="", "", _xlfn.XLOOKUP($B16, YearlyParamsB!$A:$A, YearlyParamsB!$E:$E, 0)) -> 0 | I16: =IF($A16="", "", E16*SGRate) -> 28290 | J16: =IFERROR(IF($A16="", "", _xlfn.XLOOKUP($B16, YearlyParamsB!$A:$A, YearlyParamsB!$I:$I, 0)), 0) -> 4210 | K16: =IFERROR(IF($A15="", "", IF(B16<>B15,0,Q15)), 0) -> 4210 | L16: =IFERROR(IF($A15="","",IF(B16<>B15, 0, L15 + MIN(G15+L15/PPYB, J15-K15)*F15)), 0) -> 1978.7 | M16: =IF($A16="", "", G16) -> 9433.9623 | N16: =IFERROR(IF($A16="", "", J16-K16), 0) -> 0 | O16: =IFERROR(IF($A16="", "", MIN(G16,N16)), 0) -> 0 | P16: =IFERROR(IF($A16="", "", MIN(G16+L16/PPYB,N16)*F16 + MAX(0, MIN(G16+L16/PPYB,N16) - MIN(G16,N16))), 0) -> 0 | Q16: =IFERROR(IF($A16="", "", K16+MIN(G16+L16/PPYB,N16)), 0) -> 4210 | R16: =IFERROR(IF($A15="", "", IF(B16<>B15,P16,R15+P16)), 0) -> 1978.7 | S16: =IFERROR(IF($A16="", "", S15+P16), 0) -> 81808.115
... A181: =IF(ROW()-1 <= TotalPeriodsB, ROW()-1, "") -> 180 | B181: =IF(ROW()-1 <= TotalPeriodsB, YEAR(StartYear) + INT((ROW()-2)/PPYB), "") -> 2041 | C181: =IF($A181="", "", MOD($A181-1, PPYB)+1) -> 12 | D181: =IF($A181="", "", C181=PPYB) -> TRUE | E181: =IF($A181="","",IncB*(1+Inflation)^((B181 - YEAR(StartYear)))) -> 324983.98 | F181: {=IF($A181="", "", MRate(E181))} -> 0.47 | G181: =IF($A181="", "", AfterTaxB/(1-F181)) -> 9433.9623 | H181: =IF($A181="", "", _xlfn.XLOOKUP($B181, YearlyParamsB!$A:$A, YearlyParamsB!$E:$E, 0)) -> 0 | I181: =IF($A181="", "", E181*SGRate) -> 38998.077 | J181: =IFERROR(IF($A181="", "", _xlfn.XLOOKUP($B181, YearlyParamsB!$A:$A, YearlyParamsB!$I:$I, 0)), 0) -> 11001.923 | K181: =IFERROR(IF($A180="", "", IF(B181<>B180,0,Q180)), 0) -> 11001.923 | L181: =IFERROR(IF($A180="","",IF(B181<>B180, 0, L180 + MIN(G180+L180/PPYB, J180-K180)*F180)), 0) -> 5170.9036 | M181: =IF($A181="", "", G181) -> 9433.9623 | N181: =IFERROR(IF($A181="", "", J181-K181), 0) -> 0 | O181: =IFERROR(IF($A181="", "", MIN(G181,N181)), 0) -> 0 | P181: =IFERROR(IF($A181="", "", MIN(G181+L181/PPYB,N181)*F181 + MAX(0, MIN(G181+L181/PPYB,N181) - MIN(G181,N181))), 0) -> 0 | Q181: =IFERROR(IF($A181="", "", K181+MIN(G181+L181/PPYB,N181)), 0) -> 11001.923 | R181: =IFERROR(IF($A180="", "", IF(B181<>B180,P181,R180+P181)), 0) -> 5170.9036 | S181: =IFERROR(IF($A181="", "", S180+P181), 0) -> 131613.46

Sheet Loan
A1: Scenario C: SuperSmart Strategy(Ofset & Annual Sweep) | AP1: LOAN COMPARISON SUMMARY
Q2: Scenario A: Current Trajectory (No offset or extra payment) | AC2: Scenario B: Extra after-tax payment to mortgage( no offset) | AX2: PeriodsPerYear | AY2: =_xlfn.XLOOKUP(FreqA,FreqLookup[Frequency],FreqLookup[PeriodsPerYear]) -> 12
A3: Period | B3: Year | C3: PeriodInYear | D3: OpeningBalance | E3: OffsetBeforeSweep | F3: EffectiveBalance | G3: Interest | H3: TotalPayment | I3: Principal | J3: ClosingBalance | K3: InterestSaved | L3: CumulativeInterestSaved | M3: CumulativeInterest | N3: CumulativePayments | O3: LoanYear | Q3: Period | R3: Year | S3: PeriodInYear | T3: OpeningBalance | U3: Interest | V3: TotalPayment | W3: Principal | X3: ClosingBalance | Y3: CumulativeInterest | Z3: CumulativePayments | AA3: LoanYear | AC3: Period | AD3: Year | AE3: PeriodInYear | AF3: OpeningBalance | AG3: Interest | AH3: TotalPayment | AI3: Principal | AJ3: ClosingBalance | AK3: CumulativeInterest | AL3: CumulativePayments | AM3: LoanYear | AP3: Metric | AR3: Scenario A: Current | AT3: Scenario B: Extra Payments | AV3: Scenario C: SuperSmart | AX3: TotalPeriods | AY3: =MAX(ProjYearsA,ProjYearsB)*PPY_Loan -> 180
A4: =IF(ROW()-3<=TotalPeriods_Loan,ROW()-3,"") -> 1 | B4: =IF($A4="", "", YEAR(StartYear) + INT(($A4-1)/PPY_Loan)) -> 2027 | C4: =IF($A4="", "", MOD(A4-1, PPY_Loan)+1) -> 1 | D4: =IFERROR(IF($A4="", "",LoanAmount), 0) -> 2500000 | E4: =IFERROR(IF($A4="", "", _xlfn.XLOOKUP(A4,Offset!A:A,Offset!I:I, 0)), 0) -> 25157.667 | F4: =IFERROR(IF($A4="", "", MAX(0, D4 - E4)), 0) -> 2474842.3 | G4: =IFERROR(IF($A4="", "", F4*(LoanRate/PPY_Loan)), 0) -> 16498.949 | H4: =IFERROR(IF($A4="", "", IF(D4<=0, 0, MIN(StdPayment, D4+G4))), 0) -> 27061.315 | I4: =IFERROR(IF($A4="", "", IF(D4<=0, 0,H4-G4)), 0) -> 10562.366 | J4: =IFERROR(IF($A4="", "", IF(D4<=0, 0, MAX(0, D4-I4))), 0) -> 2489437.6 | K4: =IFERROR(IF($A4="", "", IF(D4<=0, 0, E4*(LoanRate/PPY_Loan))), 0) -> 167.71778 | L4: =IF($A4="", "", K4) -> 167.71778 | M4: =IF($A4="","",G4) -> 16498.949 | N4: =IF($A4="","",H4) -> 27061.315 | O4: =IF($A4="","",1) -> 1 | Q4: =IF(ROW()-3<=TotalPeriods_Loan,ROW()-3,"") -> 1 | R4: =IF($Q4="", "", YEAR(StartYear) + INT(($Q4-1)/PPY_Loan)) -> 2027 | S4: =IF($Q4="", "", MOD(Q4-1, PPY_Loan)+1) -> 1 | T4: =IFERROR(IF($Q4="", "",LoanAmount), 0) -> 2500000 | U4: =IFERROR(IF($Q4="", "", T4*(LoanRate/PPY_Loan)), 0) -> 16666.667 | V4: =IFERROR(IF($Q4="", "", IF(T4<=0, 0, MIN(StdPayment, T4+U4))), 0) -> 27061.315 | W4: =IFERROR(IF($Q4="", "", IF(T4<=0, 0, V4-U4)), 0) -> 10394.648 | X4: =IFERROR(IF($Q4="", "", IF(T4<=0, 0, MAX(0, T4-W4))), 0) -> 2489605.4 | Y4: =IF($Q4="","",U4) -> 16666.667 | Z4: =IF($Q4="","",V4) -> 27061.315 | AA4: =IF($Q4="","",1) -> 1 | AC4: =IF(ROW()-3<=TotalPeriods_Loan,ROW()-3,"") -> 1 | AD4: =IF($AC4="", "", YEAR(StartYear) + INT(($AC4-1)/PPY_Loan)) -> 2027 | AE4: =IF($AC4="", "", MOD(AC4-1, PPY_Loan)+1) -> 1 | AF4: =IFERROR(IF($AC4="", "",LoanAmount), 0) -> 2500000 | AG4: =IFERROR(IF($AC4="", "", AF4*(LoanRate/PPY_Loan)), 0) -> 16666.667 | AH4: =IFERROR(IF($AC4="", "", IF(AF4<=0, 0, MIN(StdPayment+IF(ISBLANK(ExtraRepay),0,ExtraRepay), AF4+AG4))), 0) -> 27711.315 | AI4: =IFERROR(IF($AC4="", "", IF(AF4<=0, 0, AH4-AG4)), 0) -> 11044.648 | AJ4: =IFERROR(IF($AC4="", "", IF(AF4<=0, 0, MAX(0, AF4-AI4))), 0) -> 2488955.4 | AK4: =IF($AC4="","",AG4) -> 16666.667 | AL4: =IF($AC4="","",AH4) -> 27711.315 | AM4: =IF($AC4="","",1) -> 1 | AP4: Total Interest Paid | AR4: =SUMIF($Q$4:$Q$279,">0",U$4:U$279) -> 1396829.3 | AT4: =SUMIF($AC$4:$AC$279,">0",AG$4:AG$279) -> 1336478.7 | AV4: =SUMIF($A$4:$A$279,">0",G$4:G$279) -> 1338584.5 | AX4: StandardPayment | AY4: =IF(ISBLANK(BaseRepayment), PMT(LoanRate/PPY_Loan, LoanTerm*PPY_Loan, -LoanAmount), MAX(BaseRepayment, PMT(LoanRate/PPY_Loan, LoanTerm*PPY_Loan, -LoanAmount))) -> 27061.315
A5: =IF(ROW()-3<=TotalPeriods_Loan,ROW()-3,"") -> 2 | B5: =IF($A5="", "", YEAR(StartYear) + INT(($A5-1)/PPY_Loan)) -> 2027 | C5: =IF($A5="", "", MOD(A5-1, PPY_Loan)+1) -> 2 | D5: =IFERROR(IF($A5="", "",IF(J4<=0, 0,J4)), 0) -> 2489437.6 | E5: =IFERROR(IF($A5="", "", _xlfn.XLOOKUP(A5,Offset!A:A,Offset!I:I, 0)), 0) -> 50315.333 | F5: =IFERROR(IF($A5="", "", MAX(0, D5 - E5)), 0) -> 2439122.3 | G5: =IFERROR(IF($A5="", "", F5*(LoanRate/PPY_Loan)), 0) -> 16260.815 | H5: =IFERROR(IF($A5="", "", IF(D5<=0, 0, MIN(StdPayment, D5+G5))), 0) -> 27061.315 | I5: =IFERROR(IF($A5="", "", IF(D5<=0, 0,H5-G5)), 0) -> 10800.499 | J5: =IFERROR(IF($A5="", "", IF(D5<=0, 0, MAX(0, D5-I5))), 0) -> 2478637.1 | K5: =IFERROR(IF($A5="", "", IF(D5<=0, 0, E5*(LoanRate/PPY_Loan))), 0) -> 335.43556 | L5: =IFERROR(IF($A5="", "", L4+K5), 0) -> 503.15333 | M5: =IF($A5="","",M4+G5) -> 32759.764 | N5: =IF($A5="","",N4+H5) -> 54122.629 | O5: =IF($A5="","",IF(B5<>B4,O4+1,O4)) -> 1 | Q5: =IF(ROW()-3<=TotalPeriods_Loan,ROW()-3,"") -> 2 | R5: =IF($Q5="", "", YEAR(StartYear) + INT(($Q5-1)/PPY_Loan)) -> 2027 | S5: =IF($Q5="", "", MOD(Q5-1, PPY_Loan)+1) -> 2 | T5: =IFERROR(IF($Q5="", "",IF(X4<=0, 0, X4)), 0) -> 2489605.4 | U5: =IFERROR(IF($Q5="", "", T5*(LoanRate/PPY_Loan)), 0) -> 16597.369 | V5: =IFERROR(IF($Q5="", "", IF(T5<=0, 0, MIN(StdPayment, T5+U5))), 0) -> 27061.315 | W5: =IFERROR(IF($Q5="", "", IF(T5<=0, 0, V5-U5)), 0) -> 10463.946 | X5: =IFERROR(IF($Q5="", "", IF(T5<=0, 0, MAX(0, T5-W5))), 0) -> 2479141.4 | Y5: =IF($Q5="","",Y4+U5) -> 33264.036 | Z5: =IF($Q5="","",Z4+V5) -> 54122.629 | AA5: =IF($Q5="","",IF(R5<>R4,AA4+1,AA4)) -> 1 | AC5: =IF(ROW()-3<=TotalPeriods_Loan,ROW()-3,"") -> 2 | AD5: =IF($AC5="", "", YEAR(StartYear) + INT(($AC5-1)/PPY_Loan)) -> 2027 | AE5: =IF($AC5="", "", MOD(AC5-1, PPY_Loan)+1) -> 2 | AF5: =IFERROR(IF($AC5="", "",IF(AJ4<=0, 0, AJ4)), 0) -> 2488955.4 | AG5: =IFERROR(IF($AC5="", "", AF5*(LoanRate/PPY_Loan)), 0) -> 16593.036 | AH5: =IFERROR(IF($AC5="", "", IF(AF5<=0, 0, MIN(StdPayment+IF(ISBLANK(ExtraRepay),0,ExtraRepay), AF5+AG5))), 0) -> 27711.315 | AI5: =IFERROR(IF($AC5="", "", IF(AF5<=0, 0, AH5-AG5)), 0) -> 11118.279 | AJ5: =IFERROR(IF($AC5="", "", IF(AF5<=0, 0, MAX(0, AF5-AI5))), 0) -> 2477837.1 | AK5: =IF($AC5="","",AK4+AG5) -> 33259.702 | AL5: =IF($AC5="","",AL4+AH5) -> 55422.629 | AM5: =IF($AC5="","",IF(AD5<>AD4,AM4+1,AM4)) -> 1 | AP5: Total Principal Paid | AR5: =SUMIF($Q$4:$Q$279,">0",W$4:W$279) -> 2500000 | AT5: =SUMIF($AC$4:$AC$279,">0",AI$4:AI$279) -> 2500000 | AV5: =SUMIF($A$4:$A$279,">0",I$4:I$279) -> 2500000
A6: =IF(ROW()-3<=TotalPeriods_Loan,ROW()-3,"") -> 3 | B6: =IF($A6="", "", YEAR(StartYear) + INT(($A6-1)/PPY_Loan)) -> 2027 | C6: =IF($A6="", "", MOD(A6-1, PPY_Loan)+1) -> 3 | D6: =IFERROR(IF($A6="", "",IF(J5<=0, 0,J5)), 0) -> 2478637.1 | E6: =IFERROR(IF($A6="", "", _xlfn.XLOOKUP(A6,Offset!A:A,Offset!I:I, 0)), 0) -> 75473 | F6: =IFERROR(IF($A6="", "", MAX(0, D6 - E6)), 0) -> 2403164.1 | G6: =IFERROR(IF($A6="", "", F6*(LoanRate/PPY_Loan)), 0) -> 16021.094 | H6: =IFERROR(IF($A6="", "", IF(D6<=0, 0, MIN(StdPayment, D6+G6))), 0) -> 27061.315 | I6: =IFERROR(IF($A6="", "", IF(D6<=0, 0,H6-G6)), 0) -> 11040.22 | J6: =IFERROR(IF($A6="", "", IF(D6<=0, 0, MAX(0, D6-I6))), 0) -> 2467596.9 | K6: =IFERROR(IF($A6="", "", IF(D6<=0, 0, E6*(LoanRate/PPY_Loan))), 0) -> 503.15333 | L6: =IFERROR(IF($A6="", "", L5+K6), 0) -> 1006.3067 | M6: =IF($A6="","",M5+G6) -> 48780.858 | N6: =IF($A6="","",N5+H6) -> 81183.944 | O6: =IF($A6="","",IF(B6<>B5,O5+1,O5)) -> 1 | Q6: =IF(ROW()-3<=TotalPeriods_Loan,ROW()-3,"") -> 3 | R6: =IF($Q6="", "", YEAR(StartYear) + INT(($Q6-1)/PPY_Loan)) -> 2027 | S6: =IF($Q6="", "", MOD(Q6-1, PPY_Loan)+1) -> 3 | T6: =IFERROR(IF($Q6="", "",IF(X5<=0, 0, X5)), 0) -> 2479141.4 | U6: =IFERROR(IF($Q6="", "", T6*(LoanRate/PPY_Loan)), 0) -> 16527.609 | V6: =IFERROR(IF($Q6="", "", IF(T6<=0, 0, MIN(StdPayment, T6+U6))), 0) -> 27061.315 | W6: =IFERROR(IF($Q6="", "", IF(T6<=0, 0, V6-U6)), 0) -> 10533.705 | X6: =IFERROR(IF($Q6="", "", IF(T6<=0, 0, MAX(0, T6-W6))), 0) -> 2468607.7 | Y6: =IF($Q6="","",Y5+U6) -> 49791.645 | Z6: =IF($Q6="","",Z5+V6) -> 81183.944 | AA6: =IF($Q6="","",IF(R6<>R5,AA5+1,AA5)) -> 1 | AC6: =IF(ROW()-3<=TotalPeriods_Loan,ROW()-3,"") -> 3 | AD6: =IF($AC6="", "", YEAR(StartYear) + INT(($AC6-1)/PPY_Loan)) -> 2027 | AE6: =IF($AC6="", "", MOD(AC6-1, PPY_Loan)+1) -> 3 | AF6: =IFERROR(IF($AC6="", "",IF(AJ5<=0, 0, AJ5)), 0) -> 2477837.1 | AG6: =IFERROR(IF($AC6="", "", AF6*(LoanRate/PPY_Loan)), 0) -> 16518.914 | AH6: =IFERROR(IF($AC6="", "", IF(AF6<=0, 0, MIN(StdPayment+IF(ISBLANK(ExtraRepay),0,ExtraRepay), AF6+AG6))), 0) -> 27711.315 | AI6: =IFERROR(IF($AC6="", "", IF(AF6<=0, 0, AH6-AG6)), 0) -> 11192.401 | AJ6: =IFERROR(IF($AC6="", "", IF(AF6<=0, 0, MAX(0, AF6-AI6))), 0) -> 2466644.7 | AK6: =IF($AC6="","",AK5+AG6) -> 49778.616 | AL6: =IF($AC6="","",AL5+AH6) -> 83133.944 | AM6: =IF($AC6="","",IF(AD6<>AD5,AM5+1,AM5)) -> 1 | AP6: Ending Balance (Final Period) | AR6: =X279 | AT6: =AJ279 | AV6: =J279
A7: =IF(ROW()-3<=TotalPeriods_Loan,ROW()-3,"") -> 4 | B7: =IF($A7="", "", YEAR(StartYear) + INT(($A7-1)/PPY_Loan)) -> 2027 | C7: =IF($A7="", "", MOD(A7-1, PPY_Loan)+1) -> 4 | D7: =IFERROR(IF($A7="", "",IF(J6<=0, 0,J6)), 0) -> 2467596.9 | E7: =IFERROR(IF($A7="", "", _xlfn.XLOOKUP(A7,Offset!A:A,Offset!I:I, 0)), 0) -> 100630.67 | F7: =IFERROR(IF($A7="", "", MAX(0, D7 - E7)), 0) -> 2366966.2 | G7: =IFERROR(IF($A7="", "", F7*(LoanRate/PPY_Loan)), 0) -> 15779.775 | H7: =IFERROR(IF($A7="", "", IF(D7<=0, 0, MIN(StdPayment, D7+G7))), 0) -> 27061.315 | I7: =IFERROR(IF($A7="", "", IF(D7<=0, 0,H7-G7)), 0) -> 11281.54 | J7: =IFERROR(IF($A7="", "", IF(D7<=0, 0, MAX(0, D7-I7))), 0) -> 2456315.4 | K7: =IFERROR(IF($A7="", "", IF(D7<=0, 0, E7*(LoanRate/PPY_Loan))), 0) -> 670.87111 | L7: =IFERROR(IF($A7="", "", L6+K7), 0) -> 1677.1778 | M7: =IF($A7="","",M6+G7) -> 64560.633 | N7: =IF($A7="","",N6+H7) -> 108245.26 | O7: =IF($A7="","",IF(B7<>B6,O6+1,O6)) -> 1 | Q7: =IF(ROW()-3<=TotalPeriods_Loan,ROW()-3,"") -> 4 | R7: =IF($Q7="", "", YEAR(StartYear) + INT(($Q7-1)/PPY_Loan)) -> 2027 | S7: =IF($Q7="", "", MOD(Q7-1, PPY_Loan)+1) -> 4 | T7: =IFERROR(IF($Q7="", "",IF(X6<=0, 0, X6)), 0) -> 2468607.7 | U7: =IFERROR(IF($Q7="", "", T7*(LoanRate/PPY_Loan)), 0) -> 16457.385 | V7: =IFERROR(IF($Q7="", "", IF(T7<=0, 0, MIN(StdPayment, T7+U7))), 0) -> 27061.315 | W7: =IFERROR(IF($Q7="", "", IF(T7<=0, 0, V7-U7)), 0) -> 10603.93 | X7: =IFERROR(IF($Q7="", "", IF(T7<=0, 0, MAX(0, T7-W7))), 0) -> 2458003.8 | Y7: =IF($Q7="","",Y6+U7) -> 66249.03 | Z7: =IF($Q7="","",Z6+V7) -> 108245.26 | AA7: =IF($Q7="","",IF(R7<>R6,AA6+1,AA6)) -> 1 | AC7: =IF(ROW()-3<=TotalPeriods_Loan,ROW()-3,"") -> 4 | AD7: =IF($AC7="", "", YEAR(StartYear) + INT(($AC7-1)/PPY_Loan)) -> 2027 | AE7: =IF($AC7="", "", MOD(AC7-1, PPY_Loan)+1) -> 4 | AF7: =IFERROR(IF($AC7="", "",IF(AJ6<=0, 0, AJ6)), 0) -> 2466644.7 | AG7: =IFERROR(IF($AC7="", "", AF7*(LoanRate/PPY_Loan)), 0) -> 16444.298 | AH7: =IFERROR(IF($AC7="", "", IF(AF7<=0, 0, MIN(StdPayment+IF(ISBLANK(ExtraRepay),0,ExtraRepay), AF7+AG7))), 0) -> 27711.315 | AI7: =IFERROR(IF($AC7="", "", IF(AF7<=0, 0, AH7-AG7)), 0) -> 11267.017 | AJ7: =IFERROR(IF($AC7="", "", IF(AF7<=0, 0, MAX(0, AF7-AI7))), 0) -> 2455377.7 | AK7: =IF($AC7="","",AK6+AG7) -> 66222.914 | AL7: =IF($AC7="","",AL6+AH7) -> 110845.26 | AM7: =IF($AC7="","",IF(AD7<>AD6,AM6+1,AM6)) -> 1 | AP7: Periods Until Loan Paid Off | AR7: {=IFERROR(MATCH(TRUE,INDEX(X$4:X$279<=0,0),0),">"&AY3)} -> 145 | AT7: {=IFERROR(MATCH(TRUE,INDEX(AJ$4:AJ$279<=0,0),0),">"&AY3)} -> 139 | AV7: {=IFERROR(MATCH(TRUE,INDEX(J$4:J$279<=0,0),0),">"&AY3)} -> 142
A8: =IF(ROW()-3<=TotalPeriods_Loan,ROW()-3,"") -> 5 | B8: =IF($A8="", "", YEAR(StartYear) + INT(($A8-1)/PPY_Loan)) -> 2027 | C8: =IF($A8="", "", MOD(A8-1, PPY_Loan)+1) -> 5 | D8: =IFERROR(IF($A8="", "",IF(J7<=0, 0,J7)), 0) -> 2456315.4 | E8: =IFERROR(IF($A8="", "", _xlfn.XLOOKUP(A8,Offset!A:A,Offset!I:I, 0)), 0) -> 125788.33 | F8: =IFERROR(IF($A8="", "", MAX(0, D8 - E8)), 0) -> 2330527 | G8: =IFERROR(IF($A8="", "", F8*(LoanRate/PPY_Loan)), 0) -> 15536.847 | H8: =IFERROR(IF($A8="", "", IF(D8<=0, 0, MIN(StdPayment, D8+G8))), 0) -> 27061.315 | I8: =IFERROR(IF($A8="", "", IF(D8<=0, 0,H8-G8)), 0) -> 11524.468 | J8: =IFERROR(IF($A8="", "", IF(D8<=0, 0, MAX(0, D8-I8))), 0) -> 2444790.9 | K8: =IFERROR(IF($A8="", "", IF(D8<=0, 0, E8*(LoanRate/PPY_Loan))), 0) -> 838.58889 | L8: =IFERROR(IF($A8="", "", L7+K8), 0) -> 2515.7667 | M8: =IF($A8="","",M7+G8) -> 80097.48 | N8: =IF($A8="","",N7+H8) -> 135306.57 | O8: =IF($A8="","",IF(B8<>B7,O7+1,O7)) -> 1 | Q8: =IF(ROW()-3<=TotalPeriods_Loan,ROW()-3,"") -> 5 | R8: =IF($Q8="", "", YEAR(StartYear) + INT(($Q8-1)/PPY_Loan)) -> 2027 | S8: =IF($Q8="", "", MOD(Q8-1, PPY_Loan)+1) -> 5 | T8: =IFERROR(IF($Q8="", "",IF(X7<=0, 0, X7)), 0) -> 2458003.8 | U8: =IFERROR(IF($Q8="", "", T8*(LoanRate/PPY_Loan)), 0) -> 16386.692 | V8: =IFERROR(IF($Q8="", "", IF(T8<=0, 0, MIN(StdPayment, T8+U8))), 0) -> 27061.315 | W8: =IFERROR(IF($Q8="", "", IF(T8<=0, 0, V8-U8)), 0) -> 10674.623 | X8: =IFERROR(IF($Q8="", "", IF(T8<=0, 0, MAX(0, T8-W8))), 0) -> 2447329.1 | Y8: =IF($Q8="","",Y7+U8) -> 82635.722 | Z8: =IF($Q8="","",Z7+V8) -> 135306.57 | AA8: =IF($Q8="","",IF(R8<>R7,AA7+1,AA7)) -> 1 | AC8: =IF(ROW()-3<=TotalPeriods_Loan,ROW()-3,"") -> 5 | AD8: =IF($AC8="", "", YEAR(StartYear) + INT(($AC8-1)/PPY_Loan)) -> 2027 | AE8: =IF($AC8="", "", MOD(AC8-1, PPY_Loan)+1) -> 5 | AF8: =IFERROR(IF($AC8="", "",IF(AJ7<=0, 0, AJ7)), 0) -> 2455377.7 | AG8: =IFERROR(IF($AC8="", "", AF8*(LoanRate/PPY_Loan)), 0) -> 16369.184 | AH8: =IFERROR(IF($AC8="", "", IF(AF8<=0, 0, MIN(StdPayment+IF(ISBLANK(ExtraRepay),0,ExtraRepay), AF8+AG8))), 0) -> 27711.315 | AI8: =IFERROR(IF($AC8="", "", IF(AF8<=0, 0, AH8-AG8)), 0) -> 11342.13 | AJ8: =IFERROR(IF($AC8="", "", IF(AF8<=0, 0, MAX(0, AF8-AI8))), 0) -> 2444035.5 | AK8: =IF($AC8="","",AK7+AG8) -> 82592.098 | AL8: =IF($AC8="","",AL7+AH8) -> 138556.57 | AM8: =IF($AC8="","",IF(AD8<>AD7,AM7+1,AM7)) -> 1 | AP8: Years Until Loan Paid Off | AR8: =IF(ISNUMBER(AR7), AR7/PPY_Loan, AR7) -> 12.083333 | AT8: =IF(ISNUMBER(AT7), AT7/PPY_Loan, AT7) -> 11.583333 | AV8: =IF(ISNUMBER(AV7), AV7/PPY_Loan, AV7) -> 11.833333
A9: =IF(ROW()-3<=TotalPeriods_Loan,ROW()-3,"") -> 6 | B9: =IF($A9="", "", YEAR(StartYear) + INT(($A9-1)/PPY_Loan)) -> 2027 | C9: =IF($A9="", "", MOD(A9-1, PPY_Loan)+1) -> 6 | D9: =IFERROR(IF($A9="", "",IF(J8<=0, 0,J8)), 0) -> 2444790.9 | E9: =IFERROR(IF($A9="", "", _xlfn.XLOOKUP(A9,Offset!A:A,Offset!I:I, 0)), 0) -> 150946 | F9: =IFERROR(IF($A9="", "", MAX(0, D9 - E9)), 0) -> 2293844.9 | G9: =IFERROR(IF($A9="", "", F9*(LoanRate/PPY_Loan)), 0) -> 15292.299 | H9: =IFERROR(IF($A9="", "", IF(D9<=0, 0, MIN(StdPayment, D9+G9))), 0) -> 27061.315 | I9: =IFERROR(IF($A9="", "", IF(D9<=0, 0,H9-G9)), 0) -> 11769.015 | J9: =IFERROR(IF($A9="", "", IF(D9<=0, 0, MAX(0, D9-I9))), 0) -> 2433021.9 | K9: =IFERROR(IF($A9="", "", IF(D9<=0, 0, E9*(LoanRate/PPY_Loan))), 0) -> 1006.3067 | L9: =IFERROR(IF($A9="", "", L8+K9), 0) -> 3522.0733 | M9: =IF($A9="","",M8+G9) -> 95389.78 | N9: =IF($A9="","",N8+H9) -> 162367.89 | O9: =IF($A9="","",IF(B9<>B8,O8+1,O8)) -> 1 | Q9: =IF(ROW()-3<=TotalPeriods_Loan,ROW()-3,"") -> 6 | R9: =IF($Q9="", "", YEAR(StartYear) + INT(($Q9-1)/PPY_Loan)) -> 2027 | S9: =IF($Q9="", "", MOD(Q9-1, PPY_Loan)+1) -> 6 | T9: =IFERROR(IF($Q9="", "",IF(X8<=0, 0, X8)), 0) -> 2447329.1 | U9: =IFERROR(IF($Q9="", "", T9*(LoanRate/PPY_Loan)), 0) -> 16315.528 | V9: =IFERROR(IF($Q9="", "", IF(T9<=0, 0, MIN(StdPayment, T9+U9))), 0) -> 27061.315 | W9: =IFERROR(IF($Q9="", "", IF(T9<=0, 0, V9-U9)), 0) -> 10745.787 | X9: =IFERROR(IF($Q9="", "", IF(T9<=0, 0, MAX(0, T9-W9))), 0) -> 2436583.4 | Y9: =IF($Q9="","",Y8+U9) -> 98951.249 | Z9: =IF($Q9="","",Z8+V9) -> 162367.89 | AA9: =IF($Q9="","",IF(R9<>R8,AA8+1,AA8)) -> 1 | AC9: =IF(ROW()-3<=TotalPeriods_Loan,ROW()-3,"") -> 6 | AD9: =IF($AC9="", "", YEAR(StartYear) + INT(($AC9-1)/PPY_Loan)) -> 2027 | AE9: =IF($AC9="", "", MOD(AC9-1, PPY_Loan)+1) -> 6 | AF9: =IFERROR(IF($AC9="", "",IF(AJ8<=0, 0, AJ8)), 0) -> 2444035.5 | AG9: =IFERROR(IF($AC9="", "", AF9*(LoanRate/PPY_Loan)), 0) -> 16293.57 | AH9: =IFERROR(IF($AC9="", "", IF(AF9<=0, 0, MIN(StdPayment+IF(ISBLANK(ExtraRepay),0,ExtraRepay), AF9+AG9))), 0) -> 27711.315 | AI9: =IFERROR(IF($AC9="", "", IF(AF9<=0, 0, AH9-AG9)), 0) -> 11417.744 | AJ9: =IFERROR(IF($AC9="", "", IF(AF9<=0, 0, MAX(0, AF9-AI9))), 0) -> 2432617.8 | AK9: =IF($AC9="","",AK8+AG9) -> 98885.669 | AL9: =IF($AC9="","",AL8+AH9) -> 166267.89 | AM9: =IF($AC9="","",IF(AD9<>AD8,AM8+1,AM8)) -> 1 | AP9: Interest Saved vs Scenario A | AR9: - | AT9: =AR4-AT4 -> 60350.65 | AV9: =AR4-AV4 -> 58244.817
A10: =IF(ROW()-3<=TotalPeriods_Loan,ROW()-3,"") -> 7 | B10: =IF($A10="", "", YEAR(StartYear) + INT(($A10-1)/PPY_Loan)) -> 2027 | C10: =IF($A10="", "", MOD(A10-1, PPY_Loan)+1) -> 7 | D10: =IFERROR(IF($A10="", "",IF(J9<=0, 0,J9)), 0) -> 2433021.9 | E10: =IFERROR(IF($A10="", "", _xlfn.XLOOKUP(A10,Offset!A:A,Offset!I:I, 0)), 0) -> 176103.67 | F10: =IFERROR(IF($A10="", "", MAX(0, D10 - E10)), 0) -> 2256918.2 | G10: =IFERROR(IF($A10="", "", F10*(LoanRate/PPY_Loan)), 0) -> 15046.122 | H10: =IFERROR(IF($A10="", "", IF(D10<=0, 0, MIN(StdPayment, D10+G10))), 0) -> 27061.315 | I10: =IFERROR(IF($A10="", "", IF(D10<=0, 0,H10-G10)), 0) -> 12015.193 | J10: =IFERROR(IF($A10="", "", IF(D10<=0, 0, MAX(0, D10-I10))), 0) -> 2421006.7 | K10: =IFERROR(IF($A10="", "", IF(D10<=0, 0, E10*(LoanRate/PPY_Loan))), 0) -> 1174.0244 | L10: =IFERROR(IF($A10="", "", L9+K10), 0) -> 4696.0978 | M10: =IF($A10="","",M9+G10) -> 110435.9 | N10: =IF($A10="","",N9+H10) -> 189429.2 | O10: =IF($A10="","",IF(B10<>B9,O9+1,O9)) -> 1 | Q10: =IF(ROW()-3<=TotalPeriods_Loan,ROW()-3,"") -> 7 | R10: =IF($Q10="", "", YEAR(StartYear) + INT(($Q10-1)/PPY_Loan)) -> 2027 | S10: =IF($Q10="", "", MOD(Q10-1, PPY_Loan)+1) -> 7 | T10: =IFERROR(IF($Q10="", "",IF(X9<=0, 0, X9)), 0) -> 2436583.4 | U10: =IFERROR(IF($Q10="", "", T10*(LoanRate/PPY_Loan)), 0) -> 16243.889 | V10: =IFERROR(IF($Q10="", "", IF(T10<=0, 0, MIN(StdPayment, T10+U10))), 0) -> 27061.315 | W10: =IFERROR(IF($Q10="", "", IF(T10<=0, 0, V10-U10)), 0) -> 10817.426 | X10: =IFERROR(IF($Q10="", "", IF(T10<=0, 0, MAX(0, T10-W10))), 0) -> 2425765.9 | Y10: =IF($Q10="","",Y9+U10) -> 115195.14 | Z10: =IF($Q10="","",Z9+V10) -> 189429.2 | AA10: =IF($Q10="","",IF(R10<>R9,AA9+1,AA9)) -> 1 | AC10: =IF(ROW()-3<=TotalPeriods_Loan,ROW()-3,"") -> 7 | AD10: =IF($AC10="", "", YEAR(StartYear) + INT(($AC10-1)/PPY_Loan)) -> 2027 | AE10: =IF($AC10="", "", MOD(AC10-1, PPY_Loan)+1) -> 7 | AF10: =IFERROR(IF($AC10="", "",IF(AJ9<=0, 0, AJ9)), 0) -> 2432617.8 | AG10: =IFERROR(IF($AC10="", "", AF10*(LoanRate/PPY_Loan)), 0) -> 16217.452 | AH10: =IFERROR(IF($AC10="", "", IF(AF10<=0, 0, MIN(StdPayment+IF(ISBLANK(ExtraRepay),0,ExtraRepay), AF10+AG10))), 0) -> 27711.315 | AI10: =IFERROR(IF($AC10="", "", IF(AF10<=0, 0, AH10-AG10)), 0) -> 11493.863 | AJ10: =IFERROR(IF($AC10="", "", IF(AF10<=0, 0, MAX(0, AF10-AI10))), 0) -> 2421123.9 | AK10: =IF($AC10="","",AK9+AG10) -> 115103.12 | AL10: =IF($AC10="","",AL9+AH10) -> 193979.2 | AM10: =IF($AC10="","",IF(AD10<>AD9,AM9+1,AM9)) -> 1 | AP10: Time Saved vs Scenario A (months) | AR10: - | AT10: =IF(AND(ISNUMBER(AR7),ISNUMBER(AT7)), AR7-AT7, "N/A") -> 6 | AV10: =IF(AND(ISNUMBER(AR7),ISNUMBER(AV7)), AR7-AV7, "N/A") -> 3
A11: =IF(ROW()-3<=TotalPeriods_Loan,ROW()-3,"") -> 8 | B11: =IF($A11="", "", YEAR(StartYear) + INT(($A11-1)/PPY_Loan)) -> 2027 | C11: =IF($A11="", "", MOD(A11-1, PPY_Loan)+1) -> 8 | D11: =IFERROR(IF($A11="", "",IF(J10<=0, 0,J10)), 0) -> 2421006.7 | E11: =IFERROR(IF($A11="", "", _xlfn.XLOOKUP(A11,Offset!A:A,Offset!I:I, 0)), 0) -> 201261.33 | F11: =IFERROR(IF($A11="", "", MAX(0, D11 - E11)), 0) -> 2219745.4 | G11: =IFERROR(IF($A11="", "", F11*(LoanRate/PPY_Loan)), 0) -> 14798.302 | H11: =IFERROR(IF($A11="", "", IF(D11<=0, 0, MIN(StdPayment, D11+G11))), 0) -> 27061.315 | I11: =IFERROR(IF($A11="", "", IF(D11<=0, 0,H11-G11)), 0) -> 12263.012 | J11: =IFERROR(IF($A11="", "", IF(D11<=0, 0, MAX(0, D11-I11))), 0) -> 2408743.7 | K11: =IFERROR(IF($A11="", "", IF(D11<=0, 0, E11*(LoanRate/PPY_Loan))), 0) -> 1341.7422 | L11: =IFERROR(IF($A11="", "", L10+K11), 0) -> 6037.84 | M11: =IF($A11="","",M10+G11) -> 125234.2 | N11: =IF($A11="","",N10+H11) -> 216490.52 | O11: =IF($A11="","",IF(B11<>B10,O10+1,O10)) -> 1 | Q11: =IF(ROW()-3<=TotalPeriods_Loan,ROW()-3,"") -> 8 | R11: =IF($Q11="", "", YEAR(StartYear) + INT(($Q11-1)/PPY_Loan)) -> 2027 | S11: =IF($Q11="", "", MOD(Q11-1, PPY_Loan)+1) -> 8 | T11: =IFERROR(IF($Q11="", "",IF(X10<=0, 0, X10)), 0) -> 2425765.9 | U11: =IFERROR(IF($Q11="", "", T11*(LoanRate/PPY_Loan)), 0) -> 16171.773 | V11: =IFERROR(IF($Q11="", "", IF(T11<=0, 0, MIN(StdPayment, T11+U11))), 0) -> 27061.315 | W11: =IFERROR(IF($Q11="", "", IF(T11<=0, 0, V11-U11)), 0) -> 10889.542 | X11: =IFERROR(IF($Q11="", "", IF(T11<=0, 0, MAX(0, T11-W11))), 0) -> 2414876.4 | Y11: =IF($Q11="","",Y10+U11) -> 131366.91 | Z11: =IF($Q11="","",Z10+V11) -> 216490.52 | AA11: =IF($Q11="","",IF(R11<>R10,AA10+1,AA10)) -> 1 | AC11: =IF(ROW()-3<=TotalPeriods_Loan,ROW()-3,"") -> 8 | AD11: =IF($AC11="", "", YEAR(StartYear) + INT(($AC11-1)/PPY_Loan)) -> 2027 | AE11: =IF($AC11="", "", MOD(AC11-1, PPY_Loan)+1) -> 8 | AF11: =IFERROR(IF($AC11="", "",IF(AJ10<=0, 0, AJ10)), 0) -> 2421123.9 | AG11: =IFERROR(IF($AC11="", "", AF11*(LoanRate/PPY_Loan)), 0) -> 16140.826 | AH11: =IFERROR(IF($AC11="", "", IF(AF11<=0, 0, MIN(StdPayment+IF(ISBLANK(ExtraRepay),0,ExtraRepay), AF11+AG11))), 0) -> 27711.315 | AI11: =IFERROR(IF($AC11="", "", IF(AF11<=0, 0, AH11-AG11)), 0) -> 11570.488 | AJ11: =IFERROR(IF($AC11="", "", IF(AF11<=0, 0, MAX(0, AF11-AI11))), 0) -> 2409553.4 | AK11: =IF($AC11="","",AK10+AG11) -> 131243.95 | AL11: =IF($AC11="","",AL10+AH11) -> 221690.52 | AM11: =IF($AC11="","",IF(AD11<>AD10,AM10+1,AM10)) -> 1 | AP11: Cumulative Interest Saved (SuperSmart) | AV11: =L279
A12: =IF(ROW()-3<=TotalPeriods_Loan,ROW()-3,"") -> 9 | B12: =IF($A12="", "", YEAR(StartYear) + INT(($A12-1)/PPY_Loan)) -> 2027 | C12: =IF($A12="", "", MOD(A12-1, PPY_Loan)+1) -> 9 | D12: =IFERROR(IF($A12="", "",IF(J11<=0, 0,J11)), 0) -> 2408743.7 | E12: =IFERROR(IF($A12="", "", _xlfn.XLOOKUP(A12,Offset!A:A,Offset!I:I, 0)), 0) -> 226419 | F12: =IFERROR(IF($A12="", "", MAX(0, D12 - E12)), 0) -> 2182324.7 | G12: =IFERROR(IF($A12="", "", F12*(LoanRate/PPY_Loan)), 0) -> 14548.831 | H12: =IFERROR(IF($A12="", "", IF(D12<=0, 0, MIN(StdPayment, D12+G12))), 0) -> 27061.315 | I12: =IFERROR(IF($A12="", "", IF(D12<=0, 0,H12-G12)), 0) -> 12512.483 | J12: =IFERROR(IF($A12="", "", IF(D12<=0, 0, MAX(0, D12-I12))), 0) -> 2396231.2 | K12: =IFERROR(IF($A12="", "", IF(D12<=0, 0, E12*(LoanRate/PPY_Loan))), 0) -> 1509.46 | L12: =IFERROR(IF($A12="", "", L11+K12), 0) -> 7547.3 | M12: =IF($A12="","",M11+G12) -> 139783.03 | N12: =IF($A12="","",N11+H12) -> 243551.83 | O12: =IF($A12="","",IF(B12<>B11,O11+1,O11)) -> 1 | Q12: =IF(ROW()-3<=TotalPeriods_Loan,ROW()-3,"") -> 9 | R12: =IF($Q12="", "", YEAR(StartYear) + INT(($Q12-1)/PPY_Loan)) -> 2027 | S12: =IF($Q12="", "", MOD(Q12-1, PPY_Loan)+1) -> 9 | T12: =IFERROR(IF($Q12="", "",IF(X11<=0, 0, X11)), 0) -> 2414876.4 | U12: =IFERROR(IF($Q12="", "", T12*(LoanRate/PPY_Loan)), 0) -> 16099.176 | V12: =IFERROR(IF($Q12="", "", IF(T12<=0, 0, MIN(StdPayment, T12+U12))), 0) -> 27061.315 | W12: =IFERROR(IF($Q12="", "", IF(T12<=0, 0, V12-U12)), 0) -> 10962.139 | X12: =IFERROR(IF($Q12="", "", IF(T12<=0, 0, MAX(0, T12-W12))), 0) -> 2403914.3 | Y12: =IF($Q12="","",Y11+U12) -> 147466.09 | Z12: =IF($Q12="","",Z11+V12) -> 243551.83 | AA12: =IF($Q12="","",IF(R12<>R11,AA11+1,AA11)) -> 1 | AC12: =IF(ROW()-3<=TotalPeriods_Loan,ROW()-3,"") -> 9 | AD12: =IF($AC12="", "", YEAR(StartYear) + INT(($AC12-1)/PPY_Loan)) -> 2027 | AE12: =IF($AC12="", "", MOD(AC12-1, PPY_Loan)+1) -> 9 | AF12: =IFERROR(IF($AC12="", "",IF(AJ11<=0, 0, AJ11)), 0) -> 2409553.4 | AG12: =IFERROR(IF($AC12="", "", AF12*(LoanRate/PPY_Loan)), 0) -> 16063.69 | AH12: =IFERROR(IF($AC12="", "", IF(AF12<=0, 0, MIN(StdPayment+IF(ISBLANK(ExtraRepay),0,ExtraRepay), AF12+AG12))), 0) -> 27711.315 | AI12: =IFERROR(IF($AC12="", "", IF(AF12<=0, 0, AH12-AG12)), 0) -> 11647.625 | AJ12: =IFERROR(IF($AC12="", "", IF(AF12<=0, 0, MAX(0, AF12-AI12))), 0) -> 2397905.8 | AK12: =IF($AC12="","",AK11+AG12) -> 147307.64 | AL12: =IF($AC12="","",AL11+AH12) -> 249401.83 | AM12: =IF($AC12="","",IF(AD12<>AD11,AM11+1,AM11)) -> 1 | AP12: Total Offset Deposits Swept to Super | AV12: =SUM(Offset!J3:J182) -> 757330.2
A13: =IF(ROW()-3<=TotalPeriods_Loan,ROW()-3,"") -> 10 | B13: =IF($A13="", "", YEAR(StartYear) + INT(($A13-1)/PPY_Loan)) -> 2027 | C13: =IF($A13="", "", MOD(A13-1, PPY_Loan)+1) -> 10 | D13: =IFERROR(IF($A13="", "",IF(J12<=0, 0,J12)), 0) -> 2396231.2 | E13: =IFERROR(IF($A13="", "", _xlfn.XLOOKUP(A13,Offset!A:A,Offset!I:I, 0)), 0) -> 251576.67 | F13: =IFERROR(IF($A13="", "", MAX(0, D13 - E13)), 0) -> 2144654.5 | G13: =IFERROR(IF($A13="", "", F13*(LoanRate/PPY_Loan)), 0) -> 14297.697 | H13: =IFERROR(IF($A13="", "", IF(D13<=0, 0, MIN(StdPayment, D13+G13))), 0) -> 27061.315 | I13: =IFERROR(IF($A13="", "", IF(D13<=0, 0,H13-G13)), 0) -> 12763.618 | J13: =IFERROR(IF($A13="", "", IF(D13<=0, 0, MAX(0, D13-I13))), 0) -> 2383467.6 | K13: =IFERROR(IF($A13="", "", IF(D13<=0, 0, E13*(LoanRate/PPY_Loan))), 0) -> 1677.1778 | L13: =IFERROR(IF($A13="", "", L12+K13), 0) -> 9224.4778 | M13: =IF($A13="","",M12+G13) -> 154080.73 | N13: =IF($A13="","",N12+H13) -> 270613.15 | O13: =IF($A13="","",IF(B13<>B12,O12+1,O12)) -> 1 | Q13: =IF(ROW()-3<=TotalPeriods_Loan,ROW()-3,"") -> 10 | R13: =IF($Q13="", "", YEAR(StartYear) + INT(($Q13-1)/PPY_Loan)) -> 2027 | S13: =IF($Q13="", "", MOD(Q13-1, PPY_Loan)+1) -> 10 | T13: =IFERROR(IF($Q13="", "",IF(X12<=0, 0, X12)), 0) -> 2403914.3 | U13: =IFERROR(IF($Q13="", "", T13*(LoanRate/PPY_Loan)), 0) -> 16026.095 | V13: =IFERROR(IF($Q13="", "", IF(T13<=0, 0, MIN(StdPayment, T13+U13))), 0) -> 27061.315 | W13: =IFERROR(IF($Q13="", "", IF(T13<=0, 0, V13-U13)), 0) -> 11035.22 | X13: =IFERROR(IF($Q13="", "", IF(T13<=0, 0, MAX(0, T13-W13))), 0) -> 2392879 | Y13: =IF($Q13="","",Y12+U13) -> 163492.18 | Z13: =IF($Q13="","",Z12+V13) -> 270613.15 | AA13: =IF($Q13="","",IF(R13<>R12,AA12+1,AA12)) -> 1 | AC13: =IF(ROW()-3<=TotalPeriods_Loan,ROW()-3,"") -> 10 | AD13: =IF($AC13="", "", YEAR(StartYear) + INT(($AC13-1)/PPY_Loan)) -> 2027 | AE13: =IF($AC13="", "", MOD(AC13-1, PPY_Loan)+1) -> 10 | AF13: =IFERROR(IF($AC13="", "",IF(AJ12<=0, 0, AJ12)), 0) -> 2397905.8 | AG13: =IFERROR(IF($AC13="", "", AF13*(LoanRate/PPY_Loan)), 0) -> 15986.039 | AH13: =IFERROR(IF($AC13="", "", IF(AF13<=0, 0, MIN(StdPayment+IF(ISBLANK(ExtraRepay),0,ExtraRepay), AF13+AG13))), 0) -> 27711.315 | AI13: =IFERROR(IF($AC13="", "", IF(AF13<=0, 0, AH13-AG13)), 0) -> 11725.276 | AJ13: =IFERROR(IF($AC13="", "", IF(AF13<=0, 0, MAX(0, AF13-AI13))), 0) -> 2386180.5 | AK13: =IF($AC13="","",AK12+AG13) -> 163293.67 | AL13: =IF($AC13="","",AL12+AH13) -> 277113.15 | AM13: =IF($AC13="","",IF(AD13<>AD12,AM12+1,AM12)) -> 1 | AP13: Total Payments Made | AR13: =SUMIF($Q$4:$Q$279,">0",V$4:V$279) -> 3896829.3 | AT13: =SUMIF($AC$4:$AC$279,">0",AH$4:AH$279) -> 3836478.7 | AV13: =SUMIF($A$4:$A$279,">0",H$4:H$279) -> 3838584.5
A14: =IF(ROW()-3<=TotalPeriods_Loan,ROW()-3,"") -> 11 | B14: =IF($A14="", "", YEAR(StartYear) + INT(($A14-1)/PPY_Loan)) -> 2027 | C14: =IF($A14="", "", MOD(A14-1, PPY_Loan)+1) -> 11 | D14: =IFERROR(IF($A14="", "",IF(J13<=0, 0,J13)), 0) -> 2383467.6 | E14: =IFERROR(IF($A14="", "", _xlfn.XLOOKUP(A14,Offset!A:A,Offset!I:I, 0)), 0) -> 276734.33 | F14: =IFERROR(IF($A14="", "", MAX(0, D14 - E14)), 0) -> 2106733.3 | G14: =IFERROR(IF($A14="", "", F14*(LoanRate/PPY_Loan)), 0) -> 14044.888 | H14: =IFERROR(IF($A14="", "", IF(D14<=0, 0, MIN(StdPayment, D14+G14))), 0) -> 27061.315 | I14: =IFERROR(IF($A14="", "", IF(D14<=0, 0,H14-G14)), 0) -> 13016.426 | J14: =IFERROR(IF($A14="", "", IF(D14<=0, 0, MAX(0, D14-I14))), 0) -> 2370451.2 | K14: =IFERROR(IF($A14="", "", IF(D14<=0, 0, E14*(LoanRate/PPY_Loan))), 0) -> 1844.8956 | L14: =IFERROR(IF($A14="", "", L13+K14), 0) -> 11069.373 | M14: =IF($A14="","",M13+G14) -> 168125.62 | N14: =IF($A14="","",N13+H14) -> 297674.46 | O14: =IF($A14="","",IF(B14<>B13,O13+1,O13)) -> 1 | Q14: =IF(ROW()-3<=TotalPeriods_Loan,ROW()-3,"") -> 11 | R14: =IF($Q14="", "", YEAR(StartYear) + INT(($Q14-1)/PPY_Loan)) -> 2027 | S14: =IF($Q14="", "", MOD(Q14-1, PPY_Loan)+1) -> 11 | T14: =IFERROR(IF($Q14="", "",IF(X13<=0, 0, X13)), 0) -> 2392879 | U14: =IFERROR(IF($Q14="", "", T14*(LoanRate/PPY_Loan)), 0) -> 15952.527 | V14: =IFERROR(IF($Q14="", "", IF(T14<=0, 0, MIN(StdPayment, T14+U14))), 0) -> 27061.315 | W14: =IFERROR(IF($Q14="", "", IF(T14<=0, 0, V14-U14)), 0) -> 11108.788 | X14: =IFERROR(IF($Q14="", "", IF(T14<=0, 0, MAX(0, T14-W14))), 0) -> 2381770.2 | Y14: =IF($Q14="","",Y13+U14) -> 179444.71 | Z14: =IF($Q14="","",Z13+V14) -> 297674.46 | AA14: =IF($Q14="","",IF(R14<>R13,AA13+1,AA13)) -> 1 | AC14: =IF(ROW()-3<=TotalPeriods_Loan,ROW()-3,"") -> 11 | AD14: =IF($AC14="", "", YEAR(StartYear) + INT(($AC14-1)/PPY_Loan)) -> 2027 | AE14: =IF($AC14="", "", MOD(AC14-1, PPY_Loan)+1) -> 11 | AF14: =IFERROR(IF($AC14="", "",IF(AJ13<=0, 0, AJ13)), 0) -> 2386180.5 | AG14: =IFERROR(IF($AC14="", "", AF14*(LoanRate/PPY_Loan)), 0) -> 15907.87 | AH14: =IFERROR(IF($AC14="", "", IF(AF14<=0, 0, MIN(StdPayment+IF(ISBLANK(ExtraRepay),0,ExtraRepay), AF14+AG14))), 0) -> 27711.315 | AI14: =IFERROR(IF($AC14="", "", IF(AF14<=0, 0, AH14-AG14)), 0) -> 11803.444 | AJ14: =IFERROR(IF($AC14="", "", IF(AF14<=0, 0, MAX(0, AF14-AI14))), 0) -> 2374377.1 | AK14: =IF($AC14="","",AK13+AG14) -> 179201.54 | AL14: =IF($AC14="","",AL13+AH14) -> 304824.46 | AM14: =IF($AC14="","",IF(AD14<>AD13,AM13+1,AM13)) -> 1 | AP14: Total Cash Outlay Savings vs A | AR14: - | AT14: =AR13-AT13 -> 60350.65 | AV14: =AR13-AV13 -> 58244.817
A15: =IF(ROW()-3<=TotalPeriods_Loan,ROW()-3,"") -> 12 | B15: =IF($A15="", "", YEAR(StartYear) + INT(($A15-1)/PPY_Loan)) -> 2027 | C15: =IF($A15="", "", MOD(A15-1, PPY_Loan)+1) -> 12 | D15: =IFERROR(IF($A15="", "",IF(J14<=0, 0,J14)), 0) -> 2370451.2 | E15: =IFERROR(IF($A15="", "", _xlfn.XLOOKUP(A15,Offset!A:A,Offset!I:I, 0)), 0) -> 301892 | F15: =IFERROR(IF($A15="", "", MAX(0, D15 - E15)), 0) -> 2068559.2 | G15: =IFERROR(IF($A15="", "", F15*(LoanRate/PPY_Loan)), 0) -> 13790.394 | H15: =IFERROR(IF($A15="", "", IF(D15<=0, 0, MIN(StdPayment, D15+G15))), 0) -> 27061.315 | I15: =IFERROR(IF($A15="", "", IF(D15<=0, 0,H15-G15)), 0) -> 13270.92 | J15: =IFERROR(IF($A15="", "", IF(D15<=0, 0, MAX(0, D15-I15))), 0) -> 2357180.2 | K15: =IFERROR(IF($A15="", "", IF(D15<=0, 0, E15*(LoanRate/PPY_Loan))), 0) -> 2012.6133 | L15: =IFERROR(IF($A15="", "", L14+K15), 0) -> 13081.987 | M15: =IF($A15="","",M14+G15) -> 181916.01 | N15: =IF($A15="","",N14+H15) -> 324735.78 | O15: =IF($A15="","",IF(B15<>B14,O14+1,O14)) -> 1 | Q15: =IF(ROW()-3<=TotalPeriods_Loan,ROW()-3,"") -> 12 | R15: =IF($Q15="", "", YEAR(StartYear) + INT(($Q15-1)/PPY_Loan)) -> 2027 | S15: =IF($Q15="", "", MOD(Q15-1, PPY_Loan)+1) -> 12 | T15: =IFERROR(IF($Q15="", "",IF(X14<=0, 0, X14)), 0) -> 2381770.2 | U15: =IFERROR(IF($Q15="", "", T15*(LoanRate/PPY_Loan)), 0) -> 15878.468 | V15: =IFERROR(IF($Q15="", "", IF(T15<=0, 0, MIN(StdPayment, T15+U15))), 0) -> 27061.315 | W15: =IFERROR(IF($Q15="", "", IF(T15<=0, 0, V15-U15)), 0) -> 11182.846 | X15: =IFERROR(IF($Q15="", "", IF(T15<=0, 0, MAX(0, T15-W15))), 0) -> 2370587.4 | Y15: =IF($Q15="","",Y14+U15) -> 195323.18 | Z15: =IF($Q15="","",Z14+V15) -> 324735.78 | AA15: =IF($Q15="","",IF(R15<>R14,AA14+1,AA14)) -> 1 | AC15: =IF(ROW()-3<=TotalPeriods_Loan,ROW()-3,"") -> 12 | AD15: =IF($AC15="", "", YEAR(StartYear) + INT(($AC15-1)/PPY_Loan)) -> 2027 | AE15: =IF($AC15="", "", MOD(AC15-1, PPY_Loan)+1) -> 12 | AF15: =IFERROR(IF($AC15="", "",IF(AJ14<=0, 0, AJ14)), 0) -> 2374377.1 | AG15: =IFERROR(IF($AC15="", "", AF15*(LoanRate/PPY_Loan)), 0) -> 15829.181 | AH15: =IFERROR(IF($AC15="", "", IF(AF15<=0, 0, MIN(StdPayment+IF(ISBLANK(ExtraRepay),0,ExtraRepay), AF15+AG15))), 0) -> 27711.315 | AI15: =IFERROR(IF($AC15="", "", IF(AF15<=0, 0, AH15-AG15)), 0) -> 11882.134 | AJ15: =IFERROR(IF($AC15="", "", IF(AF15<=0, 0, MAX(0, AF15-AI15))), 0) -> 2362495 | AK15: =IF($AC15="","",AK14+AG15) -> 195030.73 | AL15: =IF($AC15="","",AL14+AH15) -> 332535.78 | AM15: =IF($AC15="","",IF(AD15<>AD14,AM14+1,AM14)) -> 1 | AP15: Cumulative Interest at End (from new cols) | AR15: =Y279 | AT15: =AK279 | AV15: =M279
A16: =IF(ROW()-3<=TotalPeriods_Loan,ROW()-3,"") -> 13 | B16: =IF($A16="", "", YEAR(StartYear) + INT(($A16-1)/PPY_Loan)) -> 2028 | C16: =IF($A16="", "", MOD(A16-1, PPY_Loan)+1) -> 1 | D16: =IFERROR(IF($A16="", "",IF(J15<=0, 0,J15)), 0) -> 2357180.2 | E16: =IFERROR(IF($A16="", "", _xlfn.XLOOKUP(A16,Offset!A:A,Offset!I:I, 0)), 0) -> 2214.4208 | F16: =IFERROR(IF($A16="", "", MAX(0, D16 - E16)), 0) -> 2354965.8 | G16: =IFERROR(IF($A16="", "", F16*(LoanRate/PPY_Loan)), 0) -> 15699.772 | H16: =IFERROR(IF($A16="", "", IF(D16<=0, 0, MIN(StdPayment, D16+G16))), 0) -> 27061.315 | I16: =IFERROR(IF($A16="", "", IF(D16<=0, 0,H16-G16)), 0) -> 11361.542 | J16: =IFERROR(IF($A16="", "", IF(D16<=0, 0, MAX(0, D16-I16))), 0) -> 2345818.7 | K16: =IFERROR(IF($A16="", "", IF(D16<=0, 0, E16*(LoanRate/PPY_Loan))), 0) -> 14.762806 | L16: =IFERROR(IF($A16="", "", L15+K16), 0) -> 13096.749 | M16: =IF($A16="","",M15+G16) -> 197615.79 | N16: =IF($A16="","",N15+H16) -> 351797.09 | O16: =IF($A16="","",IF(B16<>B15,O15+1,O15)) -> 2 | Q16: =IF(ROW()-3<=TotalPeriods_Loan,ROW()-3,"") -> 13 | R16: =IF($Q16="", "", YEAR(StartYear) + INT(($Q16-1)/PPY_Loan)) -> 2028 | S16: =IF($Q16="", "", MOD(Q16-1, PPY_Loan)+1) -> 1 | T16: =IFERROR(IF($Q16="", "",IF(X15<=0, 0, X15)), 0) -> 2370587.4 | U16: =IFERROR(IF($Q16="", "", T16*(LoanRate/PPY_Loan)), 0) -> 15803.916 | V16: =IFERROR(IF($Q16="", "", IF(T16<=0, 0, MIN(StdPayment, T16+U16))), 0) -> 27061.315 | W16: =IFERROR(IF($Q16="", "", IF(T16<=0, 0, V16-U16)), 0) -> 11257.399 | X16: =IFERROR(IF($Q16="", "", IF(T16<=0, 0, MAX(0, T16-W16))), 0) -> 2359330 | Y16: =IF($Q16="","",Y15+U16) -> 211127.09 | Z16: =IF($Q16="","",Z15+V16) -> 351797.09 | AA16: =IF($Q16="","",IF(R16<>R15,AA15+1,AA15)) -> 2 | AC16: =IF(ROW()-3<=TotalPeriods_Loan,ROW()-3,"") -> 13 | AD16: =IF($AC16="", "", YEAR(StartYear) + INT(($AC16-1)/PPY_Loan)) -> 2028 | AE16: =IF($AC16="", "", MOD(AC16-1, PPY_Loan)+1) -> 1 | AF16: =IFERROR(IF($AC16="", "",IF(AJ15<=0, 0, AJ15)), 0) -> 2362495 | AG16: =IFERROR(IF($AC16="", "", AF16*(LoanRate/PPY_Loan)), 0) -> 15749.966 | AH16: =IFERROR(IF($AC16="", "", IF(AF16<=0, 0, MIN(StdPayment+IF(ISBLANK(ExtraRepay),0,ExtraRepay), AF16+AG16))), 0) -> 27711.315 | AI16: =IFERROR(IF($AC16="", "", IF(AF16<=0, 0, AH16-AG16)), 0) -> 11961.348 | AJ16: =IFERROR(IF($AC16="", "", IF(AF16<=0, 0, MAX(0, AF16-AI16))), 0) -> 2350533.6 | AK16: =IF($AC16="","",AK15+AG16) -> 210780.69 | AL16: =IF($AC16="","",AL15+AH16) -> 360247.09 | AM16: =IF($AC16="","",IF(AD16<>AD15,AM15+1,AM15)) -> 2 | AP16: Net Position at Retirement (SuperSmart) | AV16: =IFERROR(AV11+AV12-AV6, 0) -> 0
A17: =IF(ROW()-3<=TotalPeriods_Loan,ROW()-3,"") -> 14 | B17: =IF($A17="", "", YEAR(StartYear) + INT(($A17-1)/PPY_Loan)) -> 2028 | C17: =IF($A17="", "", MOD(A17-1, PPY_Loan)+1) -> 2 | D17: =IFERROR(IF($A17="", "",IF(J16<=0, 0,J16)), 0) -> 2345818.7 | E17: =IFERROR(IF($A17="", "", _xlfn.XLOOKUP(A17,Offset!A:A,Offset!I:I, 0)), 0) -> 4428.8417 | F17: =IFERROR(IF($A17="", "", MAX(0, D17 - E17)), 0) -> 2341389.9 | G17: =IFERROR(IF($A17="", "", F17*(LoanRate/PPY_Loan)), 0) -> 15609.266 | H17: =IFERROR(IF($A17="", "", IF(D17<=0, 0, MIN(StdPayment, D17+G17))), 0) -> 27061.315 | I17: =IFERROR(IF($A17="", "", IF(D17<=0, 0,H17-G17)), 0) -> 11452.049 | J17: =IFERROR(IF($A17="", "", IF(D17<=0, 0, MAX(0, D17-I17))), 0) -> 2334366.6 | K17: =IFERROR(IF($A17="", "", IF(D17<=0, 0, E17*(LoanRate/PPY_Loan))), 0) -> 29.525611 | L17: =IFERROR(IF($A17="", "", L16+K17), 0) -> 13126.275 | M17: =IF($A17="","",M16+G17) -> 213225.05 | N17: =IF($A17="","",N16+H17) -> 378858.4 | O17: =IF($A17="","",IF(B17<>B16,O16+1,O16)) -> 2 | Q17: =IF(ROW()-3<=TotalPeriods_Loan,ROW()-3,"") -> 14 | R17: =IF($Q17="", "", YEAR(StartYear) + INT(($Q17-1)/PPY_Loan)) -> 2028 | S17: =IF($Q17="", "", MOD(Q17-1, PPY_Loan)+1) -> 2 | T17: =IFERROR(IF($Q17="", "",IF(X16<=0, 0, X16)), 0) -> 2359330 | U17: =IFERROR(IF($Q17="", "", T17*(LoanRate/PPY_Loan)), 0) -> 15728.867 | V17: =IFERROR(IF($Q17="", "", IF(T17<=0, 0, MIN(StdPayment, T17+U17))), 0) -> 27061.315 | W17: =IFERROR(IF($Q17="", "", IF(T17<=0, 0, V17-U17)), 0) -> 11332.448 | X17: =IFERROR(IF($Q17="", "", IF(T17<=0, 0, MAX(0, T17-W17))), 0) -> 2347997.6 | Y17: =IF($Q17="","",Y16+U17) -> 226855.96 | Z17: =IF($Q17="","",Z16+V17) -> 378858.4 | AA17: =IF($Q17="","",IF(R17<>R16,AA16+1,AA16)) -> 2 | AC17: =IF(ROW()-3<=TotalPeriods_Loan,ROW()-3,"") -> 14 | AD17: =IF($AC17="", "", YEAR(StartYear) + INT(($AC17-1)/PPY_Loan)) -> 2028 | AE17: =IF($AC17="", "", MOD(AC17-1, PPY_Loan)+1) -> 2 | AF17: =IFERROR(IF($AC17="", "",IF(AJ16<=0, 0, AJ16)), 0) -> 2350533.6 | AG17: =IFERROR(IF($AC17="", "", AF17*(LoanRate/PPY_Loan)), 0) -> 15670.224 | AH17: =IFERROR(IF($AC17="", "", IF(AF17<=0, 0, MIN(StdPayment+IF(ISBLANK(ExtraRepay),0,ExtraRepay), AF17+AG17))), 0) -> 27711.315 | AI17: =IFERROR(IF($AC17="", "", IF(AF17<=0, 0, AH17-AG17)), 0) -> 12041.091 | AJ17: =IFERROR(IF($AC17="", "", IF(AF17<=0, 0, MAX(0, AF17-AI17))), 0) -> 2338492.5 | AK17: =IF($AC17="","",AK16+AG17) -> 226450.92 | AL17: =IF($AC17="","",AL16+AH17) -> 387958.4 | AM17: =IF($AC17="","",IF(AD17<>AD16,AM16+1,AM16)) -> 2
A18: =IF(ROW()-3<=TotalPeriods_Loan,ROW()-3,"") -> 15 | B18: =IF($A18="", "", YEAR(StartYear) + INT(($A18-1)/PPY_Loan)) -> 2028 | C18: =IF($A18="", "", MOD(A18-1, PPY_Loan)+1) -> 3 | D18: =IFERROR(IF($A18="", "",IF(J17<=0, 0,J17)), 0) -> 2334366.6 | E18: =IFERROR(IF($A18="", "", _xlfn.XLOOKUP(A18,Offset!A:A,Offset!I:I, 0)), 0) -> 6643.2625 | F18: =IFERROR(IF($A18="", "", MAX(0, D18 - E18)), 0) -> 2327723.4 | G18: =IFERROR(IF($A18="", "", F18*(LoanRate/PPY_Loan)), 0) -> 15518.156 | H18: =IFERROR(IF($A18="", "", IF(D18<=0, 0, MIN(StdPayment, D18+G18))), 0) -> 27061.315 | I18: =IFERROR(IF($A18="", "", IF(D18<=0, 0,H18-G18)), 0) -> 11543.159 | J18: =IFERROR(IF($A18="", "", IF(D18<=0, 0, MAX(0, D18-I18))), 0) -> 2322823.5 | K18: =IFERROR(IF($A18="", "", IF(D18<=0, 0, E18*(LoanRate/PPY_Loan))), 0) -> 44.288417 | L18: =IFERROR(IF($A18="", "", L17+K18), 0) -> 13170.564 | M18: =IF($A18="","",M17+G18) -> 228743.21 | N18: =IF($A18="","",N17+H18) -> 405919.72 | O18: =IF($A18="","",IF(B18<>B17,O17+1,O17)) -> 2 | Q18: =IF(ROW()-3<=TotalPeriods_Loan,ROW()-3,"") -> 15 | R18: =IF($Q18="", "", YEAR(StartYear) + INT(($Q18-1)/PPY_Loan)) -> 2028 | S18: =IF($Q18="", "", MOD(Q18-1, PPY_Loan)+1) -> 3 | T18: =IFERROR(IF($Q18="", "",IF(X17<=0, 0, X17)), 0) -> 2347997.6 | U18: =IFERROR(IF($Q18="", "", T18*(LoanRate/PPY_Loan)), 0) -> 15653.317 | V18: =IFERROR(IF($Q18="", "", IF(T18<=0, 0, MIN(StdPayment, T18+U18))), 0) -> 27061.315 | W18: =IFERROR(IF($Q18="", "", IF(T18<=0, 0, V18-U18)), 0) -> 11407.998 | X18: =IFERROR(IF($Q18="", "", IF(T18<=0, 0, MAX(0, T18-W18))), 0) -> 2336589.6 | Y18: =IF($Q18="","",Y17+U18) -> 242509.28 | Z18: =IF($Q18="","",Z17+V18) -> 405919.72 | AA18: =IF($Q18="","",IF(R18<>R17,AA17+1,AA17)) -> 2 | AC18: =IF(ROW()-3<=TotalPeriods_Loan,ROW()-3,"") -> 15 | AD18: =IF($AC18="", "", YEAR(StartYear) + INT(($AC18-1)/PPY_Loan)) -> 2028 | AE18: =IF($AC18="", "", MOD(AC18-1, PPY_Loan)+1) -> 3 | AF18: =IFERROR(IF($AC18="", "",IF(AJ17<=0, 0, AJ17)), 0) -> 2338492.5 | AG18: =IFERROR(IF($AC18="", "", AF18*(LoanRate/PPY_Loan)), 0) -> 15589.95 | AH18: =IFERROR(IF($AC18="", "", IF(AF18<=0, 0, MIN(StdPayment+IF(ISBLANK(ExtraRepay),0,ExtraRepay), AF18+AG18))), 0) -> 27711.315 | AI18: =IFERROR(IF($AC18="", "", IF(AF18<=0, 0, AH18-AG18)), 0) -> 12121.365 | AJ18: =IFERROR(IF($AC18="", "", IF(AF18<=0, 0, MAX(0, AF18-AI18))), 0) -> 2326371.1 | AK18: =IF($AC18="","",AK17+AG18) -> 242040.87 | AL18: =IF($AC18="","",AL17+AH18) -> 415669.72 | AM18: =IF($AC18="","",IF(AD18<>AD17,AM17+1,AM17)) -> 2
A19: =IF(ROW()-3<=TotalPeriods_Loan,ROW()-3,"") -> 16 | B19: =IF($A19="", "", YEAR(StartYear) + INT(($A19-1)/PPY_Loan)) -> 2028 | C19: =IF($A19="", "", MOD(A19-1, PPY_Loan)+1) -> 4 | D19: =IFERROR(IF($A19="", "",IF(J18<=0, 0,J18)), 0) -> 2322823.5 | E19: =IFERROR(IF($A19="", "", _xlfn.XLOOKUP(A19,Offset!A:A,Offset!I:I, 0)), 0) -> 8857.6833 | F19: =IFERROR(IF($A19="", "", MAX(0, D19 - E19)), 0) -> 2313965.8 | G19: =IFERROR(IF($A19="", "", F19*(LoanRate/PPY_Loan)), 0) -> 15426.439 | H19: =IFERROR(IF($A19="", "", IF(D19<=0, 0, MIN(StdPayment, D19+G19))), 0) -> 27061.315 | I19: =IFERROR(IF($A19="", "", IF(D19<=0, 0,H19-G19)), 0) -> 11634.876 | J19: =IFERROR(IF($A19="", "", IF(D19<=0, 0, MAX(0, D19-I19))), 0) -> 2311188.6 | K19: =IFERROR(IF($A19="", "", IF(D19<=0, 0, E19*(LoanRate/PPY_Loan))), 0) -> 59.051222 | L19: =IFERROR(IF($A19="", "", L18+K19), 0) -> 13229.615 | M19: =IF($A19="","",M18+G19) -> 244169.65 | N19: =IF($A19="","",N18+H19) -> 432981.03 | O19: =IF($A19="","",IF(B19<>B18,O18+1,O18)) -> 2 | Q19: =IF(ROW()-3<=TotalPeriods_Loan,ROW()-3,"") -> 16 | R19: =IF($Q19="", "", YEAR(StartYear) + INT(($Q19-1)/PPY_Loan)) -> 2028 | S19: =IF($Q19="", "", MOD(Q19-1, PPY_Loan)+1) -> 4 | T19: =IFERROR(IF($Q19="", "",IF(X18<=0, 0, X18)), 0) -> 2336589.6 | U19: =IFERROR(IF($Q19="", "", T19*(LoanRate/PPY_Loan)), 0) -> 15577.264 | V19: =IFERROR(IF($Q19="", "", IF(T19<=0, 0, MIN(StdPayment, T19+U19))), 0) -> 27061.315 | W19: =IFERROR(IF($Q19="", "", IF(T19<=0, 0, V19-U19)), 0) -> 11484.051 | X19: =IFERROR(IF($Q19="", "", IF(T19<=0, 0, MAX(0, T19-W19))), 0) -> 2325105.5 | Y19: =IF($Q19="","",Y18+U19) -> 258086.54 | Z19: =IF($Q19="","",Z18+V19) -> 432981.03 | AA19: =IF($Q19="","",IF(R19<>R18,AA18+1,AA18)) -> 2 | AC19: =IF(ROW()-3<=TotalPeriods_Loan,ROW()-3,"") -> 16 | AD19: =IF($AC19="", "", YEAR(StartYear) + INT(($AC19-1)/PPY_Loan)) -> 2028 | AE19: =IF($AC19="", "", MOD(AC19-1, PPY_Loan)+1) -> 4 | AF19: =IFERROR(IF($AC19="", "",IF(AJ18<=0, 0, AJ18)), 0) -> 2326371.1 | AG19: =IFERROR(IF($AC19="", "", AF19*(LoanRate/PPY_Loan)), 0) -> 15509.141 | AH19: =IFERROR(IF($AC19="", "", IF(AF19<=0, 0, MIN(StdPayment+IF(ISBLANK(ExtraRepay),0,ExtraRepay), AF19+AG19))), 0) -> 27711.315 | AI19: =IFERROR(IF($AC19="", "", IF(AF19<=0, 0, AH19-AG19)), 0) -> 12202.174 | AJ19: =IFERROR(IF($AC19="", "", IF(AF19<=0, 0, MAX(0, AF19-AI19))), 0) -> 2314169 | AK19: =IF($AC19="","",AK18+AG19) -> 257550.01 | AL19: =IF($AC19="","",AL18+AH19) -> 443381.03 | AM19: =IF($AC19="","",IF(AD19<>AD18,AM18+1,AM18)) -> 2
A20: =IF(ROW()-3<=TotalPeriods_Loan,ROW()-3,"") -> 17 | B20: =IF($A20="", "", YEAR(StartYear) + INT(($A20-1)/PPY_Loan)) -> 2028 | C20: =IF($A20="", "", MOD(A20-1, PPY_Loan)+1) -> 5 | D20: =IFERROR(IF($A20="", "",IF(J19<=0, 0,J19)), 0) -> 2311188.6 | E20: =IFERROR(IF($A20="", "", _xlfn.XLOOKUP(A20,Offset!A:A,Offset!I:I, 0)), 0) -> 11072.104 | F20: =IFERROR(IF($A20="", "", MAX(0, D20 - E20)), 0) -> 2300116.5 | G20: =IFERROR(IF($A20="", "", F20*(LoanRate/PPY_Loan)), 0) -> 15334.11 | H20: =IFERROR(IF($A20="", "", IF(D20<=0, 0, MIN(StdPayment, D20+G20))), 0) -> 27061.315 | I20: =IFERROR(IF($A20="", "", IF(D20<=0, 0,H20-G20)), 0) -> 11727.205 | J20: =IFERROR(IF($A20="", "", IF(D20<=0, 0, MAX(0, D20-I20))), 0) -> 2299461.4 | K20: =IFERROR(IF($A20="", "", IF(D20<=0, 0, E20*(LoanRate/PPY_Loan))), 0) -> 73.814028 | L20: =IFERROR(IF($A20="", "", L19+K20), 0) -> 13303.429 | M20: =IF($A20="","",M19+G20) -> 259503.76 | N20: =IF($A20="","",N19+H20) -> 460042.35 | O20: =IF($A20="","",IF(B20<>B19,O19+1,O19)) -> 2 | Q20: =IF(ROW()-3<=TotalPeriods_Loan,ROW()-3,"") -> 17 | R20: =IF($Q20="", "", YEAR(StartYear) + INT(($Q20-1)/PPY_Loan)) -> 2028 | S20: =IF($Q20="", "", MOD(Q20-1, PPY_Loan)+1) -> 5 | T20: =IFERROR(IF($Q20="", "",IF(X19<=0, 0, X19)), 0) -> 2325105.5 | U20: =IFERROR(IF($Q20="", "", T20*(LoanRate/PPY_Loan)), 0) -> 15500.703 | V20: =IFERROR(IF($Q20="", "", IF(T20<=0, 0, MIN(StdPayment, T20+U20))), 0) -> 27061.315 | W20: =IFERROR(IF($Q20="", "", IF(T20<=0, 0, V20-U20)), 0) -> 11560.611 | X20: =IFERROR(IF($Q20="", "", IF(T20<=0, 0, MAX(0, T20-W20))), 0) -> 2313544.9 | Y20: =IF($Q20="","",Y19+U20) -> 273587.24 | Z20: =IF($Q20="","",Z19+V20) -> 460042.35 | AA20: =IF($Q20="","",IF(R20<>R19,AA19+1,AA19)) -> 2 | AC20: =IF(ROW()-3<=TotalPeriods_Loan,ROW()-3,"") -> 17 | AD20: =IF($AC20="", "", YEAR(StartYear) + INT(($AC20-1)/PPY_Loan)) -> 2028 | AE20: =IF($AC20="", "", MOD(AC20-1, PPY_Loan)+1) -> 5 | AF20: =IFERROR(IF($AC20="", "",IF(AJ19<=0, 0, AJ19)), 0) -> 2314169 | AG20: =IFERROR(IF($AC20="", "", AF20*(LoanRate/PPY_Loan)), 0) -> 15427.793 | AH20: =IFERROR(IF($AC20="", "", IF(AF20<=0, 0, MIN(StdPayment+IF(ISBLANK(ExtraRepay),0,ExtraRepay), AF20+AG20))), 0) -> 27711.315 | AI20: =IFERROR(IF($AC20="", "", IF(AF20<=0, 0, AH20-AG20)), 0) -> 12283.521 | AJ20: =IFERROR(IF($AC20="", "", IF(AF20<=0, 0, MAX(0, AF20-AI20))), 0) -> 2301885.5 | AK20: =IF($AC20="","",AK19+AG20) -> 272977.8 | AL20: =IF($AC20="","",AL19+AH20) -> 471092.35 | AM20: =IF($AC20="","",IF(AD20<>AD19,AM19+1,AM19)) -> 2
A21: =IF(ROW()-3<=TotalPeriods_Loan,ROW()-3,"") -> 18 | B21: =IF($A21="", "", YEAR(StartYear) + INT(($A21-1)/PPY_Loan)) -> 2028 | C21: =IF($A21="", "", MOD(A21-1, PPY_Loan)+1) -> 6 | D21: =IFERROR(IF($A21="", "",IF(J20<=0, 0,J20)), 0) -> 2299461.4 | E21: =IFERROR(IF($A21="", "", _xlfn.XLOOKUP(A21,Offset!A:A,Offset!I:I, 0)), 0) -> 13286.525 | F21: =IFERROR(IF($A21="", "", MAX(0, D21 - E21)), 0) -> 2286174.9 | G21: =IFERROR(IF($A21="", "", F21*(LoanRate/PPY_Loan)), 0) -> 15241.166 | H21: =IFERROR(IF($A21="", "", IF(D21<=0, 0, MIN(StdPayment, D21+G21))), 0) -> 27061.315 | I21: =IFERROR(IF($A21="", "", IF(D21<=0, 0,H21-G21)), 0) -> 11820.149 | J21: =IFERROR(IF($A21="", "", IF(D21<=0, 0, MAX(0, D21-I21))), 0) -> 2287641.3 | K21: =IFERROR(IF($A21="", "", IF(D21<=0, 0, E21*(LoanRate/PPY_Loan))), 0) -> 88.576833 | L21: =IFERROR(IF($A21="", "", L20+K21), 0) -> 13392.006 | M21: =IF($A21="","",M20+G21) -> 274744.92 | N21: =IF($A21="","",N20+H21) -> 487103.66 | O21: =IF($A21="","",IF(B21<>B20,O20+1,O20)) -> 2 | Q21: =IF(ROW()-3<=TotalPeriods_Loan,ROW()-3,"") -> 18 | R21: =IF($Q21="", "", YEAR(StartYear) + INT(($Q21-1)/PPY_Loan)) -> 2028 | S21: =IF($Q21="", "", MOD(Q21-1, PPY_Loan)+1) -> 6 | T21: =IFERROR(IF($Q21="", "",IF(X20<=0, 0, X20)), 0) -> 2313544.9 | U21: =IFERROR(IF($Q21="", "", T21*(LoanRate/PPY_Loan)), 0) -> 15423.633 | V21: =IFERROR(IF($Q21="", "", IF(T21<=0, 0, MIN(StdPayment, T21+U21))), 0) -> 27061.315 | W21: =IFERROR(IF($Q21="", "", IF(T21<=0, 0, V21-U21)), 0) -> 11637.682 | X21: =IFERROR(IF($Q21="", "", IF(T21<=0, 0, MAX(0, T21-W21))), 0) -> 2301907.2 | Y21: =IF($Q21="","",Y20+U21) -> 289010.88 | Z21: =IF($Q21="","",Z20+V21) -> 487103.66 | AA21: =IF($Q21="","",IF(R21<>R20,AA20+1,AA20)) -> 2 | AC21: =IF(ROW()-3<=TotalPeriods_Loan,ROW()-3,"") -> 18 | AD21: =IF($AC21="", "", YEAR(StartYear) + INT(($AC21-1)/PPY_Loan)) -> 2028 | AE21: =IF($AC21="", "", MOD(AC21-1, PPY_Loan)+1) -> 6 | AF21: =IFERROR(IF($AC21="", "",IF(AJ20<=0, 0, AJ20)), 0) -> 2301885.5 | AG21: =IFERROR(IF($AC21="", "", AF21*(LoanRate/PPY_Loan)), 0) -> 15345.903 | AH21: =IFERROR(IF($AC21="", "", IF(AF21<=0, 0, MIN(StdPayment+IF(ISBLANK(ExtraRepay),0,ExtraRepay), AF21+AG21))), 0) -> 27711.315 | AI21: =IFERROR(IF($AC21="", "", IF(AF21<=0, 0, AH21-AG21)), 0) -> 12365.412 | AJ21: =IFERROR(IF($AC21="", "", IF(AF21<=0, 0, MAX(0, AF21-AI21))), 0) -> 2289520 | AK21: =IF($AC21="","",AK20+AG21) -> 288323.7 | AL21: =IF($AC21="","",AL20+AH21) -> 498803.66 | AM21: =IF($AC21="","",IF(AD21<>AD20,AM20+1,AM20)) -> 2
A22: =IF(ROW()-3<=TotalPeriods_Loan,ROW()-3,"") -> 19 | B22: =IF($A22="", "", YEAR(StartYear) + INT(($A22-1)/PPY_Loan)) -> 2028 | C22: =IF($A22="", "", MOD(A22-1, PPY_Loan)+1) -> 7 | D22: =IFERROR(IF($A22="", "",IF(J21<=0, 0,J21)), 0) -> 2287641.3 | E22: =IFERROR(IF($A22="", "", _xlfn.XLOOKUP(A22,Offset!A:A,Offset!I:I, 0)), 0) -> 15500.946 | F22: =IFERROR(IF($A22="", "", MAX(0, D22 - E22)), 0) -> 2272140.3 | G22: =IFERROR(IF($A22="", "", F22*(LoanRate/PPY_Loan)), 0) -> 15147.602 | H22: =IFERROR(IF($A22="", "", IF(D22<=0, 0, MIN(StdPayment, D22+G22))), 0) -> 27061.315 | I22: =IFERROR(IF($A22="", "", IF(D22<=0, 0,H22-G22)), 0) -> 11913.712 | J22: =IFERROR(IF($A22="", "", IF(D22<=0, 0, MAX(0, D22-I22))), 0) -> 2275727.5 | K22: =IFERROR(IF($A22="", "", IF(D22<=0, 0, E22*(LoanRate/PPY_Loan))), 0) -> 103.33964 | L22: =IFERROR(IF($A22="", "", L21+K22), 0) -> 13495.345 | M22: =IF($A22="","",M21+G22) -> 289892.53 | N22: =IF($A22="","",N21+H22) -> 514164.98 | O22: =IF($A22="","",IF(B22<>B21,O21+1,O21)) -> 2 | Q22: =IF(ROW()-3<=TotalPeriods_Loan,ROW()-3,"") -> 19 | R22: =IF($Q22="", "", YEAR(StartYear) + INT(($Q22-1)/PPY_Loan)) -> 2028 | S22: =IF($Q22="", "", MOD(Q22-1, PPY_Loan)+1) -> 7 | T22: =IFERROR(IF($Q22="", "",IF(X21<=0, 0, X21)), 0) -> 2301907.2 | U22: =IFERROR(IF($Q22="", "", T22*(LoanRate/PPY_Loan)), 0) -> 15346.048 | V22: =IFERROR(IF($Q22="", "", IF(T22<=0, 0, MIN(StdPayment, T22+U22))), 0) -> 27061.315 | W22: =IFERROR(IF($Q22="", "", IF(T22<=0, 0, V22-U22)), 0) -> 11715.266 | X22: =IFERROR(IF($Q22="", "", IF(T22<=0, 0, MAX(0, T22-W22))), 0) -> 2290191.9 | Y22: =IF($Q22="","",Y21+U22) -> 304356.93 | Z22: =IF($Q22="","",Z21+V22) -> 514164.98 | AA22: =IF($Q22="","",IF(R22<>R21,AA21+1,AA21)) -> 2 | AC22: =IF(ROW()-3<=TotalPeriods_Loan,ROW()-3,"") -> 19 | AD22: =IF($AC22="", "", YEAR(StartYear) + INT(($AC22-1)/PPY_Loan)) -> 2028 | AE22: =IF($AC22="", "", MOD(AC22-1, PPY_Loan)+1) -> 7 | AF22: =IFERROR(IF($AC22="", "",IF(AJ21<=0, 0, AJ21)), 0) -> 2289520 | AG22: =IFERROR(IF($AC22="", "", AF22*(LoanRate/PPY_Loan)), 0) -> 15263.467 | AH22: =IFERROR(IF($AC22="", "", IF(AF22<=0, 0, MIN(StdPayment+IF(ISBLANK(ExtraRepay),0,ExtraRepay), AF22+AG22))), 0) -> 27711.315 | AI22: =IFERROR(IF($AC22="", "", IF(AF22<=0, 0, AH22-AG22)), 0) -> 12447.848 | AJ22: =IFERROR(IF($AC22="", "", IF(AF22<=0, 0, MAX(0, AF22-AI22))), 0) -> 2277072.2 | AK22: =IF($AC22="","",AK21+AG22) -> 303587.17 | AL22: =IF($AC22="","",AL21+AH22) -> 526514.98 | AM22: =IF($AC22="","",IF(AD22<>AD21,AM21+1,AM21)) -> 2
A23: =IF(ROW()-3<=TotalPeriods_Loan,ROW()-3,"") -> 20 | B23: =IF($A23="", "", YEAR(StartYear) + INT(($A23-1)/PPY_Loan)) -> 2028 | C23: =IF($A23="", "", MOD(A23-1, PPY_Loan)+1) -> 8 | D23: =IFERROR(IF($A23="", "",IF(J22<=0, 0,J22)), 0) -> 2275727.5 | E23: =IFERROR(IF($A23="", "", _xlfn.XLOOKUP(A23,Offset!A:A,Offset!I:I, 0)), 0) -> 17715.367 | F23: =IFERROR(IF($A23="", "", MAX(0, D23 - E23)), 0) -> 2258012.2 | G23: =IFERROR(IF($A23="", "", F23*(LoanRate/PPY_Loan)), 0) -> 15053.415 | H23: =IFERROR(IF($A23="", "", IF(D23<=0, 0, MIN(StdPayment, D23+G23))), 0) -> 27061.315 | I23: =IFERROR(IF($A23="", "", IF(D23<=0, 0,H23-G23)), 0) -> 12007.9 | J23: =IFERROR(IF($A23="", "", IF(D23<=0, 0, MAX(0, D23-I23))), 0) -> 2263719.6 | K23: =IFERROR(IF($A23="", "", IF(D23<=0, 0, E23*(LoanRate/PPY_Loan))), 0) -> 118.10244 | L23: =IFERROR(IF($A23="", "", L22+K23), 0) -> 13613.448 | M23: =IF($A23="","",M22+G23) -> 304945.94 | N23: =IF($A23="","",N22+H23) -> 541226.29 | O23: =IF($A23="","",IF(B23<>B22,O22+1,O22)) -> 2 | Q23: =IF(ROW()-3<=TotalPeriods_Loan,ROW()-3,"") -> 20 | R23: =IF($Q23="", "", YEAR(StartYear) + INT(($Q23-1)/PPY_Loan)) -> 2028 | S23: =IF($Q23="", "", MOD(Q23-1, PPY_Loan)+1) -> 8 | T23: =IFERROR(IF($Q23="", "",IF(X22<=0, 0, X22)), 0) -> 2290191.9 | U23: =IFERROR(IF($Q23="", "", T23*(LoanRate/PPY_Loan)), 0) -> 15267.946 | V23: =IFERROR(IF($Q23="", "", IF(T23<=0, 0, MIN(StdPayment, T23+U23))), 0) -> 27061.315 | W23: =IFERROR(IF($Q23="", "", IF(T23<=0, 0, V23-U23)), 0) -> 11793.368 | X23: =IFERROR(IF($Q23="", "", IF(T23<=0, 0, MAX(0, T23-W23))), 0) -> 2278398.6 | Y23: =IF($Q23="","",Y22+U23) -> 319624.87 | Z23: =IF($Q23="","",Z22+V23) -> 541226.29 | AA23: =IF($Q23="","",IF(R23<>R22,AA22+1,AA22)) -> 2 | AC23: =IF(ROW()-3<=TotalPeriods_Loan,ROW()-3,"") -> 20 | AD23: =IF($AC23="", "", YEAR(StartYear) + INT(($AC23-1)/PPY_Loan)) -> 2028 | AE23: =IF($AC23="", "", MOD(AC23-1, PPY_Loan)+1) -> 8 | AF23: =IFERROR(IF($AC23="", "",IF(AJ22<=0, 0, AJ22)), 0) -> 2277072.2 | AG23: =IFERROR(IF($AC23="", "", AF23*(LoanRate/PPY_Loan)), 0) -> 15180.481 | AH23: =IFERROR(IF($AC23="", "", IF(AF23<=0, 0, MIN(StdPayment+IF(ISBLANK(ExtraRepay),0,ExtraRepay), AF23+AG23))), 0) -> 27711.315 | AI23: =IFERROR(IF($AC23="", "", IF(AF23<=0, 0, AH23-AG23)), 0) -> 12530.833 | AJ23: =IFERROR(IF($AC23="", "", IF(AF23<=0, 0, MAX(0, AF23-AI23))), 0) -> 2264541.4 | AK23: =IF($AC23="","",AK22+AG23) -> 318767.65 | AL23: =IF($AC23="","",AL22+AH23) -> 554226.29 | AM23: =IF($AC23="","",IF(AD23<>AD22,AM22+1,AM22)) -> 2
A24: =IF(ROW()-3<=TotalPeriods_Loan,ROW()-3,"") -> 21 | B24: =IF($A24="", "", YEAR(StartYear) + INT(($A24-1)/PPY_Loan)) -> 2028 | C24: =IF($A24="", "", MOD(A24-1, PPY_Loan)+1) -> 9 | D24: =IFERROR(IF($A24="", "",IF(J23<=0, 0,J23)), 0) -> 2263719.6 | E24: =IFERROR(IF($A24="", "", _xlfn.XLOOKUP(A24,Offset!A:A,Offset!I:I, 0)), 0) -> 19929.788 | F24: =IFERROR(IF($A24="", "", MAX(0, D24 - E24)), 0) -> 2243789.9 | G24: =IFERROR(IF($A24="", "", F24*(LoanRate/PPY_Loan)), 0) -> 14958.599 | H24: =IFERROR(IF($A24="", "", IF(D24<=0, 0, MIN(StdPayment, D24+G24))), 0) -> 27061.315 | I24: =IFERROR(IF($A24="", "", IF(D24<=0, 0,H24-G24)), 0) -> 12102.716 | J24: =IFERROR(IF($A24="", "", IF(D24<=0, 0, MAX(0, D24-I24))), 0) -> 2251616.9 | K24: =IFERROR(IF($A24="", "", IF(D24<=0, 0, E24*(LoanRate/PPY_Loan))), 0) -> 132.86525 | L24: =IFERROR(IF($A24="", "", L23+K24), 0) -> 13746.313 | M24: =IF($A24="","",M23+G24) -> 319904.54 | N24: =IF($A24="","",N23+H24) -> 568287.61 | O24: =IF($A24="","",IF(B24<>B23,O23+1,O23)) -> 2 | Q24: =IF(ROW()-3<=TotalPeriods_Loan,ROW()-3,"") -> 21 | R24: =IF($Q24="", "", YEAR(StartYear) + INT(($Q24-1)/PPY_Loan)) -> 2028 | S24: =IF($Q24="", "", MOD(Q24-1, PPY_Loan)+1) -> 9 | T24: =IFERROR(IF($Q24="", "",IF(X23<=0, 0, X23)), 0) -> 2278398.6 | U24: =IFERROR(IF($Q24="", "", T24*(LoanRate/PPY_Loan)), 0) -> 15189.324 | V24: =IFERROR(IF($Q24="", "", IF(T24<=0, 0, MIN(StdPayment, T24+U24))), 0) -> 27061.315 | W24: =IFERROR(IF($Q24="", "", IF(T24<=0, 0, V24-U24)), 0) -> 11871.991 | X24: =IFERROR(IF($Q24="", "", IF(T24<=0, 0, MAX(0, T24-W24))), 0) -> 2266526.6 | Y24: =IF($Q24="","",Y23+U24) -> 334814.2 | Z24: =IF($Q24="","",Z23+V24) -> 568287.61 | AA24: =IF($Q24="","",IF(R24<>R23,AA23+1,AA23)) -> 2 | AC24: =IF(ROW()-3<=TotalPeriods_Loan,ROW()-3,"") -> 21 | AD24: =IF($AC24="", "", YEAR(StartYear) + INT(($AC24-1)/PPY_Loan)) -> 2028 | AE24: =IF($AC24="", "", MOD(AC24-1, PPY_Loan)+1) -> 9 | AF24: =IFERROR(IF($AC24="", "",IF(AJ23<=0, 0, AJ23)), 0) -> 2264541.4 | AG24: =IFERROR(IF($AC24="", "", AF24*(LoanRate/PPY_Loan)), 0) -> 15096.942 | AH24: =IFERROR(IF($AC24="", "", IF(AF24<=0, 0, MIN(StdPayment+IF(ISBLANK(ExtraRepay),0,ExtraRepay), AF24+AG24))), 0) -> 27711.315 | AI24: =IFERROR(IF($AC24="", "", IF(AF24<=0, 0, AH24-AG24)), 0) -> 12614.372 | AJ24: =IFERROR(IF($AC24="", "", IF(AF24<=0, 0, MAX(0, AF24-AI24))), 0) -> 2251927 | AK24: =IF($AC24="","",AK23+AG24) -> 333864.59 | AL24: =IF($AC24="","",AL23+AH24) -> 581937.61 | AM24: =IF($AC24="","",IF(AD24<>AD23,AM23+1,AM23)) -> 2
A25: =IF(ROW()-3<=TotalPeriods_Loan,ROW()-3,"") -> 22 | B25: =IF($A25="", "", YEAR(StartYear) + INT(($A25-1)/PPY_Loan)) -> 2028 | C25: =IF($A25="", "", MOD(A25-1, PPY_Loan)+1) -> 10 | D25: =IFERROR(IF($A25="", "",IF(J24<=0, 0,J24)), 0) -> 2251616.9 | E25: =IFERROR(IF($A25="", "", _xlfn.XLOOKUP(A25,Offset!A:A,Offset!I:I, 0)), 0) -> 22144.208 | F25: =IFERROR(IF($A25="", "", MAX(0, D25 - E25)), 0) -> 2229472.7 | G25: =IFERROR(IF($A25="", "", F25*(LoanRate/PPY_Loan)), 0) -> 14863.151 | H25: =IFERROR(IF($A25="", "", IF(D25<=0, 0, MIN(StdPayment, D25+G25))), 0) -> 27061.315 | I25: =IFERROR(IF($A25="", "", IF(D25<=0, 0,H25-G25)), 0) -> 12198.163 | J25: =IFERROR(IF($A25="", "", IF(D25<=0, 0, MAX(0, D25-I25))), 0) -> 2239418.8 | K25: =IFERROR(IF($A25="", "", IF(D25<=0, 0, E25*(LoanRate/PPY_Loan))), 0) -> 147.62806 | L25: =IFERROR(IF($A25="", "", L24+K25), 0) -> 13893.941 | M25: =IF($A25="","",M24+G25) -> 334767.69 | N25: =IF($A25="","",N24+H25) -> 595348.92 | O25: =IF($A25="","",IF(B25<>B24,O24+1,O24)) -> 2 | Q25: =IF(ROW()-3<=TotalPeriods_Loan,ROW()-3,"") -> 22 | R25: =IF($Q25="", "", YEAR(StartYear) + INT(($Q25-1)/PPY_Loan)) -> 2028 | S25: =IF($Q25="", "", MOD(Q25-1, PPY_Loan)+1) -> 10 | T25: =IFERROR(IF($Q25="", "",IF(X24<=0, 0, X24)), 0) -> 2266526.6 | U25: =IFERROR(IF($Q25="", "", T25*(LoanRate/PPY_Loan)), 0) -> 15110.177 | V25: =IFERROR(IF($Q25="", "", IF(T25<=0, 0, MIN(StdPayment, T25+U25))), 0) -> 27061.315 | W25: =IFERROR(IF($Q25="", "", IF(T25<=0, 0, V25-U25)), 0) -> 11951.137 | X25: =IFERROR(IF($Q25="", "", IF(T25<=0, 0, MAX(0, T25-W25))), 0) -> 2254575.5 | Y25: =IF($Q25="","",Y24+U25) -> 349924.37 | Z25: =IF($Q25="","",Z24+V25) -> 595348.92 | AA25: =IF($Q25="","",IF(R25<>R24,AA24+1,AA24)) -> 2 | AC25: =IF(ROW()-3<=TotalPeriods_Loan,ROW()-3,"") -> 22 | AD25: =IF($AC25="", "", YEAR(StartYear) + INT(($AC25-1)/PPY_Loan)) -> 2028 | AE25: =IF($AC25="", "", MOD(AC25-1, PPY_Loan)+1) -> 10 | AF25: =IFERROR(IF($AC25="", "",IF(AJ24<=0, 0, AJ24)), 0) -> 2251927 | AG25: =IFERROR(IF($AC25="", "", AF25*(LoanRate/PPY_Loan)), 0) -> 15012.847 | AH25: =IFERROR(IF($AC25="", "", IF(AF25<=0, 0, MIN(StdPayment+IF(ISBLANK(ExtraRepay),0,ExtraRepay), AF25+AG25))), 0) -> 27711.315 | AI25: =IFERROR(IF($AC25="", "", IF(AF25<=0, 0, AH25-AG25)), 0) -> 12698.468 | AJ25: =IFERROR(IF($AC25="", "", IF(AF25<=0, 0, MAX(0, AF25-AI25))), 0) -> 2239228.5 | AK25: =IF($AC25="","",AK24+AG25) -> 348877.44 | AL25: =IF($AC25="","",AL24+AH25) -> 609648.92 | AM25: =IF($AC25="","",IF(AD25<>AD24,AM24+1,AM24)) -> 2
A26: =IF(ROW()-3<=TotalPeriods_Loan,ROW()-3,"") -> 23 | B26: =IF($A26="", "", YEAR(StartYear) + INT(($A26-1)/PPY_Loan)) -> 2028 | C26: =IF($A26="", "", MOD(A26-1, PPY_Loan)+1) -> 11 | D26: =IFERROR(IF($A26="", "",IF(J25<=0, 0,J25)), 0) -> 2239418.8 | E26: =IFERROR(IF($A26="", "", _xlfn.XLOOKUP(A26,Offset!A:A,Offset!I:I, 0)), 0) -> 24358.629 | F26: =IFERROR(IF($A26="", "", MAX(0, D26 - E26)), 0) -> 2215060.1 | G26: =IFERROR(IF($A26="", "", F26*(LoanRate/PPY_Loan)), 0) -> 14767.068 | H26: =IFERROR(IF($A26="", "", IF(D26<=0, 0, MIN(StdPayment, D26+G26))), 0) -> 27061.315 | I26: =IFERROR(IF($A26="", "", IF(D26<=0, 0,H26-G26)), 0) -> 12294.247 | J26: =IFERROR(IF($A26="", "", IF(D26<=0, 0, MAX(0, D26-I26))), 0) -> 2227124.5 | K26: =IFERROR(IF($A26="", "", IF(D26<=0, 0, E26*(LoanRate/PPY_Loan))), 0) -> 162.39086 | L26: =IFERROR(IF($A26="", "", L25+K26), 0) -> 14056.332 | M26: =IF($A26="","",M25+G26) -> 349534.76 | N26: =IF($A26="","",N25+H26) -> 622410.24 | O26: =IF($A26="","",IF(B26<>B25,O25+1,O25)) -> 2 | Q26: =IF(ROW()-3<=TotalPeriods_Loan,ROW()-3,"") -> 23 | R26: =IF($Q26="", "", YEAR(StartYear) + INT(($Q26-1)/PPY_Loan)) -> 2028 | S26: =IF($Q26="", "", MOD(Q26-1, PPY_Loan)+1) -> 11 | T26: =IFERROR(IF($Q26="", "",IF(X25<=0, 0, X25)), 0) -> 2254575.5 | U26: =IFERROR(IF($Q26="", "", T26*(LoanRate/PPY_Loan)), 0) -> 15030.503 | V26: =IFERROR(IF($Q26="", "", IF(T26<=0, 0, MIN(StdPayment, T26+U26))), 0) -> 27061.315 | W26: =IFERROR(IF($Q26="", "", IF(T26<=0, 0, V26-U26)), 0) -> 12030.812 | X26: =IFERROR(IF($Q26="", "", IF(T26<=0, 0, MAX(0, T26-W26))), 0) -> 2242544.6 | Y26: =IF($Q26="","",Y25+U26) -> 364954.88 | Z26: =IF($Q26="","",Z25+V26) -> 622410.24 | AA26: =IF($Q26="","",IF(R26<>R25,AA25+1,AA25)) -> 2 | AC26: =IF(ROW()-3<=TotalPeriods_Loan,ROW()-3,"") -> 23 | AD26: =IF($AC26="", "", YEAR(StartYear) + INT(($AC26-1)/PPY_Loan)) -> 2028 | AE26: =IF($AC26="", "", MOD(AC26-1, PPY_Loan)+1) -> 11 | AF26: =IFERROR(IF($AC26="", "",IF(AJ25<=0, 0, AJ25)), 0) -> 2239228.5 | AG26: =IFERROR(IF($AC26="", "", AF26*(LoanRate/PPY_Loan)), 0) -> 14928.19 | AH26: =IFERROR(IF($AC26="", "", IF(AF26<=0, 0, MIN(StdPayment+IF(ISBLANK(ExtraRepay),0,ExtraRepay), AF26+AG26))), 0) -> 27711.315 | AI26: =IFERROR(IF($AC26="", "", IF(AF26<=0, 0, AH26-AG26)), 0) -> 12783.124 | AJ26: =IFERROR(IF($AC26="", "", IF(AF26<=0, 0, MAX(0, AF26-AI26))), 0) -> 2226445.4 | AK26: =IF($AC26="","",AK25+AG26) -> 363805.63 | AL26: =IF($AC26="","",AL25+AH26) -> 637360.24 | AM26: =IF($AC26="","",IF(AD26<>AD25,AM25+1,AM25)) -> 2
A27: =IF(ROW()-3<=TotalPeriods_Loan,ROW()-3,"") -> 24 | B27: =IF($A27="", "", YEAR(StartYear) + INT(($A27-1)/PPY_Loan)) -> 2028 | C27: =IF($A27="", "", MOD(A27-1, PPY_Loan)+1) -> 12 | D27: =IFERROR(IF($A27="", "",IF(J26<=0, 0,J26)), 0) -> 2227124.5 | E27: =IFERROR(IF($A27="", "", _xlfn.XLOOKUP(A27,Offset!A:A,Offset!I:I, 0)), 0) -> 26573.05 | F27: =IFERROR(IF($A27="", "", MAX(0, D27 - E27)), 0) -> 2200551.5 | G27: =IFERROR(IF($A27="", "", F27*(LoanRate/PPY_Loan)), 0) -> 14670.343 | H27: =IFERROR(IF($A27="", "", IF(D27<=0, 0, MIN(StdPayment, D27+G27))), 0) -> 27061.315 | I27: =IFERROR(IF($A27="", "", IF(D27<=0, 0,H27-G27)), 0) -> 12390.971 | J27: =IFERROR(IF($A27="", "", IF(D27<=0, 0, MAX(0, D27-I27))), 0) -> 2214733.6 | K27: =IFERROR(IF($A27="", "", IF(D27<=0, 0, E27*(LoanRate/PPY_Loan))), 0) -> 177.15367 | L27: =IFERROR(IF($A27="", "", L26+K27), 0) -> 14233.486 | M27: =IF($A27="","",M26+G27) -> 364205.1 | N27: =IF($A27="","",N26+H27) -> 649471.55 | O27: =IF($A27="","",IF(B27<>B26,O26+1,O26)) -> 2 | Q27: =IF(ROW()-3<=TotalPeriods_Loan,ROW()-3,"") -> 24 | R27: =IF($Q27="", "", YEAR(StartYear) + INT(($Q27-1)/PPY_Loan)) -> 2028 | S27: =IF($Q27="", "", MOD(Q27-1, PPY_Loan)+1) -> 12 | T27: =IFERROR(IF($Q27="", "",IF(X26<=0, 0, X26)), 0) -> 2242544.6 | U27: =IFERROR(IF($Q27="", "", T27*(LoanRate/PPY_Loan)), 0) -> 14950.298 | V27: =IFERROR(IF($Q27="", "", IF(T27<=0, 0, MIN(StdPayment, T27+U27))), 0) -> 27061.315 | W27: =IFERROR(IF($Q27="", "", IF(T27<=0, 0, V27-U27)), 0) -> 12111.017 | X27: =IFERROR(IF($Q27="", "", IF(T27<=0, 0, MAX(0, T27-W27))), 0) -> 2230433.6 | Y27: =IF($Q27="","",Y26+U27) -> 379905.17 | Z27: =IF($Q27="","",Z26+V27) -> 649471.55 | AA27: =IF($Q27="","",IF(R27<>R26,AA26+1,AA26)) -> 2 | AC27: =IF(ROW()-3<=TotalPeriods_Loan,ROW()-3,"") -> 24 | AD27: =IF($AC27="", "", YEAR(StartYear) + INT(($AC27-1)/PPY_Loan)) -> 2028 | AE27: =IF($AC27="", "", MOD(AC27-1, PPY_Loan)+1) -> 12 | AF27: =IFERROR(IF($AC27="", "",IF(AJ26<=0, 0, AJ26)), 0) -> 2226445.4 | AG27: =IFERROR(IF($AC27="", "", AF27*(LoanRate/PPY_Loan)), 0) -> 14842.969 | AH27: =IFERROR(IF($AC27="", "", IF(AF27<=0, 0, MIN(StdPayment+IF(ISBLANK(ExtraRepay),0,ExtraRepay), AF27+AG27))), 0) -> 27711.315 | AI27: =IFERROR(IF($AC27="", "", IF(AF27<=0, 0, AH27-AG27)), 0) -> 12868.345 | AJ27: =IFERROR(IF($AC27="", "", IF(AF27<=0, 0, MAX(0, AF27-AI27))), 0) -> 2213577 | AK27: =IF($AC27="","",AK26+AG27) -> 378648.6 | AL27: =IF($AC27="","",AL26+AH27) -> 665071.55 | AM27: =IF($AC27="","",IF(AD27<>AD26,AM26+1,AM26)) -> 2
A28: =IF(ROW()-3<=TotalPeriods_Loan,ROW()-3,"") -> 25 | B28: =IF($A28="", "", YEAR(StartYear) + INT(($A28-1)/PPY_Loan)) -> 2029 | C28: =IF($A28="", "", MOD(A28-1, PPY_Loan)+1) -> 1 | D28: =IFERROR(IF($A28="", "",IF(J27<=0, 0,J27)), 0) -> 2214733.6 | E28: =IFERROR(IF($A28="", "", _xlfn.XLOOKUP(A28,Offset!A:A,Offset!I:I, 0)), 0) -> 2671.9689 | F28: =IFERROR(IF($A28="", "", MAX(0, D28 - E28)), 0) -> 2212061.6 | G28: =IFERROR(IF($A28="", "", F28*(LoanRate/PPY_Loan)), 0) -> 14747.077 | H28: =IFERROR(IF($A28="", "", IF(D28<=0, 0, MIN(StdPayment, D28+G28))), 0) -> 27061.315 | I28: =IFERROR(IF($A28="", "", IF(D28<=0, 0,H28-G28)), 0) -> 12314.237 | J28: =IFERROR(IF($A28="", "", IF(D28<=0, 0, MAX(0, D28-I28))), 0) -> 2202419.3 | K28: =IFERROR(IF($A28="", "", IF(D28<=0, 0, E28*(LoanRate/PPY_Loan))), 0) -> 17.813126 | L28: =IFERROR(IF($A28="", "", L27+K28), 0) -> 14251.299 | M28: =IF($A28="","",M27+G28) -> 378952.18 | N28: =IF($A28="","",N27+H28) -> 676532.86 | O28: =IF($A28="","",IF(B28<>B27,O27+1,O27)) -> 3 | Q28: =IF(ROW()-3<=TotalPeriods_Loan,ROW()-3,"") -> 25 | R28: =IF($Q28="", "", YEAR(StartYear) + INT(($Q28-1)/PPY_Loan)) -> 2029 | S28: =IF($Q28="", "", MOD(Q28-1, PPY_Loan)+1) -> 1 | T28: =IFERROR(IF($Q28="", "",IF(X27<=0, 0, X27)), 0) -> 2230433.6 | U28: =IFERROR(IF($Q28="", "", T28*(LoanRate/PPY_Loan)), 0) -> 14869.557 | V28: =IFERROR(IF($Q28="", "", IF(T28<=0, 0, MIN(StdPayment, T28+U28))), 0) -> 27061.315 | W28: =IFERROR(IF($Q28="", "", IF(T28<=0, 0, V28-U28)), 0) -> 12191.757 | X28: =IFERROR(IF($Q28="", "", IF(T28<=0, 0, MAX(0, T28-W28))), 0) -> 2218241.9 | Y28: =IF($Q28="","",Y27+U28) -> 394774.73 | Z28: =IF($Q28="","",Z27+V28) -> 676532.86 | AA28: =IF($Q28="","",IF(R28<>R27,AA27+1,AA27)) -> 3 | AC28: =IF(ROW()-3<=TotalPeriods_Loan,ROW()-3,"") -> 25 | AD28: =IF($AC28="", "", YEAR(StartYear) + INT(($AC28-1)/PPY_Loan)) -> 2029 | AE28: =IF($AC28="", "", MOD(AC28-1, PPY_Loan)+1) -> 1 | AF28: =IFERROR(IF($AC28="", "",IF(AJ27<=0, 0, AJ27)), 0) -> 2213577 | AG28: =IFERROR(IF($AC28="", "", AF28*(LoanRate/PPY_Loan)), 0) -> 14757.18 | AH28: =IFERROR(IF($AC28="", "", IF(AF28<=0, 0, MIN(StdPayment+IF(ISBLANK(ExtraRepay),0,ExtraRepay), AF28+AG28))), 0) -> 27711.315 | AI28: =IFERROR(IF($AC28="", "", IF(AF28<=0, 0, AH28-AG28)), 0) -> 12954.134 | AJ28: =IFERROR(IF($AC28="", "", IF(AF28<=0, 0, MAX(0, AF28-AI28))), 0) -> 2200622.9 | AK28: =IF($AC28="","",AK27+AG28) -> 393405.78 | AL28: =IF($AC28="","",AL27+AH28) -> 692782.86 | AM28: =IF($AC28="","",IF(AD28<>AD27,AM27+1,AM27)) -> 3
... A183: =IF(ROW()-3<=TotalPeriods_Loan,ROW()-3,"") -> 180 | B183: =IF($A183="", "", YEAR(StartYear) + INT(($A183-1)/PPY_Loan)) -> 2041 | C183: =IF($A183="", "", MOD(A183-1, PPY_Loan)+1) -> 12 | D183: =IFERROR(IF($A183="", "",IF(J182<=0, 0,J182)), 0) -> 0 | E183: =IFERROR(IF($A183="", "", _xlfn.XLOOKUP(A183,Offset!A:A,Offset!I:I, 0)), 0) -> 16172.826 | F183: =IFERROR(IF($A183="", "", MAX(0, D183 - E183)), 0) -> 0 | G183: =IFERROR(IF($A183="", "", F183*(LoanRate/PPY_Loan)), 0) -> 0 | H183: =IFERROR(IF($A183="", "", IF(D183<=0, 0, MIN(StdPayment, D183+G183))), 0) -> 0 | I183: =IFERROR(IF($A183="", "", IF(D183<=0, 0,H183-G183)), 0) -> 0 | J183: =IFERROR(IF($A183="", "", IF(D183<=0, 0, MAX(0, D183-I183))), 0) -> 0 | K183: =IFERROR(IF($A183="", "", IF(D183<=0, 0, E183*(LoanRate/PPY_Loan))), 0) -> 0 | L183: =IFERROR(IF($A183="", "", L182+K183), 0) -> 30271.925 | M183: =IF($A183="","",M182+G183) -> 1338584.5 | N183: =IF($A183="","",N182+H183) -> 3838584.5 | O183: =IF($A183="","",IF(B183<>B182,O182+1,O182)) -> 15 | Q183: =IF(ROW()-3<=TotalPeriods_Loan,ROW()-3,"") -> 180 | R183: =IF($Q183="", "", YEAR(StartYear) + INT(($Q183-1)/PPY_Loan)) -> 2041 | S183: =IF($Q183="", "", MOD(Q183-1, PPY_Loan)+1) -> 12 | T183: =IFERROR(IF($Q183="", "",IF(X182<=0, 0, X182)), 0) -> 0 | U183: =IFERROR(IF($Q183="", "", T183*(LoanRate/PPY_Loan)), 0) -> 0 | V183: =IFERROR(IF($Q183="", "", IF(T183<=0, 0, MIN(StdPayment, T183+U183))), 0) -> 0 | W183: =IFERROR(IF($Q183="", "", IF(T183<=0, 0, V183-U183)), 0) -> 0 | X183: =IFERROR(IF($Q183="", "", IF(T183<=0, 0, MAX(0, T183-W183))), 0) -> 0 | Y183: =IF($Q183="","",Y182+U183) -> 1396829.3 | Z183: =IF($Q183="","",Z182+V183) -> 3896829.3 | AA183: =IF($Q183="","",IF(R183<>R182,AA182+1,AA182)) -> 15 | AC183: =IF(ROW()-3<=TotalPeriods_Loan,ROW()-3,"") -> 180 | AD183: =IF($AC183="", "", YEAR(StartYear) + INT(($AC183-1)/PPY_Loan)) -> 2041 | AE183: =IF($AC183="", "", MOD(AC183-1, PPY_Loan)+1) -> 12 | AF183: =IFERROR(IF($AC183="", "",IF(AJ182<=0, 0, AJ182)), 0) -> 0 | AG183: =IFERROR(IF($AC183="", "", AF183*(LoanRate/PPY_Loan)), 0) -> 0 | AH183: =IFERROR(IF($AC183="", "", IF(AF183<=0, 0, MIN(StdPayment+IF(ISBLANK(ExtraRepay),0,ExtraRepay), AF183+AG183))), 0) -> 0 | AI183: =IFERROR(IF($AC183="", "", IF(AF183<=0, 0, AH183-AG183)), 0) -> 0 | AJ183: =IFERROR(IF($AC183="", "", IF(AF183<=0, 0, MAX(0, AF183-AI183))), 0) -> 0 | AK183: =IF($AC183="","",AK182+AG183) -> 1336478.7 | AL183: =IF($AC183="","",AL182+AH183) -> 3836478.7 | AM183: =IF($AC183="","",IF(AD183<>AD182,AM182+1,AM182)) -> 15
A184: =IF(ROW()-3<=TotalPeriods_Loan,ROW()-3,"") | B184: =IF($A184="", "", YEAR(StartYear) + INT(($A184-1)/PPY_Loan)) | C184: =IF($A184="", "", MOD(A184-1, PPY_Loan)+1) | D184: =IFERROR(IF($A184="", "",IF(J159<=0, 0,J159)), 0) | E184: =IFERROR(IF($A184="", "", _xlfn.XLOOKUP(A184,Offset!A:A,Offset!I:I, 0)), 0) | F184: =IFERROR(IF($A184="", "", MAX(0, D184 - E184)), 0) | G184: =IFERROR(IF($A184="", "", F184*(LoanRate/PPY_Loan)), 0) | H184: =IFERROR(IF($A184="", "", IF(D184<=0, 0, MIN(StdPayment, D184+G184))), 0) | I184: =IFERROR(IF($A184="", "", IF(D184<=0, 0,H184-G184)), 0) | J184: =IFERROR(IF($A184="", "", IF(D184<=0, 0, MAX(0, D184-I184))), 0) | K184: =IFERROR(IF($A184="", "", IF(D184<=0, 0, E184*(LoanRate/PPY_Loan))), 0) | L184: =IFERROR(IF($A184="", "", L159+K184), 0) | M184: =IF($A184="","",M159+G184) | N184: =IF($A184="","",N159+H184) | O184: =IF($A184="","",IF(B184<>B159,O159+1,O159)) | Q184: =IF(ROW()-3<=TotalPeriods_Loan,ROW()-3,"") | R184: =IF($Q184="", "", YEAR(StartYear) + INT(($Q184-1)/PPY_Loan)) | S184: =IF($Q184="", "", MOD(Q184-1, PPY_Loan)+1) | T184: =IFERROR(IF($Q184="", "",IF(X159<=0, 0, X159)), 0) | U184: =IFERROR(IF($Q184="", "", T184*(LoanRate/PPY_Loan)), 0) | V184: =IFERROR(IF($Q184="", "", IF(T184<=0, 0, MIN(StdPayment, T184+U184))), 0) | W184: =IFERROR(IF($Q184="", "", IF(T184<=0, 0, V184-U184)), 0) | X184: =IFERROR(IF($Q184="", "", IF(T184<=0, 0, MAX(0, T184-W184))), 0) | Y184: =IF($Q184="","",Y159+U184) | Z184: =IF($Q184="","",Z159+V184) | AA184: =IF($Q184="","",IF(R184<>R159,AA159+1,AA159)) | AC184: =IF(ROW()-3<=TotalPeriods_Loan,ROW()-3,"") | AD184: =IF($AC184="", "", YEAR(StartYear) + INT(($AC184-1)/PPY_Loan)) | AE184: =IF($AC184="", "", MOD(AC184-1, PPY_Loan)+1) | AF184: =IFERROR(IF($AC184="", "",IF(AJ159<=0, 0, AJ159)), 0) | AG184: =IFERROR(IF($AC184="", "", AF184*(LoanRate/PPY_Loan)), 0) | AH184: =IFERROR(IF($AC184="", "", IF(AF184<=0, 0, MIN(StdPayment+IF(ISBLANK(ExtraRepay),0,ExtraRepay), AF184+AG184))), 0) | AI184: =IFERROR(IF($AC184="", "", IF(AF184<=0, 0, AH184-AG184)), 0) | AJ184: =IFERROR(IF($AC184="", "", IF(AF184<=0, 0, MAX(0, AF184-AI184))), 0) | AK184: =IF($AC184="","",AK159+AG184) | AL184: =IF($AC184="","",AL159+AH184) | AM184: =IF($AC184="","",IF(AD184<>AD159,AM159+1,AM159))
A185: =IF(ROW()-3<=TotalPeriods_Loan,ROW()-3,"") | B185: =IF($A185="", "", YEAR(StartYear) + INT(($A185-1)/PPY_Loan)) | C185: =IF($A185="", "", MOD(A185-1, PPY_Loan)+1) | D185: =IFERROR(IF($A185="", "",IF(J184<=0, 0,J184)), 0) | E185: =IFERROR(IF($A185="", "", _xlfn.XLOOKUP(A185,Offset!A:A,Offset!I:I, 0)), 0) | F185: =IFERROR(IF($A185="", "", MAX(0, D185 - E185)), 0) | G185: =IFERROR(IF($A185="", "", F185*(LoanRate/PPY_Loan)), 0) | H185: =IFERROR(IF($A185="", "", IF(D185<=0, 0, MIN(StdPayment, D185+G185))), 0) | I185: =IFERROR(IF($A185="", "", IF(D185<=0, 0,H185-G185)), 0) | J185: =IFERROR(IF($A185="", "", IF(D185<=0, 0, MAX(0, D185-I185))), 0) | K185: =IFERROR(IF($A185="", "", IF(D185<=0, 0, E185*(LoanRate/PPY_Loan))), 0) | L185: =IFERROR(IF($A185="", "", L184+K185), 0) | M185: =IF($A185="","",M184+G185) | N185: =IF($A185="","",N184+H185) | O185: =IF($A185="","",IF(B185<>B184,O184+1,O184)) | Q185: =IF(ROW()-3<=TotalPeriods_Loan,ROW()-3,"") | R185: =IF($Q185="", "", YEAR(StartYear) + INT(($Q185-1)/PPY_Loan)) | S185: =IF($Q185="", "", MOD(Q185-1, PPY_Loan)+1) | T185: =IFERROR(IF($Q185="", "",IF(X184<=0, 0, X184)), 0) | U185: =IFERROR(IF($Q185="", "", T185*(LoanRate/PPY_Loan)), 0) | V185: =IFERROR(IF($Q185="", "", IF(T185<=0, 0, MIN(StdPayment, T185+U185))), 0) | W185: =IFERROR(IF($Q185="", "", IF(T185<=0, 0, V185-U185)), 0) | X185: =IFERROR(IF($Q185="", "", IF(T185<=0, 0, MAX(0, T185-W185))), 0) | Y185: =IF($Q185="","",Y184+U185) | Z185: =IF($Q185="","",Z184+V185) | AA185: =IF($Q185="","",IF(R185<>R184,AA184+1,AA184)) | AC185: =IF(ROW()-3<=TotalPeriods_Loan,ROW()-3,"") | AD185: =IF($AC185="", "", YEAR(StartYear) + INT(($AC185-1)/PPY_Loan)) | AE185: =IF($AC185="", "", MOD(AC185-1, PPY_Loan)+1) | AF185: =IFERROR(IF($AC185="", "",IF(AJ184<=0, 0, AJ184)), 0) | AG185: =IFERROR(IF($AC185="", "", AF185*(LoanRate/PPY_Loan)), 0) | AH185: =IFERROR(IF($AC185="", "", IF(AF185<=0, 0, MIN(StdPayment+IF(ISBLANK(ExtraRepay),0,ExtraRepay), AF185+AG185))), 0) | AI185: =IFERROR(IF($AC185="", "", IF(AF185<=0, 0, AH185-AG185)), 0) | AJ185: =IFERROR(IF($AC185="", "", IF(AF185<=0, 0, MAX(0, AF185-AI185))), 0) | AK185: =IF($AC185="","",AK184+AG185) | AL185: =IF($AC185="","",AL184+AH185) | AM185: =IF($AC185="","",IF(AD185<>AD184,AM184+1,AM184))
A186: =IF(ROW()-3<=TotalPeriods_Loan,ROW()-3,"") | B186: =IF($A186="", "", YEAR(StartYear) + INT(($A186-1)/PPY_Loan)) | C186: =IF($A186="", "", MOD(A186-1, PPY_Loan)+1) | D186: =IFERROR(IF($A186="", "",IF(J185<=0, 0,J185)), 0) | E186: =IFERROR(IF($A186="", "", _xlfn.XLOOKUP(A186,Offset!A:A,Offset!I:I, 0)), 0) | F186: =IFERROR(IF($A186="", "", MAX(0, D186 - E186)), 0) | G186: =IFERROR(IF($A186="", "", F186*(LoanRate/PPY_Loan)), 0) | H186: =IFERROR(IF($A186="", "", IF(D186<=0, 0, MIN(StdPayment, D186+G186))), 0) | I186: =IFERROR(IF($A186="", "", IF(D186<=0, 0,H186-G186)), 0) | J186: =IFERROR(IF($A186="", "", IF(D186<=0, 0, MAX(0, D186-I186))), 0) | K186: =IFERROR(IF($A186="", "", IF(D186<=0, 0, E186*(LoanRate/PPY_Loan))), 0) | L186: =IFERROR(IF($A186="", "", L185+K186), 0) | M186: =IF($A186="","",M185+G186) | N186: =IF($A186="","",N185+H186) | O186: =IF($A186="","",IF(B186<>B185,O185+1,O185)) | Q186: =IF(ROW()-3<=TotalPeriods_Loan,ROW()-3,"") | R186: =IF($Q186="", "", YEAR(StartYear) + INT(($Q186-1)/PPY_Loan)) | S186: =IF($Q186="", "", MOD(Q186-1, PPY_Loan)+1) | T186: =IFERROR(IF($Q186="", "",IF(X185<=0, 0, X185)), 0) | U186: =IFERROR(IF($Q186="", "", T186*(LoanRate/PPY_Loan)), 0) | V186: =IFERROR(IF($Q186="", "", IF(T186<=0, 0, MIN(StdPayment, T186+U186))), 0) | W186: =IFERROR(IF($Q186="", "", IF(T186<=0, 0, V186-U186)), 0) | X186: =IFERROR(IF($Q186="", "", IF(T186<=0, 0, MAX(0, T186-W186))), 0) | Y186: =IF($Q186="","",Y185+U186) | Z186: =IF($Q186="","",Z185+V186) | AA186: =IF($Q186="","",IF(R186<>R185,AA185+1,AA185)) | AC186: =IF(ROW()-3<=TotalPeriods_Loan,ROW()-3,"") | AD186: =IF($AC186="", "", YEAR(StartYear) + INT(($AC186-1)/PPY_Loan)) | AE186: =IF($AC186="", "", MOD(AC186-1, PPY_Loan)+1) | AF186: =IFERROR(IF($AC186="", "",IF(AJ185<=0, 0, AJ185)), 0) | AG186: =IFERROR(IF($AC186="", "", AF186*(LoanRate/PPY_Loan)), 0) | AH186: =IFERROR(IF($AC186="", "", IF(AF186<=0, 0, MIN(StdPayment+IF(ISBLANK(ExtraRepay),0,ExtraRepay), AF186+AG186))), 0) | AI186: =IFERROR(IF($AC186="", "", IF(AF186<=0, 0, AH186-AG186)), 0) | AJ186: =IFERROR(IF($AC186="", "", IF(AF186<=0, 0, MAX(0, AF186-AI186))), 0) | AK186: =IF($AC186="","",AK185+AG186) | AL186: =IF($AC186="","",AL185+AH186) | AM186: =IF($AC186="","",IF(AD186<>AD185,AM185+1,AM185))
A187: =IF(ROW()-3<=TotalPeriods_Loan,ROW()-3,"") | B187: =IF($A187="", "", YEAR(StartYear) + INT(($A187-1)/PPY_Loan)) | C187: =IF($A187="", "", MOD(A187-1, PPY_Loan)+1) | D187: =IFERROR(IF($A187="", "",IF(J186<=0, 0,J186)), 0) | E187: =IFERROR(IF($A187="", "", _xlfn.XLOOKUP(A187,Offset!A:A,Offset!I:I, 0)), 0) | F187: =IFERROR(IF($A187="", "", MAX(0, D187 - E187)), 0) | G187: =IFERROR(IF($A187="", "", F187*(LoanRate/PPY_Loan)), 0) | H187: =IFERROR(IF($A187="", "", IF(D187<=0, 0, MIN(StdPayment, D187+G187))), 0) | I187: =IFERROR(IF($A187="", "", IF(D187<=0, 0,H187-G187)), 0) | J187: =IFERROR(IF($A187="", "", IF(D187<=0, 0, MAX(0, D187-I187))), 0) | K187: =IFERROR(IF($A187="", "", IF(D187<=0, 0, E187*(LoanRate/PPY_Loan))), 0) | L187: =IFERROR(IF($A187="", "", L186+K187), 0) | M187: =IF($A187="","",M186+G187) | N187: =IF($A187="","",N186+H187) | O187: =IF($A187="","",IF(B187<>B186,O186+1,O186)) | Q187: =IF(ROW()-3<=TotalPeriods_Loan,ROW()-3,"") | R187: =IF($Q187="", "", YEAR(StartYear) + INT(($Q187-1)/PPY_Loan)) | S187: =IF($Q187="", "", MOD(Q187-1, PPY_Loan)+1) | T187: =IFERROR(IF($Q187="", "",IF(X186<=0, 0, X186)), 0) | U187: =IFERROR(IF($Q187="", "", T187*(LoanRate/PPY_Loan)), 0) | V187: =IFERROR(IF($Q187="", "", IF(T187<=0, 0, MIN(StdPayment, T187+U187))), 0) | W187: =IFERROR(IF($Q187="", "", IF(T187<=0, 0, V187-U187)), 0) | X187: =IFERROR(IF($Q187="", "", IF(T187<=0, 0, MAX(0, T187-W187))), 0) | Y187: =IF($Q187="","",Y186+U187) | Z187: =IF($Q187="","",Z186+V187) | AA187: =IF($Q187="","",IF(R187<>R186,AA186+1,AA186)) | AC187: =IF(ROW()-3<=TotalPeriods_Loan,ROW()-3,"") | AD187: =IF($AC187="", "", YEAR(StartYear) + INT(($AC187-1)/PPY_Loan)) | AE187: =IF($AC187="", "", MOD(AC187-1, PPY_Loan)+1) | AF187: =IFERROR(IF($AC187="", "",IF(AJ186<=0, 0, AJ186)), 0) | AG187: =IFERROR(IF($AC187="", "", AF187*(LoanRate/PPY_Loan)), 0) | AH187: =IFERROR(IF($AC187="", "", IF(AF187<=0, 0, MIN(StdPayment+IF(ISBLANK(ExtraRepay),0,ExtraRepay), AF187+AG187))), 0) | AI187: =IFERROR(IF($AC187="", "", IF(AF187<=0, 0, AH187-AG187)), 0) | AJ187: =IFERROR(IF($AC187="", "", IF(AF187<=0, 0, MAX(0, AF187-AI187))), 0) | AK187: =IF($AC187="","",AK186+AG187) | AL187: =IF($AC187="","",AL186+AH187) | AM187: =IF($AC187="","",IF(AD187<>AD186,AM186+1,AM186))
A188: =IF(ROW()-3<=TotalPeriods_Loan,ROW()-3,"") | B188: =IF($A188="", "", YEAR(StartYear) + INT(($A188-1)/PPY_Loan)) | C188: =IF($A188="", "", MOD(A188-1, PPY_Loan)+1) | D188: =IFERROR(IF($A188="", "",IF(J187<=0, 0,J187)), 0) | E188: =IFERROR(IF($A188="", "", _xlfn.XLOOKUP(A188,Offset!A:A,Offset!I:I, 0)), 0) | F188: =IFERROR(IF($A188="", "", MAX(0, D188 - E188)), 0) | G188: =IFERROR(IF($A188="", "", F188*(LoanRate/PPY_Loan)), 0) | H188: =IFERROR(IF($A188="", "", IF(D188<=0, 0, MIN(StdPayment, D188+G188))), 0) | I188: =IFERROR(IF($A188="", "", IF(D188<=0, 0,H188-G188)), 0) | J188: =IFERROR(IF($A188="", "", IF(D188<=0, 0, MAX(0, D188-I188))), 0) | K188: =IFERROR(IF($A188="", "", IF(D188<=0, 0, E188*(LoanRate/PPY_Loan))), 0) | L188: =IFERROR(IF($A188="", "", L187+K188), 0) | M188: =IF($A188="","",M187+G188) | N188: =IF($A188="","",N187+H188) | O188: =IF($A188="","",IF(B188<>B187,O187+1,O187)) | Q188: =IF(ROW()-3<=TotalPeriods_Loan,ROW()-3,"") | R188: =IF($Q188="", "", YEAR(StartYear) + INT(($Q188-1)/PPY_Loan)) | S188: =IF($Q188="", "", MOD(Q188-1, PPY_Loan)+1) | T188: =IFERROR(IF($Q188="", "",IF(X187<=0, 0, X187)), 0) | U188: =IFERROR(IF($Q188="", "", T188*(LoanRate/PPY_Loan)), 0) | V188: =IFERROR(IF($Q188="", "", IF(T188<=0, 0, MIN(StdPayment, T188+U188))), 0) | W188: =IFERROR(IF($Q188="", "", IF(T188<=0, 0, V188-U188)), 0) | X188: =IFERROR(IF($Q188="", "", IF(T188<=0, 0, MAX(0, T188-W188))), 0) | Y188: =IF($Q188="","",Y187+U188) | Z188: =IF($Q188="","",Z187+V188) | AA188: =IF($Q188="","",IF(R188<>R187,AA187+1,AA187)) | AC188: =IF(ROW()-3<=TotalPeriods_Loan,ROW()-3,"") | AD188: =IF($AC188="", "", YEAR(StartYear) + INT(($AC188-1)/PPY_Loan)) | AE188: =IF($AC188="", "", MOD(AC188-1, PPY_Loan)+1) | AF188: =IFERROR(IF($AC188="", "",IF(AJ187<=0, 0, AJ187)), 0) | AG188: =IFERROR(IF($AC188="", "", AF188*(LoanRate/PPY_Loan)), 0) | AH188: =IFERROR(IF($AC188="", "", IF(AF188<=0, 0, MIN(StdPayment+IF(ISBLANK(ExtraRepay),0,ExtraRepay), AF188+AG188))), 0) | AI188: =IFERROR(IF($AC188="", "", IF(AF188<=0, 0, AH188-AG188)), 0) | AJ188: =IFERROR(IF($AC188="", "", IF(AF188<=0, 0, MAX(0, AF188-AI188))), 0) | AK188: =IF($AC188="","",AK187+AG188) | AL188: =IF($AC188="","",AL187+AH188) | AM188: =IF($AC188="","",IF(AD188<>AD187,AM187+1,AM187))
A189: =IF(ROW()-3<=TotalPeriods_Loan,ROW()-3,"") | B189: =IF($A189="", "", YEAR(StartYear) + INT(($A189-1)/PPY_Loan)) | C189: =IF($A189="", "", MOD(A189-1, PPY_Loan)+1) | D189: =IFERROR(IF($A189="", "",IF(J188<=0, 0,J188)), 0) | E189: =IFERROR(IF($A189="", "", _xlfn.XLOOKUP(A189,Offset!A:A,Offset!I:I, 0)), 0) | F189: =IFERROR(IF($A189="", "", MAX(0, D189 - E189)), 0) | G189: =IFERROR(IF($A189="", "", F189*(LoanRate/PPY_Loan)), 0) | H189: =IFERROR(IF($A189="", "", IF(D189<=0, 0, MIN(StdPayment, D189+G189))), 0) | I189: =IFERROR(IF($A189="", "", IF(D189<=0, 0,H189-G189)), 0) | J189: =IFERROR(IF($A189="", "", IF(D189<=0, 0, MAX(0, D189-I189))), 0) | K189: =IFERROR(IF($A189="", "", IF(D189<=0, 0, E189*(LoanRate/PPY_Loan))), 0) | L189: =IFERROR(IF($A189="", "", L188+K189), 0) | M189: =IF($A189="","",M188+G189) | N189: =IF($A189="","",N188+H189) | O189: =IF($A189="","",IF(B189<>B188,O188+1,O188)) | Q189: =IF(ROW()-3<=TotalPeriods_Loan,ROW()-3,"") | R189: =IF($Q189="", "", YEAR(StartYear) + INT(($Q189-1)/PPY_Loan)) | S189: =IF($Q189="", "", MOD(Q189-1, PPY_Loan)+1) | T189: =IFERROR(IF($Q189="", "",IF(X188<=0, 0, X188)), 0) | U189: =IFERROR(IF($Q189="", "", T189*(LoanRate/PPY_Loan)), 0) | V189: =IFERROR(IF($Q189="", "", IF(T189<=0, 0, MIN(StdPayment, T189+U189))), 0) | W189: =IFERROR(IF($Q189="", "", IF(T189<=0, 0, V189-U189)), 0) | X189: =IFERROR(IF($Q189="", "", IF(T189<=0, 0, MAX(0, T189-W189))), 0) | Y189: =IF($Q189="","",Y188+U189) | Z189: =IF($Q189="","",Z188+V189) | AA189: =IF($Q189="","",IF(R189<>R188,AA188+1,AA188)) | AC189: =IF(ROW()-3<=TotalPeriods_Loan,ROW()-3,"") | AD189: =IF($AC189="", "", YEAR(StartYear) + INT(($AC189-1)/PPY_Loan)) | AE189: =IF($AC189="", "", MOD(AC189-1, PPY_Loan)+1) | AF189: =IFERROR(IF($AC189="", "",IF(AJ188<=0, 0, AJ188)), 0) | AG189: =IFERROR(IF($AC189="", "", AF189*(LoanRate/PPY_Loan)), 0) | AH189: =IFERROR(IF($AC189="", "", IF(AF189<=0, 0, MIN(StdPayment+IF(ISBLANK(ExtraRepay),0,ExtraRepay), AF189+AG189))), 0) | AI189: =IFERROR(IF($AC189="", "", IF(AF189<=0, 0, AH189-AG189)), 0) | AJ189: =IFERROR(IF($AC189="", "", IF(AF189<=0, 0, MAX(0, AF189-AI189))), 0) | AK189: =IF($AC189="","",AK188+AG189) | AL189: =IF($AC189="","",AL188+AH189) | AM189: =IF($AC189="","",IF(AD189<>AD188,AM188+1,AM188))
A190: =IF(ROW()-3<=TotalPeriods_Loan,ROW()-3,"") | B190: =IF($A190="", "", YEAR(StartYear) + INT(($A190-1)/PPY_Loan)) | C190: =IF($A190="", "", MOD(A190-1, PPY_Loan)+1) | D190: =IFERROR(IF($A190="", "",IF(J189<=0, 0,J189)), 0) | E190: =IFERROR(IF($A190="", "", _xlfn.XLOOKUP(A190,Offset!A:A,Offset!I:I, 0)), 0) | F190: =IFERROR(IF($A190="", "", MAX(0, D190 - E190)), 0) | G190: =IFERROR(IF($A190="", "", F190*(LoanRate/PPY_Loan)), 0) | H190: =IFERROR(IF($A190="", "", IF(D190<=0, 0, MIN(StdPayment, D190+G190))), 0) | I190: =IFERROR(IF($A190="", "", IF(D190<=0, 0,H190-G190)), 0) | J190: =IFERROR(IF($A190="", "", IF(D190<=0, 0, MAX(0, D190-I190))), 0) | K190: =IFERROR(IF($A190="", "", IF(D190<=0, 0, E190*(LoanRate/PPY_Loan))), 0) | L190: =IFERROR(IF($A190="", "", L189+K190), 0) | M190: =IF($A190="","",M189+G190) | N190: =IF($A190="","",N189+H190) | O190: =IF($A190="","",IF(B190<>B189,O189+1,O189)) | Q190: =IF(ROW()-3<=TotalPeriods_Loan,ROW()-3,"") | R190: =IF($Q190="", "", YEAR(StartYear) + INT(($Q190-1)/PPY_Loan)) | S190: =IF($Q190="", "", MOD(Q190-1, PPY_Loan)+1) | T190: =IFERROR(IF($Q190="", "",IF(X189<=0, 0, X189)), 0) | U190: =IFERROR(IF($Q190="", "", T190*(LoanRate/PPY_Loan)), 0) | V190: =IFERROR(IF($Q190="", "", IF(T190<=0, 0, MIN(StdPayment, T190+U190))), 0) | W190: =IFERROR(IF($Q190="", "", IF(T190<=0, 0, V190-U190)), 0) | X190: =IFERROR(IF($Q190="", "", IF(T190<=0, 0, MAX(0, T190-W190))), 0) | Y190: =IF($Q190="","",Y189+U190) | Z190: =IF($Q190="","",Z189+V190) | AA190: =IF($Q190="","",IF(R190<>R189,AA189+1,AA189)) | AC190: =IF(ROW()-3<=TotalPeriods_Loan,ROW()-3,"") | AD190: =IF($AC190="", "", YEAR(StartYear) + INT(($AC190-1)/PPY_Loan)) | AE190: =IF($AC190="", "", MOD(AC190-1, PPY_Loan)+1) | AF190: =IFERROR(IF($AC190="", "",IF(AJ189<=0, 0, AJ189)), 0) | AG190: =IFERROR(IF($AC190="", "", AF190*(LoanRate/PPY_Loan)), 0) | AH190: =IFERROR(IF($AC190="", "", IF(AF190<=0, 0, MIN(StdPayment+IF(ISBLANK(ExtraRepay),0,ExtraRepay), AF190+AG190))), 0) | AI190: =IFERROR(IF($AC190="", "", IF(AF190<=0, 0, AH190-AG190)), 0) | AJ190: =IFERROR(IF($AC190="", "", IF(AF190<=0, 0, MAX(0, AF190-AI190))), 0) | AK190: =IF($AC190="","",AK189+AG190) | AL190: =IF($AC190="","",AL189+AH190) | AM190: =IF($AC190="","",IF(AD190<>AD189,AM189+1,AM189))
A191: =IF(ROW()-3<=TotalPeriods_Loan,ROW()-3,"") | B191: =IF($A191="", "", YEAR(StartYear) + INT(($A191-1)/PPY_Loan)) | C191: =IF($A191="", "", MOD(A191-1, PPY_Loan)+1) | D191: =IFERROR(IF($A191="", "",IF(J190<=0, 0,J190)), 0) | E191: =IFERROR(IF($A191="", "", _xlfn.XLOOKUP(A191,Offset!A:A,Offset!I:I, 0)), 0) | F191: =IFERROR(IF($A191="", "", MAX(0, D191 - E191)), 0) | G191: =IFERROR(IF($A191="", "", F191*(LoanRate/PPY_Loan)), 0) | H191: =IFERROR(IF($A191="", "", IF(D191<=0, 0, MIN(StdPayment, D191+G191))), 0) | I191: =IFERROR(IF($A191="", "", IF(D191<=0, 0,H191-G191)), 0) | J191: =IFERROR(IF($A191="", "", IF(D191<=0, 0, MAX(0, D191-I191))), 0) | K191: =IFERROR(IF($A191="", "", IF(D191<=0, 0, E191*(LoanRate/PPY_Loan))), 0) | L191: =IFERROR(IF($A191="", "", L190+K191), 0) | M191: =IF($A191="","",M190+G191) | N191: =IF($A191="","",N190+H191) | O191: =IF($A191="","",IF(B191<>B190,O190+1,O190)) | Q191: =IF(ROW()-3<=TotalPeriods_Loan,ROW()-3,"") | R191: =IF($Q191="", "", YEAR(StartYear) + INT(($Q191-1)/PPY_Loan)) | S191: =IF($Q191="", "", MOD(Q191-1, PPY_Loan)+1) | T191: =IFERROR(IF($Q191="", "",IF(X190<=0, 0, X190)), 0) | U191: =IFERROR(IF($Q191="", "", T191*(LoanRate/PPY_Loan)), 0) | V191: =IFERROR(IF($Q191="", "", IF(T191<=0, 0, MIN(StdPayment, T191+U191))), 0) | W191: =IFERROR(IF($Q191="", "", IF(T191<=0, 0, V191-U191)), 0) | X191: =IFERROR(IF($Q191="", "", IF(T191<=0, 0, MAX(0, T191-W191))), 0) | Y191: =IF($Q191="","",Y190+U191) | Z191: =IF($Q191="","",Z190+V191) | AA191: =IF($Q191="","",IF(R191<>R190,AA190+1,AA190)) | AC191: =IF(ROW()-3<=TotalPeriods_Loan,ROW()-3,"") | AD191: =IF($AC191="", "", YEAR(StartYear) + INT(($AC191-1)/PPY_Loan)) | AE191: =IF($AC191="", "", MOD(AC191-1, PPY_Loan)+1) | AF191: =IFERROR(IF($AC191="", "",IF(AJ190<=0, 0, AJ190)), 0) | AG191: =IFERROR(IF($AC191="", "", AF191*(LoanRate/PPY_Loan)), 0) | AH191: =IFERROR(IF($AC191="", "", IF(AF191<=0, 0, MIN(StdPayment+IF(ISBLANK(ExtraRepay),0,ExtraRepay), AF191+AG191))), 0) | AI191: =IFERROR(IF($AC191="", "", IF(AF191<=0, 0, AH191-AG191)), 0) | AJ191: =IFERROR(IF($AC191="", "", IF(AF191<=0, 0, MAX(0, AF191-AI191))), 0) | AK191: =IF($AC191="","",AK190+AG191) | AL191: =IF($AC191="","",AL190+AH191) | AM191: =IF($AC191="","",IF(AD191<>AD190,AM190+1,AM190))
A192: =IF(ROW()-3<=TotalPeriods_Loan,ROW()-3,"") | B192: =IF($A192="", "", YEAR(StartYear) + INT(($A192-1)/PPY_Loan)) | C192: =IF($A192="", "", MOD(A192-1, PPY_Loan)+1) | D192: =IFERROR(IF($A192="", "",IF(J191<=0, 0,J191)), 0) | E192: =IFERROR(IF($A192="", "", _xlfn.XLOOKUP(A192,Offset!A:A,Offset!I:I, 0)), 0) | F192: =IFERROR(IF($A192="", "", MAX(0, D192 - E192)), 0) | G192: =IFERROR(IF($A192="", "", F192*(LoanRate/PPY_Loan)), 0) | H192: =IFERROR(IF($A192="", "", IF(D192<=0, 0, MIN(StdPayment, D192+G192))), 0) | I192: =IFERROR(IF($A192="", "", IF(D192<=0, 0,H192-G192)), 0) | J192: =IFERROR(IF($A192="", "", IF(D192<=0, 0, MAX(0, D192-I192))), 0) | K192: =IFERROR(IF($A192="", "", IF(D192<=0, 0, E192*(LoanRate/PPY_Loan))), 0) | L192: =IFERROR(IF($A192="", "", L191+K192), 0) | M192: =IF($A192="","",M191+G192) | N192: =IF($A192="","",N191+H192) | O192: =IF($A192="","",IF(B192<>B191,O191+1,O191)) | Q192: =IF(ROW()-3<=TotalPeriods_Loan,ROW()-3,"") | R192: =IF($Q192="", "", YEAR(StartYear) + INT(($Q192-1)/PPY_Loan)) | S192: =IF($Q192="", "", MOD(Q192-1, PPY_Loan)+1) | T192: =IFERROR(IF($Q192="", "",IF(X191<=0, 0, X191)), 0) | U192: =IFERROR(IF($Q192="", "", T192*(LoanRate/PPY_Loan)), 0) | V192: =IFERROR(IF($Q192="", "", IF(T192<=0, 0, MIN(StdPayment, T192+U192))), 0) | W192: =IFERROR(IF($Q192="", "", IF(T192<=0, 0, V192-U192)), 0) | X192: =IFERROR(IF($Q192="", "", IF(T192<=0, 0, MAX(0, T192-W192))), 0) | Y192: =IF($Q192="","",Y191+U192) | Z192: =IF($Q192="","",Z191+V192) | AA192: =IF($Q192="","",IF(R192<>R191,AA191+1,AA191)) | AC192: =IF(ROW()-3<=TotalPeriods_Loan,ROW()-3,"") | AD192: =IF($AC192="", "", YEAR(StartYear) + INT(($AC192-1)/PPY_Loan)) | AE192: =IF($AC192="", "", MOD(AC192-1, PPY_Loan)+1) | AF192: =IFERROR(IF($AC192="", "",IF(AJ191<=0, 0, AJ191)), 0) | AG192: =IFERROR(IF($AC192="", "", AF192*(LoanRate/PPY_Loan)), 0) | AH192: =IFERROR(IF($AC192="", "", IF(AF192<=0, 0, MIN(StdPayment+IF(ISBLANK(ExtraRepay),0,ExtraRepay), AF192+AG192))), 0) | AI192: =IFERROR(IF($AC192="", "", IF(AF192<=0, 0, AH192-AG192)), 0) | AJ192: =IFERROR(IF($AC192="", "", IF(AF192<=0, 0, MAX(0, AF192-AI192))), 0) | AK192: =IF($AC192="","",AK191+AG192) | AL192: =IF($AC192="","",AL191+AH192) | AM192: =IF($AC192="","",IF(AD192<>AD191,AM191+1,AM191))
A193: =IF(ROW()-3<=TotalPeriods_Loan,ROW()-3,"") | B193: =IF($A193="", "", YEAR(StartYear) + INT(($A193-1)/PPY_Loan)) | C193: =IF($A193="", "", MOD(A193-1, PPY_Loan)+1) | D193: =IFERROR(IF($A193="", "",IF(J192<=0, 0,J192)), 0) | E193: =IFERROR(IF($A193="", "", _xlfn.XLOOKUP(A193,Offset!A:A,Offset!I:I, 0)), 0) | F193: =IFERROR(IF($A193="", "", MAX(0, D193 - E193)), 0) | G193: =IFERROR(IF($A193="", "", F193*(LoanRate/PPY_Loan)), 0) | H193: =IFERROR(IF($A193="", "", IF(D193<=0, 0, MIN(StdPayment, D193+G193))), 0) | I193: =IFERROR(IF($A193="", "", IF(D193<=0, 0,H193-G193)), 0) | J193: =IFERROR(IF($A193="", "", IF(D193<=0, 0, MAX(0, D193-I193))), 0) | K193: =IFERROR(IF($A193="", "", IF(D193<=0, 0, E193*(LoanRate/PPY_Loan))), 0) | L193: =IFERROR(IF($A193="", "", L192+K193), 0) | M193: =IF($A193="","",M192+G193) | N193: =IF($A193="","",N192+H193) | O193: =IF($A193="","",IF(B193<>B192,O192+1,O192)) | Q193: =IF(ROW()-3<=TotalPeriods_Loan,ROW()-3,"") | R193: =IF($Q193="", "", YEAR(StartYear) + INT(($Q193-1)/PPY_Loan)) | S193: =IF($Q193="", "", MOD(Q193-1, PPY_Loan)+1) | T193: =IFERROR(IF($Q193="", "",IF(X192<=0, 0, X192)), 0) | U193: =IFERROR(IF($Q193="", "", T193*(LoanRate/PPY_Loan)), 0) | V193: =IFERROR(IF($Q193="", "", IF(T193<=0, 0, MIN(StdPayment, T193+U193))), 0) | W193: =IFERROR(IF($Q193="", "", IF(T193<=0, 0, V193-U193)), 0) | X193: =IFERROR(IF($Q193="", "", IF(T193<=0, 0, MAX(0, T193-W193))), 0) | Y193: =IF($Q193="","",Y192+U193) | Z193: =IF($Q193="","",Z192+V193) | AA193: =IF($Q193="","",IF(R193<>R192,AA192+1,AA192)) | AC193: =IF(ROW()-3<=TotalPeriods_Loan,ROW()-3,"") | AD193: =IF($AC193="", "", YEAR(StartYear) + INT(($AC193-1)/PPY_Loan)) | AE193: =IF($AC193="", "", MOD(AC193-1, PPY_Loan)+1) | AF193: =IFERROR(IF($AC193="", "",IF(AJ192<=0, 0, AJ192)), 0) | AG193: =IFERROR(IF($AC193="", "", AF193*(LoanRate/PPY_Loan)), 0) | AH193: =IFERROR(IF($AC193="", "", IF(AF193<=0, 0, MIN(StdPayment+IF(ISBLANK(ExtraRepay),0,ExtraRepay), AF193+AG193))), 0) | AI193: =IFERROR(IF($AC193="", "", IF(AF193<=0, 0, AH193-AG193)), 0) | AJ193: =IFERROR(IF($AC193="", "", IF(AF193<=0, 0, MAX(0, AF193-AI193))), 0) | AK193: =IF($AC193="","",AK192+AG193) | AL193: =IF($AC193="","",AL192+AH193) | AM193: =IF($AC193="","",IF(AD193<>AD192,AM192+1,AM192))
A194: =IF(ROW()-3<=TotalPeriods_Loan,ROW()-3,"") | B194: =IF($A194="", "", YEAR(StartYear) + INT(($A194-1)/PPY_Loan)) | C194: =IF($A194="", "", MOD(A194-1, PPY_Loan)+1) | D194: =IFERROR(IF($A194="", "",IF(J193<=0, 0,J193)), 0) | E194: =IFERROR(IF($A194="", "", _xlfn.XLOOKUP(A194,Offset!A:A,Offset!I:I, 0)), 0) | F194: =IFERROR(IF($A194="", "", MAX(0, D194 - E194)), 0) | G194: =IFERROR(IF($A194="", "", F194*(LoanRate/PPY_Loan)), 0) | H194: =IFERROR(IF($A194="", "", IF(D194<=0, 0, MIN(StdPayment, D194+G194))), 0) | I194: =IFERROR(IF($A194="", "", IF(D194<=0, 0,H194-G194)), 0) | J194: =IFERROR(IF($A194="", "", IF(D194<=0, 0, MAX(0, D194-I194))), 0) | K194: =IFERROR(IF($A194="", "", IF(D194<=0, 0, E194*(LoanRate/PPY_Loan))), 0) | L194: =IFERROR(IF($A194="", "", L193+K194), 0) | M194: =IF($A194="","",M193+G194) | N194: =IF($A194="","",N193+H194) | O194: =IF($A194="","",IF(B194<>B193,O193+1,O193)) | Q194: =IF(ROW()-3<=TotalPeriods_Loan,ROW()-3,"") | R194: =IF($Q194="", "", YEAR(StartYear) + INT(($Q194-1)/PPY_Loan)) | S194: =IF($Q194="", "", MOD(Q194-1, PPY_Loan)+1) | T194: =IFERROR(IF($Q194="", "",IF(X193<=0, 0, X193)), 0) | U194: =IFERROR(IF($Q194="", "", T194*(LoanRate/PPY_Loan)), 0) | V194: =IFERROR(IF($Q194="", "", IF(T194<=0, 0, MIN(StdPayment, T194+U194))), 0) | W194: =IFERROR(IF($Q194="", "", IF(T194<=0, 0, V194-U194)), 0) | X194: =IFERROR(IF($Q194="", "", IF(T194<=0, 0, MAX(0, T194-W194))), 0) | Y194: =IF($Q194="","",Y193+U194) | Z194: =IF($Q194="","",Z193+V194) | AA194: =IF($Q194="","",IF(R194<>R193,AA193+1,AA193)) | AC194: =IF(ROW()-3<=TotalPeriods_Loan,ROW()-3,"") | AD194: =IF($AC194="", "", YEAR(StartYear) + INT(($AC194-1)/PPY_Loan)) | AE194: =IF($AC194="", "", MOD(AC194-1, PPY_Loan)+1) | AF194: =IFERROR(IF($AC194="", "",IF(AJ193<=0, 0, AJ193)), 0) | AG194: =IFERROR(IF($AC194="", "", AF194*(LoanRate/PPY_Loan)), 0) | AH194: =IFERROR(IF($AC194="", "", IF(AF194<=0, 0, MIN(StdPayment+IF(ISBLANK(ExtraRepay),0,ExtraRepay), AF194+AG194))), 0) | AI194: =IFERROR(IF($AC194="", "", IF(AF194<=0, 0, AH194-AG194)), 0) | AJ194: =IFERROR(IF($AC194="", "", IF(AF194<=0, 0, MAX(0, AF194-AI194))), 0) | AK194: =IF($AC194="","",AK193+AG194) | AL194: =IF($AC194="","",AL193+AH194) | AM194: =IF($AC194="","",IF(AD194<>AD193,AM193+1,AM193))
A195: =IF(ROW()-3<=TotalPeriods_Loan,ROW()-3,"") | B195: =IF($A195="", "", YEAR(StartYear) + INT(($A195-1)/PPY_Loan)) | C195: =IF($A195="", "", MOD(A195-1, PPY_Loan)+1) | D195: =IFERROR(IF($A195="", "",IF(J194<=0, 0,J194)), 0) | E195: =IFERROR(IF($A195="", "", _xlfn.XLOOKUP(A195,Offset!A:A,Offset!I:I, 0)), 0) | F195: =IFERROR(IF($A195="", "", MAX(0, D195 - E195)), 0) | G195: =IFERROR(IF($A195="", "", F195*(LoanRate/PPY_Loan)), 0) | H195: =IFERROR(IF($A195="", "", IF(D195<=0, 0, MIN(StdPayment, D195+G195))), 0) | I195: =IFERROR(IF($A195="", "", IF(D195<=0, 0,H195-G195)), 0) | J195: =IFERROR(IF($A195="", "", IF(D195<=0, 0, MAX(0, D195-I195))), 0) | K195: =IFERROR(IF($A195="", "", IF(D195<=0, 0, E195*(LoanRate/PPY_Loan))), 0) | L195: =IFERROR(IF($A195="", "", L194+K195), 0) | M195: =IF($A195="","",M194+G195) | N195: =IF($A195="","",N194+H195) | O195: =IF($A195="","",IF(B195<>B194,O194+1,O194)) | Q195: =IF(ROW()-3<=TotalPeriods_Loan,ROW()-3,"") | R195: =IF($Q195="", "", YEAR(StartYear) + INT(($Q195-1)/PPY_Loan)) | S195: =IF($Q195="", "", MOD(Q195-1, PPY_Loan)+1) | T195: =IFERROR(IF($Q195="", "",IF(X194<=0, 0, X194)), 0) | U195: =IFERROR(IF($Q195="", "", T195*(LoanRate/PPY_Loan)), 0) | V195: =IFERROR(IF($Q195="", "", IF(T195<=0, 0, MIN(StdPayment, T195+U195))), 0) | W195: =IFERROR(IF($Q195="", "", IF(T195<=0, 0, V195-U195)), 0) | X195: =IFERROR(IF($Q195="", "", IF(T195<=0, 0, MAX(0, T195-W195))), 0) | Y195: =IF($Q195="","",Y194+U195) | Z195: =IF($Q195="","",Z194+V195) | AA195: =IF($Q195="","",IF(R195<>R194,AA194+1,AA194)) | AC195: =IF(ROW()-3<=TotalPeriods_Loan,ROW()-3,"") | AD195: =IF($AC195="", "", YEAR(StartYear) + INT(($AC195-1)/PPY_Loan)) | AE195: =IF($AC195="", "", MOD(AC195-1, PPY_Loan)+1) | AF195: =IFERROR(IF($AC195="", "",IF(AJ194<=0, 0, AJ194)), 0) | AG195: =IFERROR(IF($AC195="", "", AF195*(LoanRate/PPY_Loan)), 0) | AH195: =IFERROR(IF($AC195="", "", IF(AF195<=0, 0, MIN(StdPayment+IF(ISBLANK(ExtraRepay),0,ExtraRepay), AF195+AG195))), 0) | AI195: =IFERROR(IF($AC195="", "", IF(AF195<=0, 0, AH195-AG195)), 0) | AJ195: =IFERROR(IF($AC195="", "", IF(AF195<=0, 0, MAX(0, AF195-AI195))), 0) | AK195: =IF($AC195="","",AK194+AG195) | AL195: =IF($AC195="","",AL194+AH195) | AM195: =IF($AC195="","",IF(AD195<>AD194,AM194+1,AM194))
A196: =IF(ROW()-3<=TotalPeriods_Loan,ROW()-3,"") | B196: =IF($A196="", "", YEAR(StartYear) + INT(($A196-1)/PPY_Loan)) | C196: =IF($A196="", "", MOD(A196-1, PPY_Loan)+1) | D196: =IFERROR(IF($A196="", "",IF(J195<=0, 0,J195)), 0) | E196: =IFERROR(IF($A196="", "", _xlfn.XLOOKUP(A196,Offset!A:A,Offset!I:I, 0)), 0) | F196: =IFERROR(IF($A196="", "", MAX(0, D196 - E196)), 0) | G196: =IFERROR(IF($A196="", "", F196*(LoanRate/PPY_Loan)), 0) | H196: =IFERROR(IF($A196="", "", IF(D196<=0, 0, MIN(StdPayment, D196+G196))), 0) | I196: =IFERROR(IF($A196="", "", IF(D196<=0, 0,H196-G196)), 0) | J196: =IFERROR(IF($A196="", "", IF(D196<=0, 0, MAX(0, D196-I196))), 0) | K196: =IFERROR(IF($A196="", "", IF(D196<=0, 0, E196*(LoanRate/PPY_Loan))), 0) | L196: =IFERROR(IF($A196="", "", L195+K196), 0) | M196: =IF($A196="","",M195+G196) | N196: =IF($A196="","",N195+H196) | O196: =IF($A196="","",IF(B196<>B195,O195+1,O195)) | Q196: =IF(ROW()-3<=TotalPeriods_Loan,ROW()-3,"") | R196: =IF($Q196="", "", YEAR(StartYear) + INT(($Q196-1)/PPY_Loan)) | S196: =IF($Q196="", "", MOD(Q196-1, PPY_Loan)+1) | T196: =IFERROR(IF($Q196="", "",IF(X195<=0, 0, X195)), 0) | U196: =IFERROR(IF($Q196="", "", T196*(LoanRate/PPY_Loan)), 0) | V196: =IFERROR(IF($Q196="", "", IF(T196<=0, 0, MIN(StdPayment, T196+U196))), 0) | W196: =IFERROR(IF($Q196="", "", IF(T196<=0, 0, V196-U196)), 0) | X196: =IFERROR(IF($Q196="", "", IF(T196<=0, 0, MAX(0, T196-W196))), 0) | Y196: =IF($Q196="","",Y195+U196) | Z196: =IF($Q196="","",Z195+V196) | AA196: =IF($Q196="","",IF(R196<>R195,AA195+1,AA195)) | AC196: =IF(ROW()-3<=TotalPeriods_Loan,ROW()-3,"") | AD196: =IF($AC196="", "", YEAR(StartYear) + INT(($AC196-1)/PPY_Loan)) | AE196: =IF($AC196="", "", MOD(AC196-1, PPY_Loan)+1) | AF196: =IFERROR(IF($AC196="", "",IF(AJ195<=0, 0, AJ195)), 0) | AG196: =IFERROR(IF($AC196="", "", AF196*(LoanRate/PPY_Loan)), 0) | AH196: =IFERROR(IF($AC196="", "", IF(AF196<=0, 0, MIN(StdPayment+IF(ISBLANK(ExtraRepay),0,ExtraRepay), AF196+AG196))), 0) | AI196: =IFERROR(IF($AC196="", "", IF(AF196<=0, 0, AH196-AG196)), 0) | AJ196: =IFERROR(IF($AC196="", "", IF(AF196<=0, 0, MAX(0, AF196-AI196))), 0) | AK196: =IF($AC196="","",AK195+AG196) | AL196: =IF($AC196="","",AL195+AH196) | AM196: =IF($AC196="","",IF(AD196<>AD195,AM195+1,AM195))
... A279: =IF(ROW()-3<=TotalPeriods_Loan,ROW()-3,"") | B279: =IF($A279="", "", YEAR(StartYear) + INT(($A279-1)/PPY_Loan)) | C279: =IF($A279="", "", MOD(A279-1, PPY_Loan)+1) | D279: =IFERROR(IF($A279="", "",IF(J278<=0, 0,J278)), 0) | E279: =IFERROR(IF($A279="", "", _xlfn.XLOOKUP(A279,Offset!A:A,Offset!I:I, 0)), 0) | F279: =IFERROR(IF($A279="", "", MAX(0, D279 - E279)), 0) | G279: =IFERROR(IF($A279="", "", F279*(LoanRate/PPY_Loan)), 0) | H279: =IFERROR(IF($A279="", "", IF(D279<=0, 0, MIN(StdPayment, D279+G279))), 0) | I279: =IFERROR(IF($A279="", "", IF(D279<=0, 0,H279-G279)), 0) | J279: =IFERROR(IF($A279="", "", IF(D279<=0, 0, MAX(0, D279-I279))), 0) | K279: =IFERROR(IF($A279="", "", IF(D279<=0, 0, E279*(LoanRate/PPY_Loan))), 0) | L279: =IFERROR(IF($A279="", "", L278+K279), 0) | M279: =IF($A279="","",M278+G279) | N279: =IF($A279="","",N278+H279) | O279: =IF($A279="","",IF(B279<>B278,O278+1,O278)) | Q279: =IF(ROW()-3<=TotalPeriods_Loan,ROW()-3,"") | R279: =IF($Q279="", "", YEAR(StartYear) + INT(($Q279-1)/PPY_Loan)) | S279: =IF($Q279="", "", MOD(Q279-1, PPY_Loan)+1) | T279: =IFERROR(IF($Q279="", "",IF(X278<=0, 0, X278)), 0) | U279: =IFERROR(IF($Q279="", "", T279*(LoanRate/PPY_Loan)), 0) | V279: =IFERROR(IF($Q279="", "", IF(T279<=0, 0, MIN(StdPayment, T279+U279))), 0) | W279: =IFERROR(IF($Q279="", "", IF(T279<=0, 0, V279-U279)), 0) | X279: =IFERROR(IF($Q279="", "", IF(T279<=0, 0, MAX(0, T279-W279))), 0) | Y279: =IF($Q279="","",Y278+U279) | Z279: =IF($Q279="","",Z278+V279) | AA279: =IF($Q279="","",IF(R279<>R278,AA278+1,AA278)) | AC279: =IF(ROW()-3<=TotalPeriods_Loan,ROW()-3,"") | AD279: =IF($AC279="", "", YEAR(StartYear) + INT(($AC279-1)/PPY_Loan)) | AE279: =IF($AC279="", "", MOD(AC279-1, PPY_Loan)+1) | AF279: =IFERROR(IF($AC279="", "",IF(AJ278<=0, 0, AJ278)), 0) | AG279: =IFERROR(IF($AC279="", "", AF279*(LoanRate/PPY_Loan)), 0) | AH279: =IFERROR(IF($AC279="", "", IF(AF279<=0, 0, MIN(StdPayment+IF(ISBLANK(ExtraRepay),0,ExtraRepay), AF279+AG279))), 0) | AI279: =IFERROR(IF($AC279="", "", IF(AF279<=0, 0, AH279-AG279)), 0) | AJ279: =IFERROR(IF($AC279="", "", IF(AF279<=0, 0, MAX(0, AF279-AI279))), 0) | AK279: =IF($AC279="","",AK278+AG279) | AL279: =IF($AC279="","",AL278+AH279) | AM279: =IF($AC279="","",IF(AD279<>AD278,AM278+1,AM278))

Sheet Offset
A1: Tracks deposits from PersonaA and PersonaB each period, accumulates, and sweeps to zero at the last period of each financial year.
A2: Period | B2: Year | C2: PeriodInYear | D2: IsSweepPeriod | E2: DepositA | F2: DepositB | G2: TotalDeposit | H2: OffsetStart | I2: OffsetBeforeSweep | J2: SweepAmount | K2: OffsetEnd | L2: TaxSavedA | M2: TaxSavedB | N2: InterestSaved | O2: CumulativeInterestSaved
A3: =IF(ROW()-2 <= TotalPeriodsOffset, ROW()-2, "") -> 1 | B3: =IF($A3="", "", YEAR(StartYear) + INT(($A3-1)/PPY)) -> 2027 | C3: =IF(A3="", "",MOD(A3-1, PPY)+1) -> 1 | D3: =IF(A3="", "",C3=PPY) -> FALSE | E3: =IF($A3="", "", IFERROR(SUMIF(PersonaA!$B:$B, $B3, PersonaA!$O:$O) / PPY, 0)) -> 6604.7778 | F3: =IF($A3="", "", IFERROR(SUMIF(PersonaB!$B:$B, $B3, PersonaB!$O:$O) / PPY, 0)) -> 8647.7987 | G3: =IF(A3="", "", E3+F3+L3+M3) -> 25157.667 | H3: =OffsetStart -> 0 | I3: =IF(A3="", "",H3+G3) -> 25157.667 | J3: =IF(A3="", "",IF(D3,I3,0)) -> 0 | K3: =IF(A3="", "",IF(D3,0,I3-J3)) -> 25157.667 | L3: =IF($A3="", "", IFERROR(SUMIF(PersonaA!$B:$B, $B3, PersonaA!$P:$P) / PPY, 0)) -> 3252.6389 | M3: =IF($A3="", "", IFERROR(SUMIF(PersonaB!$B:$B, $B3, PersonaB!$P:$P) / PPY, 0)) -> 6652.4513 | N3: =IF($A3="", "", I3*(LoanRate/PPY)) -> 167.71778 | O3: =IF($A3="", "", N3) -> 167.71778 | U3: PeriodsPerYear | V3: =_xlfn.XLOOKUP(FreqA,FreqLookup[Frequency],FreqLookup[PeriodsPerYear]) -> 12
A4: =IF(ROW()-2 <= TotalPeriodsOffset, ROW()-2, "") -> 2 | B4: =IF($A4="", "", YEAR(StartYear) + INT(($A4-1)/PPY)) -> 2027 | C4: =IF(A4="", "",MOD(A4-1, PPY)+1) -> 2 | D4: =IF(A4="", "",C4=PPY) -> FALSE | E4: =IF($A4="", "", IFERROR(SUMIF(PersonaA!$B:$B, $B4, PersonaA!$O:$O) / PPY, 0)) -> 6604.7778 | F4: =IF($A4="", "", IFERROR(SUMIF(PersonaB!$B:$B, $B4, PersonaB!$O:$O) / PPY, 0)) -> 8647.7987 | G4: =IF(A4="", "", E4+F4+L4+M4) -> 25157.667 | H4: =IF($A4="", "", K3) -> 25157.667 | I4: =IF(A4="", "",H4+G4) -> 50315.333 | J4: =IF(A4="", "",IF(D4,I4,0)) -> 0 | K4: =IF(A4="", "",IF(D4,0,I4-J4)) -> 50315.333 | L4: =IF($A4="", "", IFERROR(SUMIF(PersonaA!$B:$B, $B4, PersonaA!$P:$P) / PPY, 0)) -> 3252.6389 | M4: =IF($A4="", "", IFERROR(SUMIF(PersonaB!$B:$B, $B4, PersonaB!$P:$P) / PPY, 0)) -> 6652.4513 | N4: =IF($A4="", "", I4*(LoanRate/PPY)) -> 335.43556 | O4: =IF($A4="", "", O3+N4) -> 503.15333 | U4: TotalPeriods | V4: =MAX(ProjYearsA,ProjYearsB)*PPY -> 180
A5: =IF(ROW()-2 <= TotalPeriodsOffset, ROW()-2, "") -> 3 | B5: =IF($A5="", "", YEAR(StartYear) + INT(($A5-1)/PPY)) -> 2027 | C5: =IF(A5="", "",MOD(A5-1, PPY)+1) -> 3 | D5: =IF(A5="", "",C5=PPY) -> FALSE | E5: =IF($A5="", "", IFERROR(SUMIF(PersonaA!$B:$B, $B5, PersonaA!$O:$O) / PPY, 0)) -> 6604.7778 | F5: =IF($A5="", "", IFERROR(SUMIF(PersonaB!$B:$B, $B5, PersonaB!$O:$O) / PPY, 0)) -> 8647.7987 | G5: =IF(A5="", "", E5+F5+L5+M5) -> 25157.667 | H5: =IF($A5="", "", K4) -> 50315.333 | I5: =IF(A5="", "",H5+G5) -> 75473 | J5: =IF(A5="", "",IF(D5,I5,0)) -> 0 | K5: =IF(A5="", "",IF(D5,0,I5-J5)) -> 75473 | L5: =IF($A5="", "", IFERROR(SUMIF(PersonaA!$B:$B, $B5, PersonaA!$P:$P) / PPY, 0)) -> 3252.6389 | M5: =IF($A5="", "", IFERROR(SUMIF(PersonaB!$B:$B, $B5, PersonaB!$P:$P) / PPY, 0)) -> 6652.4513 | N5: =IF($A5="", "", I5*(LoanRate/PPY)) -> 503.15333 | O5: =IF($A5="", "", O4+N5) -> 1006.3067
A6: =IF(ROW()-2 <= TotalPeriodsOffset, ROW()-2, "") -> 4 | B6: =IF($A6="", "", YEAR(StartYear) + INT(($A6-1)/PPY)) -> 2027 | C6: =IF(A6="", "",MOD(A6-1, PPY)+1) -> 4 | D6: =IF(A6="", "",C6=PPY) -> FALSE | E6: =IF($A6="", "", IFERROR(SUMIF(PersonaA!$B:$B, $B6, PersonaA!$O:$O) / PPY, 0)) -> 6604.7778 | F6: =IF($A6="", "", IFERROR(SUMIF(PersonaB!$B:$B, $B6, PersonaB!$O:$O) / PPY, 0)) -> 8647.7987 | G6: =IF(A6="", "", E6+F6+L6+M6) -> 25157.667 | H6: =IF($A6="", "", K5) -> 75473 | I6: =IF(A6="", "",H6+G6) -> 100630.67 | J6: =IF(A6="", "",IF(D6,I6,0)) -> 0 | K6: =IF(A6="", "",IF(D6,0,I6-J6)) -> 100630.67 | L6: =IF($A6="", "", IFERROR(SUMIF(PersonaA!$B:$B, $B6, PersonaA!$P:$P) / PPY, 0)) -> 3252.6389 | M6: =IF($A6="", "", IFERROR(SUMIF(PersonaB!$B:$B, $B6, PersonaB!$P:$P) / PPY, 0)) -> 6652.4513 | N6: =IF($A6="", "", I6*(LoanRate/PPY)) -> 670.87111 | O6: =IF($A6="", "", O5+N6) -> 1677.1778
A7: =IF(ROW()-2 <= TotalPeriodsOffset, ROW()-2, "") -> 5 | B7: =IF($A7="", "", YEAR(StartYear) + INT(($A7-1)/PPY)) -> 2027 | C7: =IF(A7="", "",MOD(A7-1, PPY)+1) -> 5 | D7: =IF(A7="", "",C7=PPY) -> FALSE | E7: =IF($A7="", "", IFERROR(SUMIF(PersonaA!$B:$B, $B7, PersonaA!$O:$O) / PPY, 0)) -> 6604.7778 | F7: =IF($A7="", "", IFERROR(SUMIF(PersonaB!$B:$B, $B7, PersonaB!$O:$O) / PPY, 0)) -> 8647.7987 | G7: =IF(A7="", "", E7+F7+L7+M7) -> 25157.667 | H7: =IF($A7="", "", K6) -> 100630.67 | I7: =IF(A7="", "",H7+G7) -> 125788.33 | J7: =IF(A7="", "",IF(D7,I7,0)) -> 0 | K7: =IF(A7="", "",IF(D7,0,I7-J7)) -> 125788.33 | L7: =IF($A7="", "", IFERROR(SUMIF(PersonaA!$B:$B, $B7, PersonaA!$P:$P) / PPY, 0)) -> 3252.6389 | M7: =IF($A7="", "", IFERROR(SUMIF(PersonaB!$B:$B, $B7, PersonaB!$P:$P) / PPY, 0)) -> 6652.4513 | N7: =IF($A7="", "", I7*(LoanRate/PPY)) -> 838.58889 | O7: =IF($A7="", "", O6+N7) -> 2515.7667
A8: =IF(ROW()-2 <= TotalPeriodsOffset, ROW()-2, "") -> 6 | B8: =IF($A8="", "", YEAR(StartYear) + INT(($A8-1)/PPY)) -> 2027 | C8: =IF(A8="", "",MOD(A8-1, PPY)+1) -> 6 | D8: =IF(A8="", "",C8=PPY) -> FALSE | E8: =IF($A8="", "", IFERROR(SUMIF(PersonaA!$B:$B, $B8, PersonaA!$O:$O) / PPY, 0)) -> 6604.7778 | F8: =IF($A8="", "", IFERROR(SUMIF(PersonaB!$B:$B, $B8, PersonaB!$O:$O) / PPY, 0)) -> 8647.7987 | G8: =IF(A8="", "", E8+F8+L8+M8) -> 25157.667 | H8: =IF($A8="", "", K7) -> 125788.33 | I8: =IF(A8="", "",H8+G8) -> 150946 | J8: =IF(A8="", "",IF(D8,I8,0)) -> 0 | K8: =IF(A8="", "",IF(D8,0,I8-J8)) -> 150946 | L8: =IF($A8="", "", IFERROR(SUMIF(PersonaA!$B:$B, $B8, PersonaA!$P:$P) / PPY, 0)) -> 3252.6389 | M8: =IF($A8="", "", IFERROR(SUMIF(PersonaB!$B:$B, $B8, PersonaB!$P:$P) / PPY, 0)) -> 6652.4513 | N8: =IF($A8="", "", I8*(LoanRate/PPY)) -> 1006.3067 | O8: =IF($A8="", "", O7+N8) -> 3522.0733
A9: =IF(ROW()-2 <= TotalPeriodsOffset, ROW()-2, "") -> 7 | B9: =IF($A9="", "", YEAR(StartYear) + INT(($A9-1)/PPY)) -> 2027 | C9: =IF(A9="", "",MOD(A9-1, PPY)+1) -> 7 | D9: =IF(A9="", "",C9=PPY) -> FALSE | E9: =IF($A9="", "", IFERROR(SUMIF(PersonaA!$B:$B, $B9, PersonaA!$O:$O) / PPY, 0)) -> 6604.7778 | F9: =IF($A9="", "", IFERROR(SUMIF(PersonaB!$B:$B, $B9, PersonaB!$O:$O) / PPY, 0)) -> 8647.7987 | G9: =IF(A9="", "", E9+F9+L9+M9) -> 25157.667 | H9: =IF($A9="", "", K8) -> 150946 | I9: =IF(A9="", "",H9+G9) -> 176103.67 | J9: =IF(A9="", "",IF(D9,I9,0)) -> 0 | K9: =IF(A9="", "",IF(D9,0,I9-J9)) -> 176103.67 | L9: =IF($A9="", "", IFERROR(SUMIF(PersonaA!$B:$B, $B9, PersonaA!$P:$P) / PPY, 0)) -> 3252.6389 | M9: =IF($A9="", "", IFERROR(SUMIF(PersonaB!$B:$B, $B9, PersonaB!$P:$P) / PPY, 0)) -> 6652.4513 | N9: =IF($A9="", "", I9*(LoanRate/PPY)) -> 1174.0244 | O9: =IF($A9="", "", O8+N9) -> 4696.0978
A10: =IF(ROW()-2 <= TotalPeriodsOffset, ROW()-2, "") -> 8 | B10: =IF($A10="", "", YEAR(StartYear) + INT(($A10-1)/PPY)) -> 2027 | C10: =IF(A10="", "",MOD(A10-1, PPY)+1) -> 8 | D10: =IF(A10="", "",C10=PPY) -> FALSE | E10: =IF($A10="", "", IFERROR(SUMIF(PersonaA!$B:$B, $B10, PersonaA!$O:$O) / PPY, 0)) -> 6604.7778 | F10: =IF($A10="", "", IFERROR(SUMIF(PersonaB!$B:$B, $B10, PersonaB!$O:$O) / PPY, 0)) -> 8647.7987 | G10: =IF(A10="", "", E10+F10+L10+M10) -> 25157.667 | H10: =IF($A10="", "", K9) -> 176103.67 | I10: =IF(A10="", "",H10+G10) -> 201261.33 | J10: =IF(A10="", "",IF(D10,I10,0)) -> 0 | K10: =IF(A10="", "",IF(D10,0,I10-J10)) -> 201261.33 | L10: =IF($A10="", "", IFERROR(SUMIF(PersonaA!$B:$B, $B10, PersonaA!$P:$P) / PPY, 0)) -> 3252.6389 | M10: =IF($A10="", "", IFERROR(SUMIF(PersonaB!$B:$B, $B10, PersonaB!$P:$P) / PPY, 0)) -> 6652.4513 | N10: =IF($A10="", "", I10*(LoanRate/PPY)) -> 1341.7422 | O10: =IF($A10="", "", O9+N10) -> 6037.84
A11: =IF(ROW()-2 <= TotalPeriodsOffset, ROW()-2, "") -> 9 | B11: =IF($A11="", "", YEAR(StartYear) + INT(($A11-1)/PPY)) -> 2027 | C11: =IF(A11="", "",MOD(A11-1, PPY)+1) -> 9 | D11: =IF(A11="", "",C11=PPY) -> FALSE | E11: =IF($A11="", "", IFERROR(SUMIF(PersonaA!$B:$B, $B11, PersonaA!$O:$O) / PPY, 0)) -> 6604.7778 | F11: =IF($A11="", "", IFERROR(SUMIF(PersonaB!$B:$B, $B11, PersonaB!$O:$O) / PPY, 0)) -> 8647.7987 | G11: =IF(A11="", "", E11+F11+L11+M11) -> 25157.667 | H11: =IF($A11="", "", K10) -> 201261.33 | I11: =IF(A11="", "",H11+G11) -> 226419 | J11: =IF(A11="", "",IF(D11,I11,0)) -> 0 | K11: =IF(A11="", "",IF(D11,0,I11-J11)) -> 226419 | L11: =IF($A11="", "", IFERROR(SUMIF(PersonaA!$B:$B, $B11, PersonaA!$P:$P) / PPY, 0)) -> 3252.6389 | M11: =IF($A11="", "", IFERROR(SUMIF(PersonaB!$B:$B, $B11, PersonaB!$P:$P) / PPY, 0)) -> 6652.4513 | N11: =IF($A11="", "", I11*(LoanRate/PPY)) -> 1509.46 | O11: =IF($A11="", "", O10+N11) -> 7547.3
A12: =IF(ROW()-2 <= TotalPeriodsOffset, ROW()-2, "") -> 10 | B12: =IF($A12="", "", YEAR(StartYear) + INT(($A12-1)/PPY)) -> 2027 | C12: =IF(A12="", "",MOD(A12-1, PPY)+1) -> 10 | D12: =IF(A12="", "",C12=PPY) -> FALSE | E12: =IF($A12="", "", IFERROR(SUMIF(PersonaA!$B:$B, $B12, PersonaA!$O:$O) / PPY, 0)) -> 6604.7778 | F12: =IF($A12="", "", IFERROR(SUMIF(PersonaB!$B:$B, $B12, PersonaB!$O:$O) / PPY, 0)) -> 8647.7987 | G12: =IF(A12="", "", E12+F12+L12+M12) -> 25157.667 | H12: =IF($A12="", "", K11) -> 226419 | I12: =IF(A12="", "",H12+G12) -> 251576.67 | J12: =IF(A12="", "",IF(D12,I12,0)) -> 0 | K12: =IF(A12="", "",IF(D12,0,I12-J12)) -> 251576.67 | L12: =IF($A12="", "", IFERROR(SUMIF(PersonaA!$B:$B, $B12, PersonaA!$P:$P) / PPY, 0)) -> 3252.6389 | M12: =IF($A12="", "", IFERROR(SUMIF(PersonaB!$B:$B, $B12, PersonaB!$P:$P) / PPY, 0)) -> 6652.4513 | N12: =IF($A12="", "", I12*(LoanRate/PPY)) -> 1677.1778 | O12: =IF($A12="", "", O11+N12) -> 9224.4778
A13: =IF(ROW()-2 <= TotalPeriodsOffset, ROW()-2, "") -> 11 | B13: =IF($A13="", "", YEAR(StartYear) + INT(($A13-1)/PPY)) -> 2027 | C13: =IF(A13="", "",MOD(A13-1, PPY)+1) -> 11 | D13: =IF(A13="", "",C13=PPY) -> FALSE | E13: =IF($A13="", "", IFERROR(SUMIF(PersonaA!$B:$B, $B13, PersonaA!$O:$O) / PPY, 0)) -> 6604.7778 | F13: =IF($A13="", "", IFERROR(SUMIF(PersonaB!$B:$B, $B13, PersonaB!$O:$O) / PPY, 0)) -> 8647.7987 | G13: =IF(A13="", "", E13+F13+L13+M13) -> 25157.667 | H13: =IF($A13="", "", K12) -> 251576.67 | I13: =IF(A13="", "",H13+G13) -> 276734.33 | J13: =IF(A13="", "",IF(D13,I13,0)) -> 0 | K13: =IF(A13="", "",IF(D13,0,I13-J13)) -> 276734.33 | L13: =IF($A13="", "", IFERROR(SUMIF(PersonaA!$B:$B, $B13, PersonaA!$P:$P) / PPY, 0)) -> 3252.6389 | M13: =IF($A13="", "", IFERROR(SUMIF(PersonaB!$B:$B, $B13, PersonaB!$P:$P) / PPY, 0)) -> 6652.4513 | N13: =IF($A13="", "", I13*(LoanRate/PPY)) -> 1844.8956 | O13: =IF($A13="", "", O12+N13) -> 11069.373
A14: =IF(ROW()-2 <= TotalPeriodsOffset, ROW()-2, "") -> 12 | B14: =IF($A14="", "", YEAR(StartYear) + INT(($A14-1)/PPY)) -> 2027 | C14: =IF(A14="", "",MOD(A14-1, PPY)+1) -> 12 | D14: =IF(A14="", "",C14=PPY) -> TRUE | E14: =IF($A14="", "", IFERROR(SUMIF(PersonaA!$B:$B, $B14, PersonaA!$O:$O) / PPY, 0)) -> 6604.7778 | F14: =IF($A14="", "", IFERROR(SUMIF(PersonaB!$B:$B, $B14, PersonaB!$O:$O) / PPY, 0)) -> 8647.7987 | G14: =IF(A14="", "", E14+F14+L14+M14) -> 25157.667 | H14: =IF($A14="", "", K13) -> 276734.33 | I14: =IF(A14="", "",H14+G14) -> 301892 | J14: =IF(A14="", "",IF(D14,I14,0)) -> 301892 | K14: =IF(A14="", "",IF(D14,0,I14-J14)) -> 0 | L14: =IF($A14="", "", IFERROR(SUMIF(PersonaA!$B:$B, $B14, PersonaA!$P:$P) / PPY, 0)) -> 3252.6389 | M14: =IF($A14="", "", IFERROR(SUMIF(PersonaB!$B:$B, $B14, PersonaB!$P:$P) / PPY, 0)) -> 6652.4513 | N14: =IF($A14="", "", I14*(LoanRate/PPY)) -> 2012.6133 | O14: =IF($A14="", "", O13+N14) -> 13081.987
A15: =IF(ROW()-2 <= TotalPeriodsOffset, ROW()-2, "") -> 13 | B15: =IF($A15="", "", YEAR(StartYear) + INT(($A15-1)/PPY)) -> 2028 | C15: =IF(A15="", "",MOD(A15-1, PPY)+1) -> 1 | D15: =IF(A15="", "",C15=PPY) -> FALSE | E15: =IF($A15="", "", IFERROR(SUMIF(PersonaA!$B:$B, $B15, PersonaA!$O:$O) / PPY, 0)) -> 1222.0833 | F15: =IF($A15="", "", IFERROR(SUMIF(PersonaB!$B:$B, $B15, PersonaB!$O:$O) / PPY, 0)) -> 350.83333 | G15: =IF(A15="", "", E15+F15+L15+M15) -> 2214.4208 | H15: =IF($A15="", "", K14) -> 0 | I15: =IF(A15="", "",H15+G15) -> 2214.4208 | J15: =IF(A15="", "",IF(D15,I15,0)) -> 0 | K15: =IF(A15="", "",IF(D15,0,I15-J15)) -> 2214.4208 | L15: =IF($A15="", "", IFERROR(SUMIF(PersonaA!$B:$B, $B15, PersonaA!$P:$P) / PPY, 0)) -> 476.6125 | M15: =IF($A15="", "", IFERROR(SUMIF(PersonaB!$B:$B, $B15, PersonaB!$P:$P) / PPY, 0)) -> 164.89167 | N15: =IF($A15="", "", I15*(LoanRate/PPY)) -> 14.762806 | O15: =IF($A15="", "", O14+N15) -> 13096.749
A16: =IF(ROW()-2 <= TotalPeriodsOffset, ROW()-2, "") -> 14 | B16: =IF($A16="", "", YEAR(StartYear) + INT(($A16-1)/PPY)) -> 2028 | C16: =IF(A16="", "",MOD(A16-1, PPY)+1) -> 2 | D16: =IF(A16="", "",C16=PPY) -> FALSE | E16: =IF($A16="", "", IFERROR(SUMIF(PersonaA!$B:$B, $B16, PersonaA!$O:$O) / PPY, 0)) -> 1222.0833 | F16: =IF($A16="", "", IFERROR(SUMIF(PersonaB!$B:$B, $B16, PersonaB!$O:$O) / PPY, 0)) -> 350.83333 | G16: =IF(A16="", "", E16+F16+L16+M16) -> 2214.4208 | H16: =IF($A16="", "", K15) -> 2214.4208 | I16: =IF(A16="", "",H16+G16) -> 4428.8417 | J16: =IF(A16="", "",IF(D16,I16,0)) -> 0 | K16: =IF(A16="", "",IF(D16,0,I16-J16)) -> 4428.8417 | L16: =IF($A16="", "", IFERROR(SUMIF(PersonaA!$B:$B, $B16, PersonaA!$P:$P) / PPY, 0)) -> 476.6125 | M16: =IF($A16="", "", IFERROR(SUMIF(PersonaB!$B:$B, $B16, PersonaB!$P:$P) / PPY, 0)) -> 164.89167 | N16: =IF($A16="", "", I16*(LoanRate/PPY)) -> 29.525611 | O16: =IF($A16="", "", O15+N16) -> 13126.275
... A182: =IF(ROW()-2 <= TotalPeriodsOffset, ROW()-2, "") -> 180 | B182: =IF($A182="", "", YEAR(StartYear) + INT(($A182-1)/PPY)) -> 2041 | C182: =IF(A182="", "",MOD(A182-1, PPY)+1) -> 12 | D182: =IF(A182="", "",C182=PPY) -> TRUE | E182: =IF($A182="", "", IFERROR(SUMIF(PersonaA!$B:$B, $B182, PersonaA!$O:$O) / PPY, 0)) -> 0 | F182: =IF($A182="", "", IFERROR(SUMIF(PersonaB!$B:$B, $B182, PersonaB!$O:$O) / PPY, 0)) -> 916.82688 | G182: =IF(A182="", "", E182+F182+L182+M182) -> 1347.7355 | H182: =IF($A182="", "", K181) -> 14825.091 | I182: =IF(A182="", "",H182+G182) -> 16172.826 | J182: =IF(A182="", "",IF(D182,I182,0)) -> 16172.826 | K182: =IF(A182="", "",IF(D182,0,I182-J182)) -> 0 | L182: =IF($A182="", "", IFERROR(SUMIF(PersonaA!$B:$B, $B182, PersonaA!$P:$P) / PPY, 0)) -> 0 | M182: =IF($A182="", "", IFERROR(SUMIF(PersonaB!$B:$B, $B182, PersonaB!$P:$P) / PPY, 0)) -> 430.90863 | N182: =IF($A182="", "", I182*(LoanRate/PPY)) -> 107.81884 | O182: =IF($A182="", "", O181+N182) -> 32817.642

Sheet YearlyParamsA
A1: Year | B1: AnnualIncome | C1: EmployerSG | D1: ConcessCap | E1: CarryFwdStart | F1: PersonalContributionUsed | G1: RemainingCarryFwd | H1: ExpiredCarryFwd | I1: AllowablePersonalAnnual | J1: SuperBalanceStart | K1: SuperBalanceEnd | L1: Div293Income | M1: Div293Tax | N1: Year 0 | O1: Year 1 | P1: Year 2 | Q1: Year 3 | R1: Year 4 | S1: Year 5 | T1: Used0 | U1: Used1 | V1: Used2 | W1: Used3 | X1: Used4 | Y1: Used5 | Z1: TransferOut | AA1: NetPersonalContribution | AB1: TaxPayableNoStrategy | AC1: =ISNUMBER(N1) -> FALSE
A2: =YEAR(StartYear) -> 2027 | B2: =IncA -> 145000 | C2: =IFERROR(IF($A2="", "", B2*SGRate), 0) -> 17400 | D2: =ConcessCap -> 32500 | E2: =CarryFwdStartA -> 70000 | F2: =IFERROR(IF($A2="","",_xlfn.XLOOKUP($A2,PersonaA!B:B,PersonaA!Q:Q,,,-1)),0) -> 85100 | G2: =IFERROR(IF($A2="", "", MAX(0, D2+E2-C2-AA2)), 0) -> 0 | H2: 0 | I2: =IFERROR(IF($A2="", "", MAX(0, D2+E2-C2)), 0) -> 85100 | J2: =SuperBalStartA -> 180000 | K2: =IFERROR(IF($A2="", "", J2*(1+SuperReturn*(1-SuperTaxRate)) + (C2+AA2)*(1-SuperTaxRate) - M2), 0) -> 277835 | L2: =IFERROR(IF($A2="", "", B2 + AA2 + NetInvLoss), 0) -> 230100 | M2: =IFERROR(IF($A2="", "", IF(L2 > Div293Thresh, 0.15 * MIN(AA2, L2 - Div293Thresh), 0)), 0) -> 0 | N2: =IFERROR(IF($A2="", "", G2), 0) -> 0 | O2: 0 | P2: 0 | Q2: 0 | R2: 0 | S2: 0 | T2: =IF($A2="","",MIN(MAX(0,F2),N2)) -> 0 | U2: =IF($A2="","",MIN(MAX(0,F2-T2),O2)) -> 0 | V2: =IF($A2="","",MIN(MAX(0,F2-T2-U2),P2)) -> 0 | W2: =IF($A2="","",MIN(MAX(0,F2-T2-U2-V2),Q2)) -> 0 | X2: =IF($A2="","",MIN(MAX(0,F2-T2-U2-V2-W2),R2)) -> 0 | Y2: =IF($A2="","",MIN(MAX(0,F2-T2-U2-V2-W2-X2),S2)) -> 0 | Z2: =IF($A2="","",IF(AND(SpousalTransfer="Yes", TransferDir="Yes", SuperBalStartA>=500000), F2, 0)) -> 0 | AA2: =IF($A2="","",F2-Z2) -> 85100 | AB2: {=IF($A2="","",TaxPayable(B2))} -> 37620
A3: =IF(ROW()-1 <= ProjYearsA, A2+1, "") -> 2028 | B3: =IF($A3="","",B2*(1+Inflation)) -> 148625 | C3: =IFERROR(IF($A3="", "", B3*SGRate), 0) -> 17835 | D3: =IF($A3="","",D2+IF(MOD(A3-YEAR(StartYear),CapIndexYears)=0,CapIncrement,0)) -> 32500 | E3: =IFERROR(IF($A3="", "", IF(J2>500000, 0, MAX(0, G2-H3))), 0) -> 0 | F3: =IFERROR(IF($A3="","",_xlfn.XLOOKUP($A3,PersonaA!B:B,PersonaA!Q:Q,,,-1)),0) -> 14665 | G3: =IFERROR(IF($A3="", "", MAX(0, D3+E3-C3-AA3)), 0) -> 0 | H3: =IFERROR(IF($A3="","",IF(YEAR(StartYear)+0<A3-5,N2-T2,0)+IF(YEAR(StartYear)+1<A3-5,O2-U2,0)+IF(YEAR(StartYear)+2<A3-5,P2-V2,0)+IF(YEAR(StartYear)+3<A3-5,Q2-W2,0)+IF(YEAR(StartYear)+4<A3-5,R2-X2,0)+IF(YEAR(StartYear)+5<A3-5,S2-Y2,0)),0) -> 0 | I3: =IFERROR(IF($A3="", "", MAX(0, D3+E3-C3)), 0) -> 14665 | J3: =IFERROR(IF($A3="", "", K2), 0) -> 277835 | K3: =IFERROR(IF($A3="", "", J3*(1+SuperReturn*(1-SuperTaxRate)) + (C3+AA3)*(1-SuperTaxRate) - M3), 0) -> 321991.18 | L3: =IFERROR(IF($A3="", "", B3 + AA3 + NetInvLoss), 0) -> 163290 | M3: =IFERROR(IF($A3="", "", IF(L3 > Div293Thresh, 0.15 * MIN(AA3, L3 - Div293Thresh), 0)), 0) -> 0 | N3: =IFERROR(IF($A3="", "", G2), 0) -> 0 | O3: =IFERROR(IF($A3="", "", N2), 0) -> 0 | P3: =IFERROR(IF($A3="", "", O2), 0) -> 0 | Q3: =IFERROR(IF($A3="", "", P2), 0) -> 0 | R3: =IFERROR(IF($A3="", "", Q2), 0) -> 0 | S3: =IFERROR(IF($A3="", "", R2), 0) -> 0 | T3: =IF($A3="","",MIN(MAX(0,F3),N3)) -> 0 | U3: =IF($A3="","",MIN(MAX(0,F3-T3),O3)) -> 0 | V3: =IF($A3="","",MIN(MAX(0,F3-T3-U3),P3)) -> 0 | W3: =IF($A3="","",MIN(MAX(0,F3-T3-U3-V3),Q3)) -> 0 | X3: =IF($A3="","",MIN(MAX(0,F3-T3-U3-V3-W3),R3)) -> 0 | Y3: =IF($A3="","",MIN(MAX(0,F3-T3-U3-V3-W3-X3),S3)) -> 0 | Z3: =IF($A3="","",IF(AND(SpousalTransfer="Yes", TransferDir="Yes", J2>=500000), F3, 0)) -> 0 | AA3: =IF($A3="","",F3-Z3) -> 14665 | AB3: {=IF($A3="","",TaxPayable(B3))} -> 39033.75
A4: =IF(ROW()-1 <= ProjYearsA, A3+1, "") -> 2029 | B4: =IF($A4="","",B3*(1+Inflation)) -> 152340.62 | C4: =IFERROR(IF($A4="", "", B4*SGRate), 0) -> 18280.875 | D4: =IF($A4="","",D3+IF(MOD(A4-YEAR(StartYear),CapIndexYears)=0,CapIncrement,0)) -> 35000 | E4: =IFERROR(IF($A4="", "", IF(J3>500000, 0, MAX(0, G3-H4))), 0) -> 0 | F4: =IFERROR(IF($A4="","",_xlfn.XLOOKUP($A4,PersonaA!B:B,PersonaA!Q:Q,,,-1)),0) -> 16719.125 | G4: =IFERROR(IF($A4="", "", MAX(0, D4+E4-C4-AA4)), 0) -> 0 | H4: =IFERROR(IF($A4="","",IF(YEAR(StartYear)+0<A4-5,N3-T3,0)+IF(YEAR(StartYear)+1<A4-5,O3-U3,0)+IF(YEAR(StartYear)+2<A4-5,P3-V3,0)+IF(YEAR(StartYear)+3<A4-5,Q3-W3,0)+IF(YEAR(StartYear)+4<A4-5,R3-X3,0)+IF(YEAR(StartYear)+5<A4-5,S3-Y3,0)),0) -> 0 | I4: =IFERROR(IF($A4="", "", MAX(0, D4+E4-C4)), 0) -> 16719.125 | J4: =IFERROR(IF($A4="", "", K3), 0) -> 321991.18 | K4: =IFERROR(IF($A4="", "", J4*(1+SuperReturn*(1-SuperTaxRate)) + (C4+AA4)*(1-SuperTaxRate) - M4), 0) -> 370899.66 | L4: =IFERROR(IF($A4="", "", B4 + AA4 + NetInvLoss), 0) -> 169059.75 | M4: =IFERROR(IF($A4="", "", IF(L4 > Div293Thresh, 0.15 * MIN(AA4, L4 - Div293Thresh), 0)), 0) -> 0 | N4: =IFERROR(IF($A4="", "", G3), 0) -> 0 | O4: =IFERROR(IF($A4="", "", N3), 0) -> 0 | P4: =IFERROR(IF($A4="", "", O3), 0) -> 0 | Q4: =IFERROR(IF($A4="", "", P3), 0) -> 0 | R4: =IFERROR(IF($A4="", "", Q3), 0) -> 0 | S4: =IFERROR(IF($A4="", "", R3), 0) -> 0 | T4: =IF($A4="","",MIN(MAX(0,F4),N4)) -> 0 | U4: =IF($A4="","",MIN(MAX(0,F4-T4),O4)) -> 0 | V4: =IF($A4="","",MIN(MAX(0,F4-T4-U4),P4)) -> 0 | W4: =IF($A4="","",MIN(MAX(0,F4-T4-U4-V4),Q4)) -> 0 | X4: =IF($A4="","",MIN(MAX(0,F4-T4-U4-V4-W4),R4)) -> 0 | Y4: =IF($A4="","",MIN(MAX(0,F4-T4-U4-V4-W4-X4),S4)) -> 0 | Z4: =IF($A4="","",IF(AND(SpousalTransfer="Yes", TransferDir="Yes", J3>=500000), F4, 0)) -> 0 | AA4: =IF($A4="","",F4-Z4) -> 16719.125 | AB4: {=IF($A4="","",TaxPayable(B4))} -> 40482.844
A5: =IF(ROW()-1 <= ProjYearsA, A4+1, "") -> 2030 | B5: =IF($A5="","",B4*(1+Inflation)) -> 156149.14 | C5: =IFERROR(IF($A5="", "", B5*SGRate), 0) -> 18737.897 | D5: =IF($A5="","",D4+IF(MOD(A5-YEAR(StartYear),CapIndexYears)=0,CapIncrement,0)) -> 35000 | E5: =IFERROR(IF($A5="", "", IF(J4>500000, 0, MAX(0, G4-H5))), 0) -> 0 | F5: =IFERROR(IF($A5="","",_xlfn.XLOOKUP($A5,PersonaA!B:B,PersonaA!Q:Q,,,-1)),0) -> 16262.103 | G5: =IFERROR(IF($A5="", "", MAX(0, D5+E5-C5-AA5)), 0) -> 0 | H5: =IFERROR(IF($A5="","",IF(YEAR(StartYear)+0<A5-5,N4-T4,0)+IF(YEAR(StartYear)+1<A5-5,O4-U4,0)+IF(YEAR(StartYear)+2<A5-5,P4-V4,0)+IF(YEAR(StartYear)+3<A5-5,Q4-W4,0)+IF(YEAR(StartYear)+4<A5-5,R4-X4,0)+IF(YEAR(StartYear)+5<A5-5,S4-Y4,0)),0) -> 0 | I5: =IFERROR(IF($A5="", "", MAX(0, D5+E5-C5)), 0) -> 16262.103 | J5: =IFERROR(IF($A5="", "", K4), 0) -> 370899.66 | K5: =IFERROR(IF($A5="", "", J5*(1+SuperReturn*(1-SuperTaxRate)) + (C5+AA5)*(1-SuperTaxRate) - M5), 0) -> 422718.19 | L5: =IFERROR(IF($A5="", "", B5 + AA5 + NetInvLoss), 0) -> 172411.24 | M5: =IFERROR(IF($A5="", "", IF(L5 > Div293Thresh, 0.15 * MIN(AA5, L5 - Div293Thresh), 0)), 0) -> 0 | N5: =IFERROR(IF($A5="", "", G4), 0) -> 0 | O5: =IFERROR(IF($A5="", "", N4), 0) -> 0 | P5: =IFERROR(IF($A5="", "", O4), 0) -> 0 | Q5: =IFERROR(IF($A5="", "", P4), 0) -> 0 | R5: =IFERROR(IF($A5="", "", Q4), 0) -> 0 | S5: =IFERROR(IF($A5="", "", R4), 0) -> 0 | T5: =IF($A5="","",MIN(MAX(0,F5),N5)) -> 0 | U5: =IF($A5="","",MIN(MAX(0,F5-T5),O5)) -> 0 | V5: =IF($A5="","",MIN(MAX(0,F5-T5-U5),P5)) -> 0 | W5: =IF($A5="","",MIN(MAX(0,F5-T5-U5-V5),Q5)) -> 0 | X5: =IF($A5="","",MIN(MAX(0,F5-T5-U5-V5-W5),R5)) -> 0 | Y5: =IF($A5="","",MIN(MAX(0,F5-T5-U5-V5-W5-X5),S5)) -> 0 | Z5: =IF($A5="","",IF(AND(SpousalTransfer="Yes", TransferDir="Yes", J4>=500000), F5, 0)) -> 0 | AA5: =IF($A5="","",F5-Z5) -> 16262.103 | AB5: {=IF($A5="","",TaxPayable(B5))} -> 41968.165
A6: =IF(ROW()-1 <= ProjYearsA, A5+1, "") -> 2031 | B6: =IF($A6="","",B5*(1+Inflation)) -> 160052.87 | C6: =IFERROR(IF($A6="", "", B6*SGRate), 0) -> 19206.344 | D6: =IF($A6="","",D5+IF(MOD(A6-YEAR(StartYear),CapIndexYears)=0,CapIncrement,0)) -> 37500 | E6: =IFERROR(IF($A6="", "", IF(J5>500000, 0, MAX(0, G5-H6))), 0) -> 0 | F6: =IFERROR(IF($A6="","",_xlfn.XLOOKUP($A6,PersonaA!B:B,PersonaA!Q:Q,,,-1)),0) -> 18293.656 | G6: =IFERROR(IF($A6="", "", MAX(0, D6+E6-C6-AA6)), 0) -> 0 | H6: =IFERROR(IF($A6="","",IF(YEAR(StartYear)+0<A6-5,N5-T5,0)+IF(YEAR(StartYear)+1<A6-5,O5-U5,0)+IF(YEAR(StartYear)+2<A6-5,P5-V5,0)+IF(YEAR(StartYear)+3<A6-5,Q5-W5,0)+IF(YEAR(StartYear)+4<A6-5,R5-X5,0)+IF(YEAR(StartYear)+5<A6-5,S5-Y5,0)),0) -> 0 | I6: =IFERROR(IF($A6="", "", MAX(0, D6+E6-C6)), 0) -> 18293.656 | J6: =IFERROR(IF($A6="", "", K5), 0) -> 422718.19 | K6: =IFERROR(IF($A6="", "", J6*(1+SuperReturn*(1-SuperTaxRate)) + (C6+AA6)*(1-SuperTaxRate) - M6), 0) -> 479744.92 | L6: =IFERROR(IF($A6="", "", B6 + AA6 + NetInvLoss), 0) -> 178346.52 | M6: =IFERROR(IF($A6="", "", IF(L6 > Div293Thresh, 0.15 * MIN(AA6, L6 - Div293Thresh), 0)), 0) -> 0 | N6: =IFERROR(IF($A6="", "", G5), 0) -> 0 | O6: =IFERROR(IF($A6="", "", N5), 0) -> 0 | P6: =IFERROR(IF($A6="", "", O5), 0) -> 0 | Q6: =IFERROR(IF($A6="", "", P5), 0) -> 0 | R6: =IFERROR(IF($A6="", "", Q5), 0) -> 0 | S6: =IFERROR(IF($A6="", "", R5), 0) -> 0 | T6: =IF($A6="","",MIN(MAX(0,F6),N6)) -> 0 | U6: =IF($A6="","",MIN(MAX(0,F6-T6),O6)) -> 0 | V6: =IF($A6="","",MIN(MAX(0,F6-T6-U6),P6)) -> 0 | W6: =IF($A6="","",MIN(MAX(0,F6-T6-U6-V6),Q6)) -> 0 | X6: =IF($A6="","",MIN(MAX(0,F6-T6-U6-V6-W6),R6)) -> 0 | Y6: =IF($A6="","",MIN(MAX(0,F6-T6-U6-V6-W6-X6),S6)) -> 0 | Z6: =IF($A6="","",IF(AND(SpousalTransfer="Yes", TransferDir="Yes", J5>=500000), F6, 0)) -> 0 | AA6: =IF($A6="","",F6-Z6) -> 18293.656 | AB6: {=IF($A6="","",TaxPayable(B6))} -> 43490.619
A7: =IF(ROW()-1 <= ProjYearsA, A6+1, "") -> 2032 | B7: =IF($A7="","",B6*(1+Inflation)) -> 164054.19 | C7: =IFERROR(IF($A7="", "", B7*SGRate), 0) -> 19686.503 | D7: =IF($A7="","",D6+IF(MOD(A7-YEAR(StartYear),CapIndexYears)=0,CapIncrement,0)) -> 37500 | E7: =IFERROR(IF($A7="", "", IF(J6>500000, 0, MAX(0, G6-H7))), 0) -> 0 | F7: =IFERROR(IF($A7="","",_xlfn.XLOOKUP($A7,PersonaA!B:B,PersonaA!Q:Q,,,-1)),0) -> 17813.497 | G7: =IFERROR(IF($A7="", "", MAX(0, D7+E7-C7-AA7)), 0) -> 0 | H7: =IFERROR(IF($A7="","",IF(YEAR(StartYear)+0<A7-5,N6-T6,0)+IF(YEAR(StartYear)+1<A7-5,O6-U6,0)+IF(YEAR(StartYear)+2<A7-5,P6-V6,0)+IF(YEAR(StartYear)+3<A7-5,Q6-W6,0)+IF(YEAR(StartYear)+4<A7-5,R6-X6,0)+IF(YEAR(StartYear)+5<A7-5,S6-Y6,0)),0) -> 0 | I7: =IFERROR(IF($A7="", "", MAX(0, D7+E7-C7)), 0) -> 17813.497 | J7: =IFERROR(IF($A7="", "", K6), 0) -> 479744.92 | K7: =IFERROR(IF($A7="", "", J7*(1+SuperReturn*(1-SuperTaxRate)) + (C7+AA7)*(1-SuperTaxRate) - M7), 0) -> 540164.74 | L7: =IFERROR(IF($A7="", "", B7 + AA7 + NetInvLoss), 0) -> 181867.69 | M7: =IFERROR(IF($A7="", "", IF(L7 > Div293Thresh, 0.15 * MIN(AA7, L7 - Div293Thresh), 0)), 0) -> 0 | N7: =IFERROR(IF($A7="", "", G6), 0) -> 0 | O7: =IFERROR(IF($A7="", "", N6), 0) -> 0 | P7: =IFERROR(IF($A7="", "", O6), 0) -> 0 | Q7: =IFERROR(IF($A7="", "", P6), 0) -> 0 | R7: =IFERROR(IF($A7="", "", Q6), 0) -> 0 | S7: =IFERROR(IF($A7="", "", R6), 0) -> 0 | T7: =IF($A7="","",MIN(MAX(0,F7),N7)) -> 0 | U7: =IF($A7="","",MIN(MAX(0,F7-T7),O7)) -> 0 | V7: =IF($A7="","",MIN(MAX(0,F7-T7-U7),P7)) -> 0 | W7: =IF($A7="","",MIN(MAX(0,F7-T7-U7-V7),Q7)) -> 0 | X7: =IF($A7="","",MIN(MAX(0,F7-T7-U7-V7-W7),R7)) -> 0 | Y7: =IF($A7="","",MIN(MAX(0,F7-T7-U7-V7-W7-X7),S7)) -> 0 | Z7: =IF($A7="","",IF(AND(SpousalTransfer="Yes", TransferDir="Yes", J6>=500000), F7, 0)) -> 0 | AA7: =IF($A7="","",F7-Z7) -> 17813.497 | AB7: {=IF($A7="","",TaxPayable(B7))} -> 45051.134
A8: =IF(ROW()-1 <= ProjYearsA, A7+1, "") -> 2033 | B8: =IF($A8="","",B7*(1+Inflation)) -> 168155.55 | C8: =IFERROR(IF($A8="", "", B8*SGRate), 0) -> 20178.665 | D8: =IF($A8="","",D7+IF(MOD(A8-YEAR(StartYear),CapIndexYears)=0,CapIncrement,0)) -> 40000 | E8: =IFERROR(IF($A8="", "", IF(J7>500000, 0, MAX(0, G7-H8))), 0) -> 0 | F8: =IFERROR(IF($A8="","",_xlfn.XLOOKUP($A8,PersonaA!B:B,PersonaA!Q:Q,,,-1)),0) -> 19821.335 | G8: =IFERROR(IF($A8="", "", MAX(0, D8+E8-C8-AA8)), 0) -> 0 | H8: =IFERROR(IF($A8="","",IF(YEAR(StartYear)+0<A8-5,N7-T7,0)+IF(YEAR(StartYear)+1<A8-5,O7-U7,0)+IF(YEAR(StartYear)+2<A8-5,P7-V7,0)+IF(YEAR(StartYear)+3<A8-5,Q7-W7,0)+IF(YEAR(StartYear)+4<A8-5,R7-X7,0)+IF(YEAR(StartYear)+5<A8-5,S7-Y7,0)),0) -> 0 | I8: =IFERROR(IF($A8="", "", MAX(0, D8+E8-C8)), 0) -> 19821.335 | J8: =IFERROR(IF($A8="", "", K7), 0) -> 540164.74 | K8: =IFERROR(IF($A8="", "", J8*(1+SuperReturn*(1-SuperTaxRate)) + (C8+AA8)*(1-SuperTaxRate) - M8), 0) -> 606304.54 | L8: =IFERROR(IF($A8="", "", B8 + AA8 + NetInvLoss), 0) -> 187976.88 | M8: =IFERROR(IF($A8="", "", IF(L8 > Div293Thresh, 0.15 * MIN(AA8, L8 - Div293Thresh), 0)), 0) -> 0 | N8: =IFERROR(IF($A8="", "", G7), 0) -> 0 | O8: =IFERROR(IF($A8="", "", N7), 0) -> 0 | P8: =IFERROR(IF($A8="", "", O7), 0) -> 0 | Q8: =IFERROR(IF($A8="", "", P7), 0) -> 0 | R8: =IFERROR(IF($A8="", "", Q7), 0) -> 0 | S8: =IFERROR(IF($A8="", "", R7), 0) -> 0 | T8: =IF($A8="","",MIN(MAX(0,F8),N8)) -> 0 | U8: =IF($A8="","",MIN(MAX(0,F8-T8),O8)) -> 0 | V8: =IF($A8="","",MIN(MAX(0,F8-T8-U8),P8)) -> 0 | W8: =IF($A8="","",MIN(MAX(0,F8-T8-U8-V8),Q8)) -> 0 | X8: =IF($A8="","",MIN(MAX(0,F8-T8-U8-V8-W8),R8)) -> 0 | Y8: =IF($A8="","",MIN(MAX(0,F8-T8-U8-V8-W8-X8),S8)) -> 0 | Z8: =IF($A8="","",IF(AND(SpousalTransfer="Yes", TransferDir="Yes", J7>=500000), F8, 0)) -> 0 | AA8: =IF($A8="","",F8-Z8) -> 19821.335 | AB8: {=IF($A8="","",TaxPayable(B8))} -> 46650.663
A9: =IF(ROW()-1 <= ProjYearsA, A8+1, "") -> 2034 | B9: =IF($A9="","",B8*(1+Inflation)) -> 172359.43 | C9: =IFERROR(IF($A9="", "", B9*SGRate), 0) -> 20683.132 | D9: =IF($A9="","",D8+IF(MOD(A9-YEAR(StartYear),CapIndexYears)=0,CapIncrement,0)) -> 40000 | E9: =IFERROR(IF($A9="", "", IF(J8>500000, 0, MAX(0, G8-H9))), 0) -> 0 | F9: =IFERROR(IF($A9="","",_xlfn.XLOOKUP($A9,PersonaA!B:B,PersonaA!Q:Q,,,-1)),0) -> 19316.868 | G9: =IFERROR(IF($A9="", "", MAX(0, D9+E9-C9-AA9)), 0) -> 19316.868 | H9: =IFERROR(IF($A9="","",IF(YEAR(StartYear)+0<A9-5,N8-T8,0)+IF(YEAR(StartYear)+1<A9-5,O8-U8,0)+IF(YEAR(StartYear)+2<A9-5,P8-V8,0)+IF(YEAR(StartYear)+3<A9-5,Q8-W8,0)+IF(YEAR(StartYear)+4<A9-5,R8-X8,0)+IF(YEAR(StartYear)+5<A9-5,S8-Y8,0)),0) -> 0 | I9: =IFERROR(IF($A9="", "", MAX(0, D9+E9-C9)), 0) -> 19316.868 | J9: =IFERROR(IF($A9="", "", K8), 0) -> 606304.54 | K9: =IFERROR(IF($A9="", "", J9*(1+SuperReturn*(1-SuperTaxRate)) + (C9+AA9)*(1-SuperTaxRate) - M9), 0) -> 659960.33 | L9: =IFERROR(IF($A9="", "", B9 + AA9 + NetInvLoss), 0) -> 172359.43 | M9: =IFERROR(IF($A9="", "", IF(L9 > Div293Thresh, 0.15 * MIN(AA9, L9 - Div293Thresh), 0)), 0) -> 0 | N9: =IFERROR(IF($A9="", "", G8), 0) -> 0 | O9: =IFERROR(IF($A9="", "", N8), 0) -> 0 | P9: =IFERROR(IF($A9="", "", O8), 0) -> 0 | Q9: =IFERROR(IF($A9="", "", P8), 0) -> 0 | R9: =IFERROR(IF($A9="", "", Q8), 0) -> 0 | S9: =IFERROR(IF($A9="", "", R8), 0) -> 0 | T9: =IF($A9="","",MIN(MAX(0,F9),N9)) -> 0 | U9: =IF($A9="","",MIN(MAX(0,F9-T9),O9)) -> 0 | V9: =IF($A9="","",MIN(MAX(0,F9-T9-U9),P9)) -> 0 | W9: =IF($A9="","",MIN(MAX(0,F9-T9-U9-V9),Q9)) -> 0 | X9: =IF($A9="","",MIN(MAX(0,F9-T9-U9-V9-W9),R9)) -> 0 | Y9: =IF($A9="","",MIN(MAX(0,F9-T9-U9-V9-W9-X9),S9)) -> 0 | Z9: =IF($A9="","",IF(AND(SpousalTransfer="Yes", TransferDir="Yes", J8>=500000), F9, 0)) -> 19316.868 | AA9: =IF($A9="","",F9-Z9) -> 0 | AB9: {=IF($A9="","",TaxPayable(B9))} -> 48290.179
A10: =IF(ROW()-1 <= ProjYearsA, A9+1, "") -> 2035 | B10: =IF($A10="","",B9*(1+Inflation)) -> 176668.42 | C10: =IFERROR(IF($A10="", "", B10*SGRate), 0) -> 21200.21 | D10: =IF($A10="","",D9+IF(MOD(A10-YEAR(StartYear),CapIndexYears)=0,CapIncrement,0)) -> 42500 | E10: =IFERROR(IF($A10="", "", IF(J9>500000, 0, MAX(0, G9-H10))), 0) -> 0 | F10: =IFERROR(IF($A10="","",_xlfn.XLOOKUP($A10,PersonaA!B:B,PersonaA!Q:Q,,,-1)),0) -> 21299.79 | G10: =IFERROR(IF($A10="", "", MAX(0, D10+E10-C10-AA10)), 0) -> 21299.79 | H10: =IFERROR(IF($A10="","",IF(YEAR(StartYear)+0<A10-5,N9-T9,0)+IF(YEAR(StartYear)+1<A10-5,O9-U9,0)+IF(YEAR(StartYear)+2<A10-5,P9-V9,0)+IF(YEAR(StartYear)+3<A10-5,Q9-W9,0)+IF(YEAR(StartYear)+4<A10-5,R9-X9,0)+IF(YEAR(StartYear)+5<A10-5,S9-Y9,0)),0) -> 0 | I10: =IFERROR(IF($A10="", "", MAX(0, D10+E10-C10)), 0) -> 21299.79 | J10: =IFERROR(IF($A10="", "", K9), 0) -> 659960.33 | K10: =IFERROR(IF($A10="", "", J10*(1+SuperReturn*(1-SuperTaxRate)) + (C10+AA10)*(1-SuperTaxRate) - M10), 0) -> 717248.15 | L10: =IFERROR(IF($A10="", "", B10 + AA10 + NetInvLoss), 0) -> 176668.42 | M10: =IFERROR(IF($A10="", "", IF(L10 > Div293Thresh, 0.15 * MIN(AA10, L10 - Div293Thresh), 0)), 0) -> 0 | N10: =IFERROR(IF($A10="", "", G9), 0) -> 19316.868 | O10: =IFERROR(IF($A10="", "", N9), 0) -> 0 | P10: =IFERROR(IF($A10="", "", O9), 0) -> 0 | Q10: =IFERROR(IF($A10="", "", P9), 0) -> 0 | R10: =IFERROR(IF($A10="", "", Q9), 0) -> 0 | S10: =IFERROR(IF($A10="", "", R9), 0) -> 0 | T10: =IF($A10="","",MIN(MAX(0,F10),N10)) -> 19316.868 | U10: =IF($A10="","",MIN(MAX(0,F10-T10),O10)) -> 0 | V10: =IF($A10="","",MIN(MAX(0,F10-T10-U10),P10)) -> 0 | W10: =IF($A10="","",MIN(MAX(0,F10-T10-U10-V10),Q10)) -> 0 | X10: =IF($A10="","",MIN(MAX(0,F10-T10-U10-V10-W10),R10)) -> 0 | Y10: =IF($A10="","",MIN(MAX(0,F10-T10-U10-V10-W10-X10),S10)) -> 0 | Z10: =IF($A10="","",IF(AND(SpousalTransfer="Yes", TransferDir="Yes", J9>=500000), F10, 0)) -> 21299.79 | AA10: =IF($A10="","",F10-Z10) -> 0 | AB10: {=IF($A10="","",TaxPayable(B10))} -> 49970.684
A11: =IF(ROW()-1 <= ProjYearsA, A10+1, "") -> 2036 | B11: =IF($A11="","",B10*(1+Inflation)) -> 181085.13 | C11: =IFERROR(IF($A11="", "", B11*SGRate), 0) -> 21730.216 | D11: =IF($A11="","",D10+IF(MOD(A11-YEAR(StartYear),CapIndexYears)=0,CapIncrement,0)) -> 42500 | E11: =IFERROR(IF($A11="", "", IF(J10>500000, 0, MAX(0, G10-H11))), 0) -> 0 | F11: =IFERROR(IF($A11="","",_xlfn.XLOOKUP($A11,PersonaA!B:B,PersonaA!Q:Q,,,-1)),0) -> 20769.784 | G11: =IFERROR(IF($A11="", "", MAX(0, D11+E11-C11-AA11)), 0) -> 20769.784 | H11: =IFERROR(IF($A11="","",IF(YEAR(StartYear)+0<A11-5,N10-T10,0)+IF(YEAR(StartYear)+1<A11-5,O10-U10,0)+IF(YEAR(StartYear)+2<A11-5,P10-V10,0)+IF(YEAR(StartYear)+3<A11-5,Q10-W10,0)+IF(YEAR(StartYear)+4<A11-5,R10-X10,0)+IF(YEAR(StartYear)+5<A11-5,S10-Y10,0)),0) -> 0 | I11: =IFERROR(IF($A11="", "", MAX(0, D11+E11-C11)), 0) -> 20769.784 | J11: =IFERROR(IF($A11="", "", K10), 0) -> 717248.15 | K11: =IFERROR(IF($A11="", "", J11*(1+SuperReturn*(1-SuperTaxRate)) + (C11+AA11)*(1-SuperTaxRate) - M11), 0) -> 778395.09 | L11: =IFERROR(IF($A11="", "", B11 + AA11 + NetInvLoss), 0) -> 181085.13 | M11: =IFERROR(IF($A11="", "", IF(L11 > Div293Thresh, 0.15 * MIN(AA11, L11 - Div293Thresh), 0)), 0) -> 0 | N11: =IFERROR(IF($A11="", "", G10), 0) -> 21299.79 | O11: =IFERROR(IF($A11="", "", N10), 0) -> 19316.868 | P11: =IFERROR(IF($A11="", "", O10), 0) -> 0 | Q11: =IFERROR(IF($A11="", "", P10), 0) -> 0 | R11: =IFERROR(IF($A11="", "", Q10), 0) -> 0 | S11: =IFERROR(IF($A11="", "", R10), 0) -> 0 | T11: =IF($A11="","",MIN(MAX(0,F11),N11)) -> 20769.784 | U11: =IF($A11="","",MIN(MAX(0,F11-T11),O11)) -> 0 | V11: =IF($A11="","",MIN(MAX(0,F11-T11-U11),P11)) -> 0 | W11: =IF($A11="","",MIN(MAX(0,F11-T11-U11-V11),Q11)) -> 0 | X11: =IF($A11="","",MIN(MAX(0,F11-T11-U11-V11-W11),R11)) -> 0 | Y11: =IF($A11="","",MIN(MAX(0,F11-T11-U11-V11-W11-X11),S11)) -> 0 | Z11: =IF($A11="","",IF(AND(SpousalTransfer="Yes", TransferDir="Yes", J10>=500000), F11, 0)) -> 20769.784 | AA11: =IF($A11="","",F11-Z11) -> 0 | AB11: {=IF($A11="","",TaxPayable(B11))} -> 51693.201
A12: =IF(ROW()-1 <= ProjYearsA, A11+1, "") -> 2037 | B12: =IF($A12="","",B11*(1+Inflation)) -> 185612.26 | C12: =IFERROR(IF($A12="", "", B12*SGRate), 0) -> 22273.471 | D12: =IF($A12="","",D11+IF(MOD(A12-YEAR(StartYear),CapIndexYears)=0,CapIncrement,0)) -> 45000 | E12: =IFERROR(IF($A12="", "", IF(J11>500000, 0, MAX(0, G11-H12))), 0) -> 0 | F12: =IFERROR(IF($A12="","",_xlfn.XLOOKUP($A12,PersonaA!B:B,PersonaA!Q:Q,,,-1)),0) -> 22726.529 | G12: =IFERROR(IF($A12="", "", MAX(0, D12+E12-C12-AA12)), 0) -> 22726.529 | H12: =IFERROR(IF($A12="","",IF(YEAR(StartYear)+0<A12-5,N11-T11,0)+IF(YEAR(StartYear)+1<A12-5,O11-U11,0)+IF(YEAR(StartYear)+2<A12-5,P11-V11,0)+IF(YEAR(StartYear)+3<A12-5,Q11-W11,0)+IF(YEAR(StartYear)+4<A12-5,R11-X11,0)+IF(YEAR(StartYear)+5<A12-5,S11-Y11,0)),0) -> 19846.873 | I12: =IFERROR(IF($A12="", "", MAX(0, D12+E12-C12)), 0) -> 22726.529 | J12: =IFERROR(IF($A12="", "", K11), 0) -> 778395.09 | K12: =IFERROR(IF($A12="", "", J12*(1+SuperReturn*(1-SuperTaxRate)) + (C12+AA12)*(1-SuperTaxRate) - M12), 0) -> 843642.05 | L12: =IFERROR(IF($A12="", "", B12 + AA12 + NetInvLoss), 0) -> 185612.26 | M12: =IFERROR(IF($A12="", "", IF(L12 > Div293Thresh, 0.15 * MIN(AA12, L12 - Div293Thresh), 0)), 0) -> 0 | N12: =IFERROR(IF($A12="", "", G11), 0) -> 20769.784 | O12: =IFERROR(IF($A12="", "", N11), 0) -> 21299.79 | P12: =IFERROR(IF($A12="", "", O11), 0) -> 19316.868 | Q12: =IFERROR(IF($A12="", "", P11), 0) -> 0 | R12: =IFERROR(IF($A12="", "", Q11), 0) -> 0 | S12: =IFERROR(IF($A12="", "", R11), 0) -> 0 | T12: =IF($A12="","",MIN(MAX(0,F12),N12)) -> 20769.784 | U12: =IF($A12="","",MIN(MAX(0,F12-T12),O12)) -> 1956.7446 | V12: =IF($A12="","",MIN(MAX(0,F12-T12-U12),P12)) -> 0 | W12: =IF($A12="","",MIN(MAX(0,F12-T12-U12-V12),Q12)) -> 0 | X12: =IF($A12="","",MIN(MAX(0,F12-T12-U12-V12-W12),R12)) -> 0 | Y12: =IF($A12="","",MIN(MAX(0,F12-T12-U12-V12-W12-X12),S12)) -> 0 | Z12: =IF($A12="","",IF(AND(SpousalTransfer="Yes", TransferDir="Yes", J11>=500000), F12, 0)) -> 22726.529 | AA12: =IF($A12="","",F12-Z12) -> 0 | AB12: {=IF($A12="","",TaxPayable(B12))} -> 53458.781
A13: =IF(ROW()-1 <= ProjYearsA, A12+1, "") -> 2038 | B13: =IF($A13="","",B12*(1+Inflation)) -> 190252.57 | C13: =IFERROR(IF($A13="", "", B13*SGRate), 0) -> 22830.308 | D13: =IF($A13="","",D12+IF(MOD(A13-YEAR(StartYear),CapIndexYears)=0,CapIncrement,0)) -> 45000 | E13: =IFERROR(IF($A13="", "", IF(J12>500000, 0, MAX(0, G12-H13))), 0) -> 0 | F13: =IFERROR(IF($A13="","",_xlfn.XLOOKUP($A13,PersonaA!B:B,PersonaA!Q:Q,,,-1)),0) -> 22169.692 | G13: =IFERROR(IF($A13="", "", MAX(0, D13+E13-C13-AA13)), 0) -> 22169.692 | H13: =IFERROR(IF($A13="","",IF(YEAR(StartYear)+0<A13-5,N12-T12,0)+IF(YEAR(StartYear)+1<A13-5,O12-U12,0)+IF(YEAR(StartYear)+2<A13-5,P12-V12,0)+IF(YEAR(StartYear)+3<A13-5,Q12-W12,0)+IF(YEAR(StartYear)+4<A13-5,R12-X12,0)+IF(YEAR(StartYear)+5<A13-5,S12-Y12,0)),0) -> 38659.913 | I13: =IFERROR(IF($A13="", "", MAX(0, D13+E13-C13)), 0) -> 22169.692 | J13: =IFERROR(IF($A13="", "", K12), 0) -> 843642.05 | K13: =IFERROR(IF($A13="", "", J13*(1+SuperReturn*(1-SuperTaxRate)) + (C13+AA13)*(1-SuperTaxRate) - M13), 0) -> 913244.52 | L13: =IFERROR(IF($A13="", "", B13 + AA13 + NetInvLoss), 0) -> 190252.57 | M13: =IFERROR(IF($A13="", "", IF(L13 > Div293Thresh, 0.15 * MIN(AA13, L13 - Div293Thresh), 0)), 0) -> 0 | N13: =IFERROR(IF($A13="", "", G12), 0) -> 22726.529 | O13: =IFERROR(IF($A13="", "", N12), 0) -> 20769.784 | P13: =IFERROR(IF($A13="", "", O12), 0) -> 21299.79 | Q13: =IFERROR(IF($A13="", "", P12), 0) -> 19316.868 | R13: =IFERROR(IF($A13="", "", Q12), 0) -> 0 | S13: =IFERROR(IF($A13="", "", R12), 0) -> 0 | T13: =IF($A13="","",MIN(MAX(0,F13),N13)) -> 22169.692 | U13: =IF($A13="","",MIN(MAX(0,F13-T13),O13)) -> 0 | V13: =IF($A13="","",MIN(MAX(0,F13-T13-U13),P13)) -> 0 | W13: =IF($A13="","",MIN(MAX(0,F13-T13-U13-V13),Q13)) -> 0 | X13: =IF($A13="","",MIN(MAX(0,F13-T13-U13-V13-W13),R13)) -> 0 | Y13: =IF($A13="","",MIN(MAX(0,F13-T13-U13-V13-W13-X13),S13)) -> 0 | Z13: =IF($A13="","",IF(AND(SpousalTransfer="Yes", TransferDir="Yes", J12>=500000), F13, 0)) -> 22169.692 | AA13: =IF($A13="","",F13-Z13) -> 0 | AB13: {=IF($A13="","",TaxPayable(B13))} -> 55288.706
A14: =IF(ROW()-1 <= ProjYearsA, A13+1, "") | B14: =IF($A14="","",B13*(1+Inflation)) | C14: =IFERROR(IF($A14="", "", B14*SGRate), 0) | D14: =IF($A14="","",D13+IF(MOD(A14-YEAR(StartYear),CapIndexYears)=0,CapIncrement,0)) | E14: =IFERROR(IF($A14="", "", IF(J13>500000, 0, MAX(0, G13-H14))), 0) | F14: =IFERROR(IF($A14="","",_xlfn.XLOOKUP($A14,PersonaA!B:B,PersonaA!Q:Q,,,-1)),0) | G14: =IFERROR(IF($A14="", "", MAX(0, D14+E14-C14-AA14)), 0) | H14: =IFERROR(IF($A14="","",IF(YEAR(StartYear)+0<A14-5,N13-T13,0)+IF(YEAR(StartYear)+1<A14-5,O13-U13,0)+IF(YEAR(StartYear)+2<A14-5,P13-V13,0)+IF(YEAR(StartYear)+3<A14-5,Q13-W13,0)+IF(YEAR(StartYear)+4<A14-5,R13-X13,0)+IF(YEAR(StartYear)+5<A14-5,S13-Y13,0)),0) | I14: =IFERROR(IF($A14="", "", MAX(0, D14+E14-C14)), 0) | J14: =IFERROR(IF($A14="", "", K13), 0) | K14: =IFERROR(IF($A14="", "", J14*(1+SuperReturn*(1-SuperTaxRate)) + (C14+AA14)*(1-SuperTaxRate) - M14), 0) | L14: =IFERROR(IF($A14="", "", B14 + AA14 + NetInvLoss), 0) | M14: =IFERROR(IF($A14="", "", IF(L14 > Div293Thresh, 0.15 * MIN(AA14, L14 - Div293Thresh), 0)), 0) | N14: =IFERROR(IF($A14="", "", G13), 0) | O14: =IFERROR(IF($A14="", "", N13), 0) | P14: =IFERROR(IF($A14="", "", O13), 0) | Q14: =IFERROR(IF($A14="", "", P13), 0) | R14: =IFERROR(IF($A14="", "", Q13), 0) | S14: =IFERROR(IF($A14="", "", R13), 0) | T14: =IF($A14="","",MIN(MAX(0,F14),N14)) | U14: =IF($A14="","",MIN(MAX(0,F14-T14),O14)) | V14: =IF($A14="","",MIN(MAX(0,F14-T14-U14),P14)) | W14: =IF($A14="","",MIN(MAX(0,F14-T14-U14-V14),Q14)) | X14: =IF($A14="","",MIN(MAX(0,F14-T14-U14-V14-W14),R14)) | Y14: =IF($A14="","",MIN(MAX(0,F14-T14-U14-V14-W14-X14),S14)) | Z14: =IF($A14="","",IF(AND(SpousalTransfer="Yes", TransferDir="Yes", J13>=500000), F14, 0)) | AA14: =IF($A14="","",F14-Z14)
